Workbook

Sheet Strategy comparison
B2: ST Capital Gains | E2: Strategy Comparison
F3: No Planning | G3: Film | H3: Solar | I3: LCD | J3: Solar & Charitable | K3: LEAP | L3: LEAP & Charitable
B4: Filing Status | C4: Married-Joint | E4: Fed Ordinary Income Tax | F4: ='No planning'!C19 -> 81195.42 | G4: =Film!C22 -> 11599.88 | H4: =MIN(Solar!C20, F4) -> 0 | I4: =Charitable!C22 -> 33423.66 | J4: =MIN('Solar & Charitable'!C25,'Solar & Charitable'!C58) -> 0 | K4: =LEAP!C28 -> 113167.1 | L4: ='LEAP & Charitable'!C63 -> 33423.66
B5: W2 | C5: 400000 | E5: Fed LTCG Tax | F5: ='No planning'!C20 -> 0 | G5: =Film!C24 -> 0 | H5: =MIN(MAX(Solar!C20 - H4, 0), F5) -> 0 | I5: =Charitable!C24 -> 0 | J5: =MIN(MAX('Solar & Charitable'!C58-'Strategy comparison'!J4,0),'Solar & Charitable'!C27) -> 0 | K5: =LEAP!J28 -> 0 | L5: ='LEAP & Charitable'!C65 -> 0
B6: Business Income | E6: State Tax | F6: ='No planning'!I42 -> 12000 | G6: =Film!I42 -> 3024 | H6: =Solar!J42 -> 11058.167 | I6: =Charitable!H42 -> 12000 | J6: ='Solar & Charitable'!J42 -> 11017.89 | K6: =LEAP!C29 -> 12000 | L6: ='LEAP & Charitable'!C64 -> 12000
B7: ST Capital Gains | E7: Strategy Contribution | F7: 0 | G7: =Film!D14 -> 62989.474 | H7: =Solar!C18 -> 70591.824 | I7: =Charitable!D14 -> 40000 | J7: ='Solar & Charitable'!D17+'Solar & Charitable'!C49 -> 73022.32 | K7: =LEAP!D14+LEAP!E14+LEAP!D12+LEAP!E12 -> -17640 | L7: ='LEAP & Charitable'!C78-L9 -> 40000
B8: LT Capital Gains | E8: Investment Account | F8: 0 | G8: 0 | H8: 0 | I8: 0 | J8: 0 | K8: =LEAP!D20+LEAP!E20 -> -7560 | L8: ='LEAP & Charitable'!C79 -> 0
B9: Interest | E9: Membership Fee | F9: 0 | G9: =Film!D16 -> 0 | H9: =C12 -> 0 | I9: =C12 -> 0 | J9: =C12 -> 0 | K9: =C12 -> 0 | L9: =C12 -> 0
B10: Qualified Dividends | E10: Total Cash Outlay | F10: =SUM(F4:F9) -> 93195.42 | G10: =SUM(G4:G9) -> 77613.354 | H10: =SUM(H4:H9) -> 81649.991 | I10: =SUM(I4:I9) -> 85423.66 | J10: =SUM(J4:J9) -> 84040.21 | K10: =SUM(K4:K7)+K9 -> 107527.1 | L10: =SUM(L4:L9) -> 85423.66
B11: Nonqualified Dividends | E11: Savings | F11: 0 | G11: =$F10-G10 -> 15582.066 | H11: =$F10-H10 -> 11545.429 | I11: =$F10-I10 -> 7771.76 | J11: =$F10-J10 -> 9155.2102 | K11: =$F10-K10 -> -14331.68 | L11: =F10-L10+L8 -> 7771.76
B12: Consulting Fee | E12: Effective Tax Rate | F12: =($F$10-F11)/'No planning'!$C$15 -> 0.23298855 | G12: =($F$10-G11)/'No planning'!$C$15 -> 0.19403338 | H12: =($F$10-H11)/'No planning'!$C$15 -> 0.20412498 | I12: =($F$10-I11)/'No planning'!$C$15 -> 0.21355915 | J12: =($F$10-J11)/'No planning'!$C$15 -> 0.21010052 | K12: =K10/'No planning'!$C$15 -> 0.26881775 | L12: =($F$10-L11)/'No planning'!$C$15 -> 0.21355915
G15: Manual Inputs
G16: Film | H16: Solar | I16: Charitable | J16: Solar & Charitable | K16: LEAP | L16: LEAP & Charitable
G17: Income Offset | H17: Equity Contribution | I17: Charitable Donation | J17: Charitable Donation | K17: SOP NEG K1 - Biz. Income | L17: SOP NEG K1 - Biz. Income
G18: =SUM(C5:C11)-100800 -> 299200 | K18: =C6-100800 -> -100800
J19: Equity Contribution | K19: SOP NEG K1 - LTCG | L19: SOP NEG K1 - LTCG
L21: Charitable Donation

Sheet DB comparison
B2: DB Contribution | G2: Manual Inputs
G3: Film & DB | H3: Solar & DB | I3: Charitable & DB | J3: Solar & Charitable & DB | K3: LEAP & DB | L3: LEAP & Charitable & DB
G4: Income Offset | H4: Equity Contribution | I4: Charitable Donation | J4: Charitable Donation | K4: SOP NEG K1 - Biz. Income | L4: SOP NEG K1 - Biz. Income
J6: Equity Contribution | K6: SOP NEG K1 - LTCG | L6: SOP NEG K1 - LTCG
L8: Charitable Donation
E11: No DB Contribution
F12: No Planning | G12: Film | H12: Solar | I12: Charitable | J12: Solar & Charitable | K12: LEAP | L12: LEAP & Charitable
E13: Fed Ordinary Income Tax | F13: ='No planning'!C19 -> 81195.42 | G13: =Film!C22 -> 11599.88 | H13: =MIN(Solar!C20, F13) -> 0 | I13: =Charitable!C22 -> 33423.66 | J13: =MIN('Solar & Charitable'!C25,'Solar & Charitable'!C58) -> 0 | K13: =LEAP!C28 -> 113167.1 | L13: ='LEAP & Charitable'!C63 -> 33423.66
E14: Fed LTCG Tax | F14: ='No planning'!C20 -> 0 | G14: =Film!C24 -> 0 | H14: =MIN(MAX(Solar!C20 - H13, 0), F14) -> 0 | I14: =Charitable!C24 -> 0 | J14: =MIN(MAX('Solar & Charitable'!C58-'Strategy comparison'!J4,0),'Solar & Charitable'!C27) -> 0 | K14: =LEAP!J28 -> 0 | L14: ='LEAP & Charitable'!C65 -> 0
E15: State Tax | F15: ='No planning'!I42 -> 12000 | G15: =Film!I42 -> 3024 | H15: =Solar!J42 -> 11059.732 | I15: =Charitable!H42 -> 12000 | J15: ='Solar & Charitable'!J42 -> 11017.77 | K15: =LEAP!C29 -> 12000 | L15: ='LEAP & Charitable'!C64 -> 12000
E16: Strategy Contribution | F16: 0 | G16: =Film!D14 -> 62989.474 | H16: =Solar!C18 -> 70583.134 | I16: =Charitable!D14 -> 40000 | J16: ='Solar & Charitable'!D17+'Solar & Charitable'!C49 -> 73013.342 | K16: =LEAP!D14+LEAP!E14+LEAP!D12+LEAP!E12 -> -17640 | L16: ='LEAP & Charitable'!C78-L18 -> 40000
E17: Investment Account | F17: 0 | G17: 0 | H17: 0 | I17: 0 | J17: 0 | K17: =LEAP!D20+LEAP!E20 -> -7560 | L17: ='LEAP & Charitable'!C79 -> 0
E18: Membership Fee | F18: 0 | G18: ='Strategy comparison'!$C$12 -> 0 | H18: ='Strategy comparison'!$C$12 -> 0 | I18: ='Strategy comparison'!$C$12 -> 0 | J18: ='Strategy comparison'!$C$12 -> 0 | K18: ='Strategy comparison'!$C$12 -> 0 | L18: ='Strategy comparison'!$C$12 -> 0
E19: Total Cash Outlay | F19: =SUM(F13:F18) -> 93195.42 | G19: =SUM(G13:G18) -> 77613.354 | H19: =SUM(H13:H18) -> 81642.866 | I19: =SUM(I13:I18) -> 85423.66 | J19: =SUM(J13:J18) -> 84031.112 | K19: =SUM(K13:K18) -> 99967.1 | L19: =SUM(L13:L18) -> 85423.66
E20: Savings | F20: 0 | G20: =$F19-G19 -> 15582.066 | H20: =$F19-H19 -> 11552.554 | I20: =$F19-I19 -> 7771.76 | J20: =$F19-J19 -> 9164.3082 | K20: =$F19-K19+K17 -> -14331.68 | L20: =F19-L19+L17 -> 7771.76
E21: Effective Tax Rate | F21: =($F$19-F20)/'No planning'!$C$15 -> 0.23298855 | G21: =($F$19-G20)/'No planning'!$C$15 -> 0.19403338 | H21: =($F$19-H20)/'No planning'!$C$15 -> 0.20410716 | I21: =($F$19-I20)/'No planning'!$C$15 -> 0.21355915 | J21: =($F$19-J20)/'No planning'!$C$15 -> 0.21007778 | K21: =($F$19-K20)/'No planning'!$C$15 -> 0.26881775 | L21: =($F$19-L20)/'No planning'!$C$15 -> 0.21355915
E23: DB Contribution
F24: DB Only | G24: Film & DB | H24: Solar & DB | I24: Charitable & DB | J24: Solar & Charitable & DB | K24: LEAP & DB | L24: LEAP & Charitable & DB
E25: DB Contribution | F25: ='DB comparison'!$C$2 -> 0 | G25: ='DB comparison'!$C$2 -> 0 | H25: ='DB comparison'!$C$2 -> 0 | I25: ='DB comparison'!$C$2 -> 0 | J25: ='DB comparison'!$C$2 -> 0 | K25: ='DB comparison'!$C$2 -> 0 | L25: ='DB comparison'!$C$2 -> 0
E26: Fed Ordinary Income Tax | F26: ='DB Only'!C14 -> 81195.42 | G26: ='Film & DB'!C22 -> 0 | H26: =MIN('Solar & DB'!C20, F26) -> 0 | I26: ='Charitable & DB'!C22 -> 33423.66 | J26: =MIN('Solar & Charitable & DB'!C25,'Solar & Charitable & DB'!C58) -> 0 | K26: ='LEAP & DB'!C28 -> 81195.42 | L26: ='LEAP & Charitable & DB'!C63 -> 33423.66
E27: Fed LTCG Tax | F27: ='DB Only'!C15 -> 0 | G27: ='Film & DB'!C24 -> 0 | H27: =MIN(MAX('Solar & DB'!C20 - H26, 0), F27) -> 0 | I27: ='Charitable & DB'!C24 -> 0 | J27: =MIN(MAX('Solar & Charitable & DB'!C58-'DB comparison'!J26,0),'Solar & Charitable & DB'!C27) -> 0 | K27: ='LEAP & DB'!C30 -> 0 | L27: ='LEAP & Charitable & DB'!C65 -> 0
E28: State Tax | F28: ='DB Only'!C16 -> 12000 | G28: ='Film & DB'!C23 -> 0 | H28: ='Solar & DB'!J42 -> 11059.732 | I28: ='Charitable & DB'!C23 -> 12000 | J28: ='Solar & Charitable & DB'!J42 -> 11017.796 | K28: ='LEAP & DB'!J42 -> 12000 | L28: ='LEAP & Charitable & DB'!C64 -> 12000
E29: Strategy Contribution | F29: 0 | G29: ='Film & DB'!D14 -> 84210.526 | H29: ='Solar & DB'!C18 -> 70583.134 | I29: ='Charitable & DB'!D14 -> 40000 | J29: ='Solar & Charitable & DB'!D17+'Solar & Charitable & DB'!C49 -> 73029.372 | K29: ='LEAP & DB'!D14+'LEAP & DB'!E14+'LEAP & DB'!D12+'LEAP & DB'!E12 -> 0 | L29: ='LEAP & Charitable & DB'!C78-L31 -> 40000
E30: Investment Account | F30: 0 | G30: 0 | H30: 0 | I30: 0 | J30: 0 | K30: ='LEAP & DB'!D20+'LEAP & DB'!E20 -> 0 | L30: ='LEAP & Charitable & DB'!C79 -> 0
E31: Planning Fee | F31: ='Strategy comparison'!$C$12 -> 0 | G31: ='Strategy comparison'!$C$12 -> 0 | H31: ='Strategy comparison'!$C$12 -> 0 | I31: ='Strategy comparison'!$C$12 -> 0 | J31: ='Strategy comparison'!$C$12 -> 0 | K31: ='Strategy comparison'!$C$12 -> 0 | L31: ='Strategy comparison'!$C$12 -> 0
E32: Total Cash Outlay | F32: =SUM(F25:F31) -> 93195.42 | G32: =SUM(G25:G31) -> 84210.526 | H32: =SUM(H25:H31) -> 81642.866 | I32: =SUM(I25:I31) -> 85423.66 | J32: =SUM(J25:J31) -> 84047.168 | K32: =SUM(K25:K31) -> 93195.42 | L32: =SUM(L25:L31) -> 85423.66
E33: Savings | F33: ='Strategy comparison'!$F$10-F32+F25+F30 -> 0 | G33: ='Strategy comparison'!$F$10-G32+G25+G30 -> 8984.8937 | H33: ='Strategy comparison'!$F$10-H32+H25+H30 -> 11552.554 | I33: ='Strategy comparison'!$F$10-I32+I25+I30 -> 7771.76 | J33: ='Strategy comparison'!$F$10-J32+J25+J30 -> 9148.2522 | K33: ='Strategy comparison'!$F$10-K32+K25+K30 -> 0 | L33: ='Strategy comparison'!$F$10-L32+L25+L30 -> 7771.76
E34: Effective Tax Rate | F34: =('Strategy comparison'!$F$10-F33)/'No planning'!$C$15 -> 0.23298855 | G34: =('Strategy comparison'!$F$10-G33)/'No planning'!$C$15 -> 0.21052632 | H34: =('Strategy comparison'!$F$10-H33)/'No planning'!$C$15 -> 0.20410716 | I34: =('Strategy comparison'!$F$10-I33)/'No planning'!$C$15 -> 0.21355915 | J34: =('Strategy comparison'!$F$10-J33)/'No planning'!$C$15 -> 0.21011792 | K34: =('Strategy comparison'!$F$10-K33)/'No planning'!$C$15 -> 0.23298855 | L34: =('Strategy comparison'!$F$10-L33)/'No planning'!$C$15 -> 0.21355915
E36: Net Savings
F37: No Strategy | G37: Film | H37: Solar | I37: Charitable | J37: Solar & Charitable | K37: LEAP | L37: LEAP & Charitable
E38: No DB Plan | F38: ='Strategy comparison'!F11 -> 0 | G38: ='Strategy comparison'!G11 -> 15582.066 | H38: ='Strategy comparison'!H11 -> 11552.554 | I38: ='Strategy comparison'!I11 -> 7771.76 | J38: ='Strategy comparison'!J11 -> 9164.3082 | K38: ='Strategy comparison'!K11 -> -14331.68 | L38: ='Strategy comparison'!L11 -> 7771.76
E39: DB Plan | F39: ='DB comparison'!F33 -> 0 | G39: ='DB comparison'!G33 -> 8984.8937 | H39: ='DB comparison'!H33 -> 11552.554 | I39: ='DB comparison'!I33 -> 7771.76 | J39: ='DB comparison'!J33 -> 9148.2522 | K39: ='DB comparison'!K33 -> 0 | L39: ='DB comparison'!L33 -> 7771.76
E41: Effective Tax Rate
F42: No Strategy | G42: Film | H42: Solar | I42: Charitable | J42: Solar & Charitable | K42: LEAP | L42: LEAP & Charitable
E43: No DB Plan | F43: ='Strategy comparison'!F12 -> 0.23298855 | G43: ='Strategy comparison'!G12 -> 0.19403338 | H43: ='Strategy comparison'!H12 -> 0.20410716 | I43: ='Strategy comparison'!I12 -> 0.21355915 | J43: ='Strategy comparison'!J12 -> 0.21007778 | K43: ='Strategy comparison'!K12 -> 0.26881775 | L43: ='Strategy comparison'!L12 -> 0.21355915
E44: DB Plan | F44: ='DB comparison'!F34 -> 0.23298855 | G44: ='DB comparison'!G34 -> 0.21052632 | H44: ='DB comparison'!H34 -> 0.20410716 | I44: ='DB comparison'!I34 -> 0.21355915 | J44: ='DB comparison'!J34 -> 0.21011792 | K44: ='DB comparison'!K34 -> 0.23298855 | L44: ='DB comparison'!L34 -> 0.21355915

Sheet Roth comparison
S1: Age | T1: Roth IRA (Post Strategy) Income | U1: Roth IRA (No Strategy) Income | V1: Traditional IRA Income
B2: Roth conversion amount | C2: 450000 | G2: Manual Inputs | N2: Roth Conversion Tax w/ Savings | O2: Roth conversion tax | P2: PV Traditional IRA RMD Tax | S2: =C3 -> 65 | T2: =IFERROR(_xlfn.XLOOKUP(S2,'RMD Simulation'!AL:AL,'RMD Simulation'!AS:AS),"") -> 13235.941 | U2: =IFERROR(_xlfn.XLOOKUP(S2,'RMD Simulation'!AA:AA,'RMD Simulation'!AH:AH),"") -> 11241.302 | V2: =IFERROR(_xlfn.XLOOKUP(S2,'RMD Simulation'!P:P,'RMD Simulation'!W:W),"") -> 11700
B3: Current Age | C3: 65 | G3: Film & Roth | H3: Solar & Roth | I3: Charitable & Roth | J3: Solar & Charitable & Roth | K3: LEAP & Roth | L3: LEAP & Charitable & Roth | N3: =O3-C13 -> 119101.47 | O3: ='RMD Simulation'!B14 -> 168967.46 | P3: ='RMD Simulation'!B22 -> 151200 | S3: =IFERROR(IF(S2+1>99,"",S2+1),"") -> 66 | T3: =IFERROR(_xlfn.XLOOKUP(S3,'RMD Simulation'!AL:AL,'RMD Simulation'!AS:AS),"") -> 13595.959 | U3: =IFERROR(_xlfn.XLOOKUP(S3,'RMD Simulation'!AA:AA,'RMD Simulation'!AH:AH),"") -> 11547.065 | V3: =IFERROR(_xlfn.XLOOKUP(S3,'RMD Simulation'!P:P,'RMD Simulation'!W:W),"") -> 12018.24
B4: Retirement age | C4: 65 | G4: Income Offset | H4: Equity Contribution | I4: Charitable Donation | J4: Charitable Donation | K4: SOP NEG K1 - Biz. Income | L4: SOP NEG K1 - Biz. Income | N4: Roth IRA (Post Strategy) at 100 | O4: Roth IRA (No Strategy) at 100 | P4: Traditional IRA at 100 (post tax) | S4: =IFERROR(IF(S3+1>99,"",S3+1),"") -> 67 | T4: =IFERROR(_xlfn.XLOOKUP(S4,'RMD Simulation'!AL:AL,'RMD Simulation'!AS:AS),"") -> 13965.769 | U4: =IFERROR(_xlfn.XLOOKUP(S4,'RMD Simulation'!AA:AA,'RMD Simulation'!AH:AH),"") -> 11861.145 | V4: =IFERROR(_xlfn.XLOOKUP(S4,'RMD Simulation'!P:P,'RMD Simulation'!W:W),"") -> 12345.136
B5: Minimum withdrawal rate | C5: 0.04 | N5: ='RMD Simulation'!AO68 -> 304538.76 | O5: ='RMD Simulation'!AH68 -> 258645.16 | P5: ='RMD Simulation'!W68 -> 269199.1 | S5: =IFERROR(IF(S4+1>99,"",S4+1),"") -> 68 | T5: =IFERROR(_xlfn.XLOOKUP(S5,'RMD Simulation'!AL:AL,'RMD Simulation'!AS:AS),"") -> 14345.638 | U5: =IFERROR(_xlfn.XLOOKUP(S5,'RMD Simulation'!AA:AA,'RMD Simulation'!AH:AH),"") -> 12183.768 | V5: =IFERROR(_xlfn.XLOOKUP(S5,'RMD Simulation'!P:P,'RMD Simulation'!W:W),"") -> 12680.924
B6: Current tax rate (federal + state) | C6: ='RMD Simulation'!B15 -> 0.37548324 | J6: Equity Contribution | K6: SOP NEG K1 - LTCG | L6: SOP NEG K1 - LTCG | S6: =IFERROR(IF(S5+1>99,"",S5+1),"") -> 69 | T6: =IFERROR(_xlfn.XLOOKUP(S6,'RMD Simulation'!AL:AL,'RMD Simulation'!AS:AS),"") -> 14735.839 | U6: =IFERROR(_xlfn.XLOOKUP(S6,'RMD Simulation'!AA:AA,'RMD Simulation'!AH:AH),"") -> 12515.167 | V6: =IFERROR(_xlfn.XLOOKUP(S6,'RMD Simulation'!P:P,'RMD Simulation'!W:W),"") -> 13025.845
B7: Input: Projected tax rate (federal + state) | C7: 0.35 | S7: =IFERROR(IF(S6+1>99,"",S6+1),"") -> 70 | T7: =IFERROR(_xlfn.XLOOKUP(S7,'RMD Simulation'!AL:AL,'RMD Simulation'!AS:AS),"") -> 15136.654 | U7: =IFERROR(_xlfn.XLOOKUP(S7,'RMD Simulation'!AA:AA,'RMD Simulation'!AH:AH),"") -> 12855.579 | V7: =IFERROR(_xlfn.XLOOKUP(S7,'RMD Simulation'!P:P,'RMD Simulation'!W:W),"") -> 13380.148
B8: Projected tax rate (federal + state) | C8: =IF(C7="",C6,C7) -> 0.35 | L8: Charitable Donation | S8: =IFERROR(IF(S7+1>99,"",S7+1),"") -> 71 | T8: =IFERROR(_xlfn.XLOOKUP(S8,'RMD Simulation'!AL:AL,'RMD Simulation'!AS:AS),"") -> 15548.371 | U8: =IFERROR(_xlfn.XLOOKUP(S8,'RMD Simulation'!AA:AA,'RMD Simulation'!AH:AH),"") -> 13205.251 | V8: =IFERROR(_xlfn.XLOOKUP(S8,'RMD Simulation'!P:P,'RMD Simulation'!W:W),"") -> 13744.088
B9: Discount rate | C9: 0.07 | S9: =IFERROR(IF(S8+1>99,"",S8+1),"") -> 72 | T9: =IFERROR(_xlfn.XLOOKUP(S9,'RMD Simulation'!AL:AL,'RMD Simulation'!AS:AS),"") -> 15971.286 | U9: =IFERROR(_xlfn.XLOOKUP(S9,'RMD Simulation'!AA:AA,'RMD Simulation'!AH:AH),"") -> 13564.434 | V9: =IFERROR(_xlfn.XLOOKUP(S9,'RMD Simulation'!P:P,'RMD Simulation'!W:W),"") -> 14117.927
S10: =IFERROR(IF(S9+1>99,"",S9+1),"") -> 73 | T10: =IFERROR(_xlfn.XLOOKUP(S10,'RMD Simulation'!AL:AL,'RMD Simulation'!AS:AS),"") -> 16405.705 | U10: =IFERROR(_xlfn.XLOOKUP(S10,'RMD Simulation'!AA:AA,'RMD Simulation'!AH:AH),"") -> 13933.387 | V10: =IFERROR(_xlfn.XLOOKUP(S10,'RMD Simulation'!P:P,'RMD Simulation'!W:W),"") -> 14501.935
B11: Strategy Input | E11: RMD (No conversion) | S11: =IFERROR(IF(S10+1>99,"",S10+1),"") -> 74 | T11: =IFERROR(_xlfn.XLOOKUP(S11,'RMD Simulation'!AL:AL,'RMD Simulation'!AS:AS),"") -> 16851.941 | U11: =IFERROR(_xlfn.XLOOKUP(S11,'RMD Simulation'!AA:AA,'RMD Simulation'!AH:AH),"") -> 14312.375 | V11: =IFERROR(_xlfn.XLOOKUP(S11,'RMD Simulation'!P:P,'RMD Simulation'!W:W),"") -> 14896.387
B12: Strategy Used | C12: =IF(C11="",_xlfn.XLOOKUP(MAX(F42:L42),F42:L42,F40:L40),C11) -> Film | F12: No Planning | G12: Film | H12: Solar | I12: Charitable | J12: Solar & Charitable | K12: LEAP | L12: LEAP & Charitable | S12: =IFERROR(IF(S11+1>99,"",S11+1),"") -> 75 | T12: =IFERROR(_xlfn.XLOOKUP(S12,'RMD Simulation'!AL:AL,'RMD Simulation'!AS:AS),"") -> 17591.782 | U12: =IFERROR(_xlfn.XLOOKUP(S12,'RMD Simulation'!AA:AA,'RMD Simulation'!AH:AH),"") -> 14940.723 | V12: =IFERROR(_xlfn.XLOOKUP(S12,'RMD Simulation'!P:P,'RMD Simulation'!W:W),"") -> 15550.375
B13: Savings | C13: =_xlfn.XLOOKUP(C12,F40:L40,F43:L43) -> 49865.985 | E13: Fed Ordinary Income Tax | F13: ='No planning'!C19 -> 81195.42 | G13: =Film!C22 -> 11599.88 | H13: =MIN(Solar!C20, F13) -> 0 | I13: =Charitable!C22 -> 33423.66 | J13: =MIN('Solar & Charitable'!C25,'Solar & Charitable'!C58) -> 0 | K13: =LEAP!C28 -> 113167.1 | L13: ='LEAP & Charitable'!C63 -> 33423.66 | S13: =IFERROR(IF(S12+1>99,"",S12+1),"") -> 76 | T13: =IFERROR(_xlfn.XLOOKUP(S13,'RMD Simulation'!AL:AL,'RMD Simulation'!AS:AS),"") -> 18743.784 | U13: =IFERROR(_xlfn.XLOOKUP(S13,'RMD Simulation'!AA:AA,'RMD Simulation'!AH:AH),"") -> 15919.12 | V13: =IFERROR(_xlfn.XLOOKUP(S13,'RMD Simulation'!P:P,'RMD Simulation'!W:W),"") -> 16568.695
E14: PV RMD Tax | F14: ='RMD Simulation'!$B$22 -> 151200 | G14: ='RMD Simulation'!$B$22 -> 151200 | H14: ='RMD Simulation'!$B$22 -> 151200 | I14: ='RMD Simulation'!$B$22 -> 151200 | J14: ='RMD Simulation'!$B$22 -> 151200 | K14: ='RMD Simulation'!$B$22 -> 151200 | L14: ='RMD Simulation'!$B$22 -> 151200 | S14: =IFERROR(IF(S13+1>99,"",S13+1),"") -> 77 | T14: =IFERROR(_xlfn.XLOOKUP(S14,'RMD Simulation'!AL:AL,'RMD Simulation'!AS:AS),"") -> 19880.688 | U14: =IFERROR(_xlfn.XLOOKUP(S14,'RMD Simulation'!AA:AA,'RMD Simulation'!AH:AH),"") -> 16884.694 | V14: =IFERROR(_xlfn.XLOOKUP(S14,'RMD Simulation'!P:P,'RMD Simulation'!W:W),"") -> 17573.67
E15: Fed LTCG Tax | F15: ='No planning'!C20 -> 0 | G15: =Film!C24 -> 0 | H15: =MIN(MAX(Solar!C20 - H13, 0), F15) -> 0 | I15: =Charitable!C24 -> 0 | J15: =MIN(MAX('Solar & Charitable'!C58-J13,0),'Solar & Charitable'!C27) -> 0 | K15: =LEAP!J28 -> 0 | L15: ='LEAP & Charitable'!C65 -> 0 | S15: =IFERROR(IF(S14+1>99,"",S14+1),"") -> 78 | T15: =IFERROR(_xlfn.XLOOKUP(S15,'RMD Simulation'!AL:AL,'RMD Simulation'!AS:AS),"") -> 21175.644 | U15: =IFERROR(_xlfn.XLOOKUP(S15,'RMD Simulation'!AA:AA,'RMD Simulation'!AH:AH),"") -> 17984.502 | V15: =IFERROR(_xlfn.XLOOKUP(S15,'RMD Simulation'!P:P,'RMD Simulation'!W:W),"") -> 18718.355
E16: State Tax | F16: ='No planning'!I42 -> 12000 | G16: =Film!I42 -> 3024 | H16: =Solar!J42 -> 11059.732 | I16: =Charitable!H42 -> 12000 | J16: ='Solar & Charitable'!J42 -> 11017.77 | K16: =LEAP!C29 -> 12000 | L16: ='LEAP & Charitable'!C64 -> 12000 | S16: =IFERROR(IF(S15+1>99,"",S15+1),"") -> 79 | T16: =IFERROR(_xlfn.XLOOKUP(S16,'RMD Simulation'!AL:AL,'RMD Simulation'!AS:AS),"") -> 22550.556 | U16: =IFERROR(_xlfn.XLOOKUP(S16,'RMD Simulation'!AA:AA,'RMD Simulation'!AH:AH),"") -> 19152.216 | V16: =IFERROR(_xlfn.XLOOKUP(S16,'RMD Simulation'!P:P,'RMD Simulation'!W:W),"") -> 19933.717
E17: Strategy Contribution | F17: 0 | G17: =Film!D14 -> 62989.474 | H17: =Solar!C18 -> 70583.134 | I17: =Charitable!D14 -> 40000 | J17: ='Solar & Charitable'!D17+'Solar & Charitable'!C49 -> 73013.342 | K17: =LEAP!D14+LEAP!E14+LEAP!D12+LEAP!E12 -> -17640 | L17: ='LEAP & Charitable'!C78-L19 -> 40000 | S17: =IFERROR(IF(S16+1>99,"",S16+1),"") -> 80 | T17: =IFERROR(_xlfn.XLOOKUP(S17,'RMD Simulation'!AL:AL,'RMD Simulation'!AS:AS),"") -> 24009.644 | U17: =IFERROR(_xlfn.XLOOKUP(S17,'RMD Simulation'!AA:AA,'RMD Simulation'!AH:AH),"") -> 20391.421 | V17: =IFERROR(_xlfn.XLOOKUP(S17,'RMD Simulation'!P:P,'RMD Simulation'!W:W),"") -> 21223.488
E18: Investment Account | F18: 0 | G18: 0 | H18: 0 | I18: 0 | J18: 0 | K18: =LEAP!D20+LEAP!E20 -> -7560 | L18: ='LEAP & Charitable'!C79 -> 0 | S18: =IFERROR(IF(S17+1>99,"",S17+1),"") -> 81 | T18: =IFERROR(_xlfn.XLOOKUP(S18,'RMD Simulation'!AL:AL,'RMD Simulation'!AS:AS),"") -> 25425.47 | U18: =IFERROR(_xlfn.XLOOKUP(S18,'RMD Simulation'!AA:AA,'RMD Simulation'!AH:AH),"") -> 21593.884 | V18: =IFERROR(_xlfn.XLOOKUP(S18,'RMD Simulation'!P:P,'RMD Simulation'!W:W),"") -> 22475.017
E19: Membership Fee | F19: 0 | G19: =Film!D16 -> 0 | H19: ='Strategy comparison'!C12 -> 0 | I19: ='Strategy comparison'!C12 -> 0 | J19: ='Strategy comparison'!C12 -> 0 | K19: ='Strategy comparison'!C12 -> 0 | L19: ='Strategy comparison'!C12 -> 0 | S19: =IFERROR(IF(S18+1>99,"",S18+1),"") -> 82 | T19: =IFERROR(_xlfn.XLOOKUP(S19,'RMD Simulation'!AL:AL,'RMD Simulation'!AS:AS),"") -> 27058.197 | U19: =IFERROR(_xlfn.XLOOKUP(S19,'RMD Simulation'!AA:AA,'RMD Simulation'!AH:AH),"") -> 22980.562 | V19: =IFERROR(_xlfn.XLOOKUP(S19,'RMD Simulation'!P:P,'RMD Simulation'!W:W),"") -> 23918.278
E20: Total Cash Outlay | F20: =SUM(F13:F19) -> 244395.42 | G20: =SUM(G13:G19) -> 228813.35 | H20: =SUM(H13:H19) -> 232842.87 | I20: =SUM(I13:I19) -> 236623.66 | J20: =SUM(J13:J19) -> 235231.11 | K20: =SUM(K13:K19) -> 251167.1 | L20: =SUM(L13:L19) -> 236623.66 | S20: =IFERROR(IF(S19+1>99,"",S19+1),"") -> 83 | T20: =IFERROR(_xlfn.XLOOKUP(S20,'RMD Simulation'!AL:AL,'RMD Simulation'!AS:AS),"") -> 28625.127 | U20: =IFERROR(_xlfn.XLOOKUP(S20,'RMD Simulation'!AA:AA,'RMD Simulation'!AH:AH),"") -> 24311.357 | V20: =IFERROR(_xlfn.XLOOKUP(S20,'RMD Simulation'!P:P,'RMD Simulation'!W:W),"") -> 25303.376
E21: Savings | F21: 0 | G21: =$F20-G20 -> 15582.066 | H21: =$F20-H20 -> 11552.554 | I21: =$F20-I20 -> 7771.76 | J21: =$F20-J20 -> 9164.3082 | K21: =$F20-K20+K18 -> -14331.68 | L21: =F20-L20+L18 -> 7771.76 | S21: =IFERROR(IF(S20+1>99,"",S20+1),"") -> 84 | T21: =IFERROR(_xlfn.XLOOKUP(S21,'RMD Simulation'!AL:AL,'RMD Simulation'!AS:AS),"") -> 30446.571 | U21: =IFERROR(_xlfn.XLOOKUP(S21,'RMD Simulation'!AA:AA,'RMD Simulation'!AH:AH),"") -> 25858.312 | V21: =IFERROR(_xlfn.XLOOKUP(S21,'RMD Simulation'!P:P,'RMD Simulation'!W:W),"") -> 26913.453
E22: Effective Tax Rate | F22: =($F$20-F21)/('No planning'!$C$15+$C$2) -> 0.28752402 | G22: =($F$20-G21)/('No planning'!$C$15+$C$2) -> 0.26919218 | H22: =($F$20-H21)/('No planning'!$C$15+$C$2) -> 0.27393278 | I22: =($F$20-I21)/('No planning'!$C$15+$C$2) -> 0.27838078 | J22: =($F$20-J21)/('No planning'!$C$15+$C$2) -> 0.27674248 | K22: =($F$20-K21)/('No planning'!$C$15+$C$2) -> 0.30438482 | L22: =($F$20-L21)/('No planning'!$C$15+$C$2) -> 0.27838078 | S22: =IFERROR(IF(S21+1>99,"",S21+1),"") -> 85 | T22: =IFERROR(_xlfn.XLOOKUP(S22,'RMD Simulation'!AL:AL,'RMD Simulation'!AS:AS),"") -> 32170.608 | U22: =IFERROR(_xlfn.XLOOKUP(S22,'RMD Simulation'!AA:AA,'RMD Simulation'!AH:AH),"") -> 27322.539 | V22: =IFERROR(_xlfn.XLOOKUP(S22,'RMD Simulation'!P:P,'RMD Simulation'!W:W),"") -> 28437.428
S23: =IFERROR(IF(S22+1>99,"",S22+1),"") -> 86 | T23: =IFERROR(_xlfn.XLOOKUP(S23,'RMD Simulation'!AL:AL,'RMD Simulation'!AS:AS),"") -> 33969.622 | U23: =IFERROR(_xlfn.XLOOKUP(S23,'RMD Simulation'!AA:AA,'RMD Simulation'!AH:AH),"") -> 28850.444 | V23: =IFERROR(_xlfn.XLOOKUP(S23,'RMD Simulation'!P:P,'RMD Simulation'!W:W),"") -> 30027.679
S24: =IFERROR(IF(S23+1>99,"",S23+1),"") -> 87 | T24: =IFERROR(_xlfn.XLOOKUP(S24,'RMD Simulation'!AL:AL,'RMD Simulation'!AS:AS),"") -> 35842.67 | U24: =IFERROR(_xlfn.XLOOKUP(S24,'RMD Simulation'!AA:AA,'RMD Simulation'!AH:AH),"") -> 30441.225 | V24: =IFERROR(_xlfn.XLOOKUP(S24,'RMD Simulation'!P:P,'RMD Simulation'!W:W),"") -> 31683.371
S25: =IFERROR(IF(S24+1>99,"",S24+1),"") -> 88 | T25: =IFERROR(_xlfn.XLOOKUP(S25,'RMD Simulation'!AL:AL,'RMD Simulation'!AS:AS),"") -> 37511.839 | U25: =IFERROR(_xlfn.XLOOKUP(S25,'RMD Simulation'!AA:AA,'RMD Simulation'!AH:AH),"") -> 31858.853 | V25: =IFERROR(_xlfn.XLOOKUP(S25,'RMD Simulation'!P:P,'RMD Simulation'!W:W),"") -> 33158.845
E26: Roth Conversion | S26: =IFERROR(IF(S25+1>99,"",S25+1),"") -> 89 | T26: =IFERROR(_xlfn.XLOOKUP(S26,'RMD Simulation'!AL:AL,'RMD Simulation'!AS:AS),"") -> 39515.379 | U26: =IFERROR(_xlfn.XLOOKUP(S26,'RMD Simulation'!AA:AA,'RMD Simulation'!AH:AH),"") -> 33560.461 | V26: =IFERROR(_xlfn.XLOOKUP(S26,'RMD Simulation'!P:P,'RMD Simulation'!W:W),"") -> 34929.887
F27: No Planning | G27: Film | H27: Solar | I27: Charitable | J27: Solar & Charitable | K27: LEAP | L27: LEAP & Charitable | S27: =IFERROR(IF(S26+1>99,"",S26+1),"") -> 90 | T27: =IFERROR(_xlfn.XLOOKUP(S27,'RMD Simulation'!AL:AL,'RMD Simulation'!AS:AS),"") -> 41241.747 | U27: =IFERROR(_xlfn.XLOOKUP(S27,'RMD Simulation'!AA:AA,'RMD Simulation'!AH:AH),"") -> 35026.669 | V27: =IFERROR(_xlfn.XLOOKUP(S27,'RMD Simulation'!P:P,'RMD Simulation'!W:W),"") -> 36455.923
E28: Fed Ordinary Income Tax | F28: ='Roth only'!C19 -> 236662.88 | G28: ='Film & Roth'!C22 -> 0 | H28: =MIN('Solar & Roth'!C20, F28) -> 0 | I28: ='Charitable & Roth'!C22 -> 88911.1 | J28: =MIN('Solar & Charitable & Roth'!C25,'Solar & Charitable & Roth'!C58) -> 0 | K28: ='LEAP & Roth'!C28 -> 236662.88 | L28: ='LEAP & Charitable & Roth'!C63 -> 88911.1 | S28: =IFERROR(IF(S27+1>99,"",S27+1),"") -> 91 | T28: =IFERROR(_xlfn.XLOOKUP(S28,'RMD Simulation'!AL:AL,'RMD Simulation'!AS:AS),"") -> 42977.487 | U28: =IFERROR(_xlfn.XLOOKUP(S28,'RMD Simulation'!AA:AA,'RMD Simulation'!AH:AH),"") -> 36500.834 | V28: =IFERROR(_xlfn.XLOOKUP(S28,'RMD Simulation'!P:P,'RMD Simulation'!W:W),"") -> 37990.242
E29: Fed LTCG Tax | F29: ='Roth only'!C20 -> 0 | G29: ='Film & Roth'!C24 -> 0 | H29: =MIN(MAX('Solar & Roth'!C20 - H28, 0), F29) -> 0 | I29: ='Charitable & Roth'!C24 -> 0 | J29: =MIN(MAX('Solar & Charitable & Roth'!C58-J28,0),'Solar & Charitable & Roth'!C27) -> 0 | K29: ='LEAP & Roth'!J28 -> 0 | L29: ='LEAP & Charitable & Roth'!C65 -> 0 | S29: =IFERROR(IF(S28+1>99,"",S28+1),"") -> 92 | T29: =IFERROR(_xlfn.XLOOKUP(S29,'RMD Simulation'!AL:AL,'RMD Simulation'!AS:AS),"") -> 44708.524 | U29: =IFERROR(_xlfn.XLOOKUP(S29,'RMD Simulation'!AA:AA,'RMD Simulation'!AH:AH),"") -> 37971.007 | V29: =IFERROR(_xlfn.XLOOKUP(S29,'RMD Simulation'!P:P,'RMD Simulation'!W:W),"") -> 39520.404
E30: State Tax | F30: ='Roth only'!C21 -> 25500 | G30: ='Film & Roth'!I42 -> 0 | H30: ='Solar & Roth'!J42 -> 22811.802 | I30: ='Charitable & Roth'!H42 -> 25500 | J30: ='Solar & Charitable & Roth'!J42 -> 24450.752 | K30: ='LEAP & Roth'!C29 -> 25500 | L30: ='LEAP & Charitable & Roth'!C64 -> 25500 | S30: =IFERROR(IF(S29+1>99,"",S29+1),"") -> 93 | T30: =IFERROR(_xlfn.XLOOKUP(S30,'RMD Simulation'!AL:AL,'RMD Simulation'!AS:AS),"") -> 46417.187 | U30: =IFERROR(_xlfn.XLOOKUP(S30,'RMD Simulation'!AA:AA,'RMD Simulation'!AH:AH),"") -> 39422.176 | V30: =IFERROR(_xlfn.XLOOKUP(S30,'RMD Simulation'!P:P,'RMD Simulation'!W:W),"") -> 41030.788
E31: Strategy Contribution | F31: 0 | G31: ='Film & Roth'!D14 -> 178947.37 | H31: ='Solar & Roth'!C18 -> 201426.72 | I31: ='Charitable & Roth'!D14 -> 85000 | J31: ='Solar & Charitable & Roth'!D17+'Solar & Charitable & Roth'!C49 -> 163613.21 | K31: ='LEAP & Roth'!D14+'LEAP & Roth'!E14+'LEAP & Roth'!D12+'LEAP & Roth'!E12 -> 0 | L31: ='LEAP & Charitable & Roth'!C78-L19 -> 85000 | S31: =IFERROR(IF(S30+1>99,"",S30+1),"") -> 94 | T31: =IFERROR(_xlfn.XLOOKUP(S31,'RMD Simulation'!AL:AL,'RMD Simulation'!AS:AS),"") -> 47575.174 | U31: =IFERROR(_xlfn.XLOOKUP(S31,'RMD Simulation'!AA:AA,'RMD Simulation'!AH:AH),"") -> 40405.656 | V31: =IFERROR(_xlfn.XLOOKUP(S31,'RMD Simulation'!P:P,'RMD Simulation'!W:W),"") -> 42054.398
E32: Investment Account | F32: 0 | G32: 0 | H32: 0 | I32: 0 | J32: 0 | K32: ='LEAP & Roth'!D20+'LEAP & Roth'!E20 -> 0 | L32: ='LEAP & Charitable & Roth'!C79 -> 0 | S32: =IFERROR(IF(S31+1>99,"",S31+1),"") -> 95 | T32: =IFERROR(_xlfn.XLOOKUP(S32,'RMD Simulation'!AL:AL,'RMD Simulation'!AS:AS),"") -> 48617.551 | U32: =IFERROR(_xlfn.XLOOKUP(S32,'RMD Simulation'!AA:AA,'RMD Simulation'!AH:AH),"") -> 41290.948 | V32: =IFERROR(_xlfn.XLOOKUP(S32,'RMD Simulation'!P:P,'RMD Simulation'!W:W),"") -> 42975.815
E33: Membership Fee | F33: ='Strategy comparison'!$C$12 -> 0 | G33: ='Film & Roth'!D16 -> 0 | H33: ='Strategy comparison'!C12 -> 0 | I33: ='Strategy comparison'!C12 -> 0 | J33: ='Strategy comparison'!C12 -> 0 | K33: ='Strategy comparison'!C12 -> 0 | L33: ='Strategy comparison'!C12 -> 0 | S33: =IFERROR(IF(S32+1>99,"",S32+1),"") -> 96 | T33: =IFERROR(_xlfn.XLOOKUP(S33,'RMD Simulation'!AL:AL,'RMD Simulation'!AS:AS),"") -> 48924.305 | U33: =IFERROR(_xlfn.XLOOKUP(S33,'RMD Simulation'!AA:AA,'RMD Simulation'!AH:AH),"") -> 41551.474 | V33: =IFERROR(_xlfn.XLOOKUP(S33,'RMD Simulation'!P:P,'RMD Simulation'!W:W),"") -> 43246.971
E34: Total Cash Outlay | F34: =SUM(F28:F33) -> 262162.88 | G34: =SUM(G28:G33) -> 178947.37 | H34: =SUM(H28:H33) -> 224238.52 | I34: =SUM(I28:I33) -> 199411.1 | J34: =SUM(J28:J33) -> 188063.96 | K34: =SUM(K28:K33) -> 262162.88 | L34: =SUM(L28:L33) -> 199411.1 | S34: =IFERROR(IF(S33+1>99,"",S33+1),"") -> 97 | T34: =IFERROR(_xlfn.XLOOKUP(S34,'RMD Simulation'!AL:AL,'RMD Simulation'!AS:AS),"") -> 49664.441 | U34: =IFERROR(_xlfn.XLOOKUP(S34,'RMD Simulation'!AA:AA,'RMD Simulation'!AH:AH),"") -> 42180.074 | V34: =IFERROR(_xlfn.XLOOKUP(S34,'RMD Simulation'!P:P,'RMD Simulation'!W:W),"") -> 43901.221
E35: Savings | F35: =$F20-F34 -> -17767.46 | G35: =$F20-G34 -> 65448.052 | H35: =$F20-H34 -> 20156.896 | I35: =$F20-I34 -> 44984.32 | J35: =$F20-J34 -> 56331.459 | K35: =$F20-K34+K32 -> -17767.46 | L35: =$F20-L34+L32 -> 44984.32 | S35: =IFERROR(IF(S34+1>99,"",S34+1),"") -> 98 | T35: =IFERROR(_xlfn.XLOOKUP(S35,'RMD Simulation'!AL:AL,'RMD Simulation'!AS:AS),"") -> 49501.161 | U35: =IFERROR(_xlfn.XLOOKUP(S35,'RMD Simulation'!AA:AA,'RMD Simulation'!AH:AH),"") -> 42041.399 | V35: =IFERROR(_xlfn.XLOOKUP(S35,'RMD Simulation'!P:P,'RMD Simulation'!W:W),"") -> 43756.888
E36: Effective Tax Rate | F36: =($F$20-F35)/('No planning'!$C$15+$C$2) -> 0.30842692 | G36: =($F$20-G35)/('No planning'!$C$15+$C$2) -> 0.21052632 | H36: =($F$20-H35)/('No planning'!$C$15+$C$2) -> 0.26381003 | I36: =($F$20-I35)/('No planning'!$C$15+$C$2) -> 0.23460129 | J36: =($F$20-J35)/('No planning'!$C$15+$C$2) -> 0.22125172 | K36: =($F$20-K35)/('No planning'!$C$15+$C$2) -> 0.30842692 | L36: =($F$20-L35)/('No planning'!$C$15+$C$2) -> 0.23460129 | S36: =IFERROR(IF(S35+1>99,"",S35+1),"") -> 99 | T36: =IFERROR(_xlfn.XLOOKUP(S36,'RMD Simulation'!AL:AL,'RMD Simulation'!AS:AS),"") -> 49071.666 | U36: =IFERROR(_xlfn.XLOOKUP(S36,'RMD Simulation'!AA:AA,'RMD Simulation'!AH:AH),"") -> 41676.628 | V36: =IFERROR(_xlfn.XLOOKUP(S36,'RMD Simulation'!P:P,'RMD Simulation'!W:W),"") -> 43377.232
S37: =IFERROR(IF(S36+1>99,"",S36+1),"") | U37: =IFERROR(_xlfn.XLOOKUP(S37,'RMD Simulation'!AA:AA,'RMD Simulation'!AH:AH),"") | V37: =IFERROR(_xlfn.XLOOKUP(S37,'RMD Simulation'!P:P,'RMD Simulation'!W:W),"")
S38: =IFERROR(IF(S37+1>99,"",S37+1),"") | U38: =IFERROR(_xlfn.XLOOKUP(S38,'RMD Simulation'!AA:AA,'RMD Simulation'!AH:AH),"") | V38: =IFERROR(_xlfn.XLOOKUP(S38,'RMD Simulation'!P:P,'RMD Simulation'!W:W),"")
E39: Net Savings | S39: =IFERROR(IF(S38+1>99,"",S38+1),"") | U39: =IFERROR(_xlfn.XLOOKUP(S39,'RMD Simulation'!AA:AA,'RMD Simulation'!AH:AH),"") | V39: =IFERROR(_xlfn.XLOOKUP(S39,'RMD Simulation'!P:P,'RMD Simulation'!W:W),"")
F40: No Planning | G40: Film | H40: Solar | I40: Charitable | J40: Solar & Charitable | K40: LEAP | L40: LEAP & Charitable | S40: =IFERROR(IF(S39+1>99,"",S39+1),"") | U40: =IFERROR(_xlfn.XLOOKUP(S40,'RMD Simulation'!AA:AA,'RMD Simulation'!AH:AH),"") | V40: =IFERROR(_xlfn.XLOOKUP(S40,'RMD Simulation'!P:P,'RMD Simulation'!W:W),"")
E41: No Conversion | F41: =F21 -> 0 | G41: =G21 -> 15582.066 | H41: =H21 -> 11552.554 | I41: =I21 -> 7771.76 | J41: =J21 -> 9164.3082 | K41: =K21 -> -14331.68 | L41: =L21 -> 7771.76 | S41: =IFERROR(IF(S40+1>99,"",S40+1),"") | U41: =IFERROR(_xlfn.XLOOKUP(S41,'RMD Simulation'!AA:AA,'RMD Simulation'!AH:AH),"") | V41: =IFERROR(_xlfn.XLOOKUP(S41,'RMD Simulation'!P:P,'RMD Simulation'!W:W),"")
E42: Conversion | F42: =F35 -> -17767.46 | G42: =G35 -> 65448.052 | H42: =H35 -> 20156.896 | I42: =I35 -> 44984.32 | J42: =J35 -> 56331.459 | K42: =K35 -> -17767.46 | L42: =L35 -> 44984.32 | S42: =IFERROR(IF(S41+1>99,"",S41+1),"") | U42: =IFERROR(_xlfn.XLOOKUP(S42,'RMD Simulation'!AA:AA,'RMD Simulation'!AH:AH),"") | V42: =IFERROR(_xlfn.XLOOKUP(S42,'RMD Simulation'!P:P,'RMD Simulation'!W:W),"")
E43: Net Additional Savings | F43: =F42-F41 -> -17767.46 | G43: =G42-G41 -> 49865.985 | H43: =H42-H41 -> 8604.3412 | I43: =I42-I41 -> 37212.56 | J43: =J42-J41 -> 47167.151 | K43: =K42-K41 -> -3435.78 | L43: =L42-L41 -> 37212.56 | S43: =IFERROR(IF(S42+1>99,"",S42+1),"") | U43: =IFERROR(_xlfn.XLOOKUP(S43,'RMD Simulation'!AA:AA,'RMD Simulation'!AH:AH),"") | V43: =IFERROR(_xlfn.XLOOKUP(S43,'RMD Simulation'!P:P,'RMD Simulation'!W:W),"")
S44: =IFERROR(IF(S43+1>99,"",S43+1),"") | U44: =IFERROR(_xlfn.XLOOKUP(S44,'RMD Simulation'!AA:AA,'RMD Simulation'!AH:AH),"") | V44: =IFERROR(_xlfn.XLOOKUP(S44,'RMD Simulation'!P:P,'RMD Simulation'!W:W),"")
E45: Effective Tax Rate | S45: =IFERROR(IF(S44+1>99,"",S44+1),"") | U45: =IFERROR(_xlfn.XLOOKUP(S45,'RMD Simulation'!AA:AA,'RMD Simulation'!AH:AH),"") | V45: =IFERROR(_xlfn.XLOOKUP(S45,'RMD Simulation'!P:P,'RMD Simulation'!W:W),"")
F46: No Planning | G46: Film | H46: Solar | I46: Charitable | J46: Solar & Charitable | K46: LEAP | L46: LEAP & Charitable | S46: =IFERROR(IF(S45+1>99,"",S45+1),"") | U46: =IFERROR(_xlfn.XLOOKUP(S46,'RMD Simulation'!AA:AA,'RMD Simulation'!AH:AH),"") | V46: =IFERROR(_xlfn.XLOOKUP(S46,'RMD Simulation'!P:P,'RMD Simulation'!W:W),"")
E47: No Conversion | F47: =F22 -> 0.28752402 | G47: =G22 -> 0.26919218 | H47: =H22 -> 0.27393278 | I47: =I22 -> 0.27838078 | J47: =J22 -> 0.27674248 | K47: =K22 -> 0.30438482 | L47: =L22 -> 0.27838078 | S47: =IFERROR(IF(S46+1>99,"",S46+1),"") | U47: =IFERROR(_xlfn.XLOOKUP(S47,'RMD Simulation'!AA:AA,'RMD Simulation'!AH:AH),"") | V47: =IFERROR(_xlfn.XLOOKUP(S47,'RMD Simulation'!P:P,'RMD Simulation'!W:W),"")
E48: Conversion | F48: =F36 -> 0.30842692 | G48: =G36 -> 0.21052632 | H48: =H36 -> 0.26381003 | I48: =I36 -> 0.23460129 | J48: =J36 -> 0.22125172 | K48: =K36 -> 0.30842692 | L48: =L36 -> 0.23460129 | S48: =IFERROR(IF(S47+1>99,"",S47+1),"") | U48: =IFERROR(_xlfn.XLOOKUP(S48,'RMD Simulation'!AA:AA,'RMD Simulation'!AH:AH),"") | V48: =IFERROR(_xlfn.XLOOKUP(S48,'RMD Simulation'!P:P,'RMD Simulation'!W:W),"")
S49: =IFERROR(IF(S48+1>99,"",S48+1),"") | U49: =IFERROR(_xlfn.XLOOKUP(S49,'RMD Simulation'!AA:AA,'RMD Simulation'!AH:AH),"") | V49: =IFERROR(_xlfn.XLOOKUP(S49,'RMD Simulation'!P:P,'RMD Simulation'!W:W),"")
S50: =IFERROR(IF(S49+1>99,"",S49+1),"") | U50: =IFERROR(_xlfn.XLOOKUP(S50,'RMD Simulation'!AA:AA,'RMD Simulation'!AH:AH),"") | V50: =IFERROR(_xlfn.XLOOKUP(S50,'RMD Simulation'!P:P,'RMD Simulation'!W:W),"")
S51: =IFERROR(IF(S50+1>99,"",S50+1),"") | U51: =IFERROR(_xlfn.XLOOKUP(S51,'RMD Simulation'!AA:AA,'RMD Simulation'!AH:AH),"") | V51: =IFERROR(_xlfn.XLOOKUP(S51,'RMD Simulation'!P:P,'RMD Simulation'!W:W),"")
S52: =IFERROR(IF(S51+1>99,"",S51+1),"") | U52: =IFERROR(_xlfn.XLOOKUP(S52,'RMD Simulation'!AA:AA,'RMD Simulation'!AH:AH),"") | V52: =IFERROR(_xlfn.XLOOKUP(S52,'RMD Simulation'!P:P,'RMD Simulation'!W:W),"")
S53: =IFERROR(IF(S52+1>99,"",S52+1),"") | U53: =IFERROR(_xlfn.XLOOKUP(S53,'RMD Simulation'!AA:AA,'RMD Simulation'!AH:AH),"") | V53: =IFERROR(_xlfn.XLOOKUP(S53,'RMD Simulation'!P:P,'RMD Simulation'!W:W),"")
S54: =IFERROR(IF(S53+1>99,"",S53+1),"") | U54: =IFERROR(_xlfn.XLOOKUP(S54,'RMD Simulation'!AA:AA,'RMD Simulation'!AH:AH),"") | V54: =IFERROR(_xlfn.XLOOKUP(S54,'RMD Simulation'!P:P,'RMD Simulation'!W:W),"")
S55: =IFERROR(IF(S54+1>99,"",S54+1),"") | U55: =IFERROR(_xlfn.XLOOKUP(S55,'RMD Simulation'!AA:AA,'RMD Simulation'!AH:AH),"") | V55: =IFERROR(_xlfn.XLOOKUP(S55,'RMD Simulation'!P:P,'RMD Simulation'!W:W),"")
S56: =IFERROR(IF(S55+1>99,"",S55+1),"") | U56: =IFERROR(_xlfn.XLOOKUP(S56,'RMD Simulation'!AA:AA,'RMD Simulation'!AH:AH),"") | V56: =IFERROR(_xlfn.XLOOKUP(S56,'RMD Simulation'!P:P,'RMD Simulation'!W:W),"")
S57: =IFERROR(IF(S56+1>99,"",S56+1),"") | U57: =IFERROR(_xlfn.XLOOKUP(S57,'RMD Simulation'!AA:AA,'RMD Simulation'!AH:AH),"") | V57: =IFERROR(_xlfn.XLOOKUP(S57,'RMD Simulation'!P:P,'RMD Simulation'!W:W),"")
S58: =IFERROR(IF(S57+1>99,"",S57+1),"") | U58: =IFERROR(_xlfn.XLOOKUP(S58,'RMD Simulation'!AA:AA,'RMD Simulation'!AH:AH),"") | V58: =IFERROR(_xlfn.XLOOKUP(S58,'RMD Simulation'!P:P,'RMD Simulation'!W:W),"")
S59: =IFERROR(IF(S58+1>99,"",S58+1),"") | U59: =IFERROR(_xlfn.XLOOKUP(S59,'RMD Simulation'!AA:AA,'RMD Simulation'!AH:AH),"") | V59: =IFERROR(_xlfn.XLOOKUP(S59,'RMD Simulation'!P:P,'RMD Simulation'!W:W),"")
S60: =IFERROR(IF(S59+1>99,"",S59+1),"") | U60: =IFERROR(_xlfn.XLOOKUP(S60,'RMD Simulation'!AA:AA,'RMD Simulation'!AH:AH),"") | V60: =IFERROR(_xlfn.XLOOKUP(S60,'RMD Simulation'!P:P,'RMD Simulation'!W:W),"")
... S79: =IFERROR(IF(S78+1>99,"",S78+1),"") | U79: =IFERROR(_xlfn.XLOOKUP(S79,'RMD Simulation'!AA:AA,'RMD Simulation'!AH:AH),"") | V79: =IFERROR(_xlfn.XLOOKUP(S79,'RMD Simulation'!P:P,'RMD Simulation'!W:W),"")
S80: =IFERROR(IF(S79+1>100,"",S79+1),"") | U80: =IFERROR(_xlfn.XLOOKUP(S80,'RMD Simulation'!AA:AA,'RMD Simulation'!AH:AH),"") | V80: =IFERROR(_xlfn.XLOOKUP(S80,'RMD Simulation'!P:P,'RMD Simulation'!W:W),"")
S81: =IFERROR(IF(S80+1>100,"",S80+1),"")
S82: =IFERROR(IF(S81+1>100,"",S81+1),"")
S83: =IFERROR(IF(S82+1>100,"",S82+1),"")
S84: =IFERROR(IF(S83+1>100,"",S83+1),"")
S85: =IFERROR(IF(S84+1>100,"",S84+1),"")
S86: =IFERROR(IF(S85+1>100,"",S85+1),"")

Sheet No planning
B4: Inputs | G4: Federal Ordinary Income Tax
B5: Filing Status - LA | C5: ='Strategy comparison'!C4 -> Married-Joint
B6: W2 Income | C6: ='Strategy comparison'!C5 -> 400000 | G6: Married Filing Joint | J6: Ordinary Income | K6: Non-LTCG AGI w Gift | M6: Unmarried/Single | P6: Ordinary Income | Q6: Non-LTCG AGI w Gift
B7: Business Income | C7: ='Strategy comparison'!C6 -> 0 | J7: =C12 -> 400000 | K7: =J7-MIN(C15*#REF!,J7) -> #REF! | P7: =J7 -> 400000 | Q7: =K7 -> #REF!
B8: ST Capital Gains | C8: ='Strategy comparison'!C7 -> 0 | G8: ='Tax Tables'!B6 -> 0 | H8: ='Tax Tables'!C6 -> 24800 | I8: ='Tax Tables'!D6 -> 0.1 | J8: =IF(IF(J$7>H8,(H8-G8)*I8,(J$7-G8)*I8)>0,IF(J$7>H8,(H8-G8)*I8,(J$7-G8)*I8),0) -> 2480 | K8: =IF(IF(K$7>H8,(H8-G8)*I8,(K$7-G8)*I8)>0,IF(K$7>H8,(H8-G8)*I8,(K$7-G8)*I8),0) -> #REF! | M8: ='Tax Tables'!F6 -> 0 | N8: ='Tax Tables'!G6 -> 12400 | O8: ='Tax Tables'!H6 -> 0.1 | P8: =IF(IF(P$7>N8,(N8-M8)*O8,(P$7-M8)*O8)>0,IF(P$7>N8,(N8-M8)*O8,(P$7-M8)*O8),0) -> 1240 | Q8: =IF(IF(Q$7>N8,(N8-M8)*O8,(Q$7-M8)*O8)>0,IF(Q$7>N8,(N8-M8)*O8,(Q$7-M8)*O8),0) -> #REF!
B9: Interest | C9: ='Strategy comparison'!$C$9 -> 0 | G9: ='Tax Tables'!B7 -> 24801 | H9: ='Tax Tables'!C7 -> 100800 | I9: ='Tax Tables'!D7 -> 0.12 | J9: =IF(IF(J$7>H9,(H9-G9)*I9,(J$7-G9)*I9)>0,IF(J$7>H9,(H9-G9)*I9,(J$7-G9)*I9),0) -> 9119.88 | K9: =IF(IF(K$7>H9,(H9-G9)*I9,(K$7-G9)*I9)>0,IF(K$7>H9,(H9-G9)*I9,(K$7-G9)*I9),0) -> #REF! | M9: ='Tax Tables'!F7 -> 12401 | N9: ='Tax Tables'!G7 -> 50400 | O9: ='Tax Tables'!H7 -> 0.12 | P9: =IF(IF(P$7>N9,(N9-M9)*O9,(P$7-M9)*O9)>0,IF(P$7>N9,(N9-M9)*O9,(P$7-M9)*O9),0) -> 4559.88 | Q9: =IF(IF(Q$7>N9,(N9-M9)*O9,(Q$7-M9)*O9)>0,IF(Q$7>N9,(N9-M9)*O9,(Q$7-M9)*O9),0) -> #REF!
B10: Qualified Dividends | C10: ='Strategy comparison'!$C$10 -> 0 | G10: ='Tax Tables'!B8 -> 100801 | H10: ='Tax Tables'!C8 -> 211400 | I10: ='Tax Tables'!D8 -> 0.22 | J10: =IF(IF(J$7>H10,(H10-G10)*I10,(J$7-G10)*I10)>0,IF(J$7>H10,(H10-G10)*I10,(J$7-G10)*I10),0) -> 24331.78 | K10: =IF(IF(K$7>H10,(H10-G10)*I10,(K$7-G10)*I10)>0,IF(K$7>H10,(H10-G10)*I10,(K$7-G10)*I10),0) -> #REF! | M10: ='Tax Tables'!F8 -> 50401 | N10: ='Tax Tables'!G8 -> 105700 | O10: ='Tax Tables'!H8 -> 0.22 | P10: =IF(IF(P$7>N10,(N10-M10)*O10,(P$7-M10)*O10)>0,IF(P$7>N10,(N10-M10)*O10,(P$7-M10)*O10),0) -> 12165.78 | Q10: =IF(IF(Q$7>N10,(N10-M10)*O10,(Q$7-M10)*O10)>0,IF(Q$7>N10,(N10-M10)*O10,(Q$7-M10)*O10),0) -> #REF!
B11: Nonqualified Dividends | C11: ='Strategy comparison'!$C$11 -> 0 | G11: ='Tax Tables'!B9 -> 211401 | H11: ='Tax Tables'!C9 -> 403550 | I11: ='Tax Tables'!D9 -> 0.24 | J11: =IF(IF(J$7>H11,(H11-G11)*I11,(J$7-G11)*I11)>0,IF(J$7>H11,(H11-G11)*I11,(J$7-G11)*I11),0) -> 45263.76 | K11: =IF(IF(K$7>H11,(H11-G11)*I11,(K$7-G11)*I11)>0,IF(K$7>H11,(H11-G11)*I11,(K$7-G11)*I11),0) -> #REF! | M11: ='Tax Tables'!F9 -> 105701 | N11: ='Tax Tables'!G9 -> 201775 | O11: ='Tax Tables'!H9 -> 0.24 | P11: =IF(IF(P$7>N11,(N11-M11)*O11,(P$7-M11)*O11)>0,IF(P$7>N11,(N11-M11)*O11,(P$7-M11)*O11),0) -> 23057.76 | Q11: =IF(IF(Q$7>N11,(N11-M11)*O11,(Q$7-M11)*O11)>0,IF(Q$7>N11,(N11-M11)*O11,(Q$7-M11)*O11),0) -> #REF!
B12: Ordinary Income | C12: =SUM(C6:C9)+C11 -> 400000 | G12: ='Tax Tables'!B10 -> 403551 | H12: ='Tax Tables'!C10 -> 512450 | I12: ='Tax Tables'!D10 -> 0.32 | J12: =IF(IF(J$7>H12,(H12-G12)*I12,(J$7-G12)*I12)>0,IF(J$7>H12,(H12-G12)*I12,(J$7-G12)*I12),0) -> 0 | K12: =IF(IF(K$7>H12,(H12-G12)*I12,(K$7-G12)*I12)>0,IF(K$7>H12,(H12-G12)*I12,(K$7-G12)*I12),0) -> #REF! | M12: ='Tax Tables'!F10 -> 201776 | N12: ='Tax Tables'!G10 -> 256225 | O12: ='Tax Tables'!H10 -> 0.32 | P12: =IF(IF(P$7>N12,(N12-M12)*O12,(P$7-M12)*O12)>0,IF(P$7>N12,(N12-M12)*O12,(P$7-M12)*O12),0) -> 17423.68 | Q12: =IF(IF(Q$7>N12,(N12-M12)*O12,(Q$7-M12)*O12)>0,IF(Q$7>N12,(N12-M12)*O12,(Q$7-M12)*O12),0) -> #REF!
B13: LTCG | C13: ='Strategy comparison'!C8 -> 0 | G13: ='Tax Tables'!B11 -> 512451 | H13: ='Tax Tables'!C11 -> 768700 | I13: ='Tax Tables'!D11 -> 0.35 | J13: =IF(IF(J$7>H13,(H13-G13)*I13,(J$7-G13)*I13)>0,IF(J$7>H13,(H13-G13)*I13,(J$7-G13)*I13),0) -> 0 | K13: =IF(IF(K$7>H13,(H13-G13)*I13,(K$7-G13)*I13)>0,IF(K$7>H13,(H13-G13)*I13,(K$7-G13)*I13),0) -> #REF! | M13: ='Tax Tables'!F11 -> 256226 | N13: ='Tax Tables'!G11 -> 640600 | O13: ='Tax Tables'!H11 -> 0.35 | P13: =IF(IF(P$7>N13,(N13-M13)*O13,(P$7-M13)*O13)>0,IF(P$7>N13,(N13-M13)*O13,(P$7-M13)*O13),0) -> 50320.9 | Q13: =IF(IF(Q$7>N13,(N13-M13)*O13,(Q$7-M13)*O13)>0,IF(Q$7>N13,(N13-M13)*O13,(Q$7-M13)*O13),0) -> #REF!
B14: LTCG & Qualified Dividends | C14: =C13+C10 -> 0 | G14: ='Tax Tables'!B12 -> 768701 | H14: ='Tax Tables'!C12 -> 99999999999 | I14: ='Tax Tables'!D12 -> 0.37 | J14: =IF(J7>=G14,(J7-G14)*I14,0) -> 0 | K14: =IF(K7>=G14,(K7-G14)*I14,0) -> #REF! | M14: ='Tax Tables'!F12 -> 640601 | N14: ='Tax Tables'!G12 -> 99999999999 | O14: ='Tax Tables'!H12 -> 0.37 | P14: =IF(P7>=M14,(P7-M14)*O14,0) -> 0 | Q14: =IF(Q7>=M14,(Q7-M14)*O14,0) -> #REF!
B15: AGI | C15: =C12+C14 -> 400000
I16: Est. Tax Expense | K16: Difference | O16: Est. Tax Expense | Q16: Difference
I17: =SUM(J8:J14) -> 81195.42 | J17: =SUM(K8:K14) -> #REF! | K17: =I17-J17 -> #REF! | O17: =SUM(P8:P14) -> 108768 | P17: =SUM(Q8:Q14) -> #REF! | Q17: =O17-P17 -> #REF!
B18: Summary
B19: Fed Ord. Income Tax | C19: =IF(C5="Married-Joint", I17,O17) -> 81195.42 | G19: Long Term Capital Gains & Qualified Dividends Tax
B20: Fed LTCG & QD Tax | C20: =IF(C5="Married-Joint", I28,O28) -> 0
B21: State Tax | C21: =I42 -> 12000 | G21: Married Filing Joint | J21: LTCG & QD | K21: AGI w Gift | M21: Unmarried/Single | P21: LTCG & QD | Q21: AGI w Gift
B22: NIIT | C22: =I45 -> 5700 | J22: =C14 -> 0 | K22: =J22-IF((#REF!*#REF!)>J7, (#REF!*#REF!)-J7,0) -> #REF! | P22: =J22 -> 0 | Q22: =P22-IF((#REF!*#REF!)>P7, (#REF!*#REF!)-P7,0) -> #REF!
B23: Total | C23: =SUM(C19:C22) -> 98895.42 | G23: ='Tax Tables'!B18 -> 0 | H23: ='Tax Tables'!C18 -> 98900 | I23: ='Tax Tables'!D18 -> 0 | J23: =IF(J$22>$H23,($H23-$G23)*$I23,MAX((J$22-$G23),0)*$I23) -> 0 | K23: =IF(K$22>$H23,($H23-$G23)*$I23,MAX((K$22-$G23),0)*$I23) -> #REF! | M23: ='Tax Tables'!F18 -> 0 | N23: ='Tax Tables'!G18 -> 49450 | O23: ='Tax Tables'!H18 -> 0 | P23: =IF(P$22>$N23,($N23-$M23)*$O23,MAX((P$22-$M23),0)*$O23) -> 0 | Q23: =IF(Q$22>$N23,($N23-$M23)*$O23,MAX((Q$22-$M23),0)*$O23) -> #REF!
G24: ='Tax Tables'!B19 -> 98901 | H24: ='Tax Tables'!C19 -> 613700 | I24: ='Tax Tables'!D19 -> 0.15 | J24: =IF(J$22>$H24,($H24-$G24)*$I24,MAX((J$22-$G24),0)*$I24) -> 0 | K24: =IF(K$22>$H24,($H24-$G24)*$I24,MAX((K$22-$G24),0)*$I24) -> #REF! | M24: ='Tax Tables'!F19 -> 49451 | N24: ='Tax Tables'!G19 -> 545500 | O24: ='Tax Tables'!H19 -> 0.15 | P24: =IF(P$22>$N24,($N24-$M24)*$O24,MAX((P$22-$M24),0)*$O24) -> 0 | Q24: =IF(Q$22>$N24,($N24-$M24)*$O24,MAX((Q$22-$M24),0)*$O24) -> #REF!
G25: ='Tax Tables'!B20 -> 613701 | H25: ='Tax Tables'!C20 -> 99999999999 | I25: ='Tax Tables'!D20 -> 0.2 | J25: =IF(J$22>$H25,($H25-$G25)*$I25,MAX((J$22-$G25),0)*$I25) -> 0 | K25: =IF(K$22>$H25,($H25-$G25)*$I25,MAX((K$22-$G25),0)*$I25) -> #REF! | M25: ='Tax Tables'!F20 -> 545501 | N25: ='Tax Tables'!G20 -> 99999999999 | O25: ='Tax Tables'!H20 -> 0.2 | P25: =IF(P$22>$N25,($N25-$M25)*$O25,MAX((P$22-$M25),0)*$O25) -> 0 | Q25: =IF(Q$22>$N25,($N25-$M25)*$O25,MAX((Q$22-$M25),0)*$O25) -> #REF!
I27: Est. Tax Expense | K27: Difference | O27: Est. Tax Expense | Q27: Difference
I28: =SUM(J23:J25) -> 0 | J28: =SUM(K23:K25) -> #REF! | K28: =I28-J28 -> #REF! | O28: =SUM(P23:P25) -> 0 | P28: =SUM(Q23:Q25) -> #REF! | Q28: =O28-P28 -> #REF!
G30: State Income Tax - Louisiana
G32: Married Filing Joint | J32: AGI | K32: AGI w Depreciation | M32: Unmarried/Single | P32: AGI | Q32: AGI w Depreciation
J33: =C15 -> 400000 | K33: =J33-#REF! -> #REF! | P33: =J33 -> 400000 | Q33: =P33-#REF! -> #REF!
G34: ='Tax Tables'!B25 -> 0 | H34: ='Tax Tables'!C25 -> 100000000 | I34: ='Tax Tables'!D25 -> 0.03 | J34: =IF(IF(J$33>H34,(H34-G34)*I34,(J$33-G34)*I34)>0,IF(J$33>H34,(H34-G34)*I34,(J$33-G34)*I34),0) -> 12000 | K34: =IF(IF(K$33>H34,(H34-G34)*I34,(K$33-G34)*I34)>0,IF(K$33>H34,(H34-G34)*I34,(K$33-G34)*I34),0) -> #REF! | M34: ='Tax Tables'!F25 -> 0 | N34: ='Tax Tables'!G25 -> 100000000 | O34: ='Tax Tables'!H25 -> 0.03 | P34: =IF(IF(P$33>N34,(N34-M34)*O34,(P$33-M34)*O34)>0,IF(P$33>N34,(N34-M34)*O34,(P$33-M34)*O34),0) -> 12000 | Q34: =IF(IF(Q$33>N34,(N34-M34)*O34,(Q$33-M34)*O34)>0,IF(Q$33>N34,(N34-M34)*O34,(Q$33-M34)*O34),0) -> #REF!
G35: ='Tax Tables'!B26 -> 0 | H35: ='Tax Tables'!C26 -> 0 | I35: ='Tax Tables'!D26 -> 0 | J35: =IF(IF(J$33>H35,(H35-G35)*I35,(J$33-G35)*I35)>0,IF(J$33>H35,(H35-G35)*I35,(J$33-G35)*I35),0) -> 0 | K35: =IF(IF(K$33>H35,(H35-G35)*I35,(K$33-G35)*I35)>0,IF(K$33>H35,(H35-G35)*I35,(K$33-G35)*I35),0) -> #REF! | M35: ='Tax Tables'!F26 -> 0 | N35: ='Tax Tables'!G26 -> 0 | O35: ='Tax Tables'!H26 -> 0 | P35: =IF(IF(P$33>N35,(N35-M35)*O35,(P$33-M35)*O35)>0,IF(P$33>N35,(N35-M35)*O35,(P$33-M35)*O35),0) -> 0 | Q35: =IF(IF(Q$33>N35,(N35-M35)*O35,(Q$33-M35)*O35)>0,IF(Q$33>N35,(N35-M35)*O35,(Q$33-M35)*O35),0) -> #REF!
G36: ='Tax Tables'!B27 -> 0 | H36: ='Tax Tables'!C27 -> 0 | I36: ='Tax Tables'!D27 -> 0 | J36: =IF(IF(J$33>H36,(H36-G36)*I36,(J$33-G36)*I36)>0,IF(J$33>H36,(H36-G36)*I36,(J$33-G36)*I36),0) -> 0 | K36: =IF(IF(K$33>H36,(H36-G36)*I36,(K$33-G36)*I36)>0,IF(K$33>H36,(H36-G36)*I36,(K$33-G36)*I36),0) -> #REF! | M36: ='Tax Tables'!F27 -> 0 | N36: ='Tax Tables'!G27 -> 0 | O36: ='Tax Tables'!H27 -> 0 | P36: =IF(IF(P$33>N36,(N36-M36)*O36,(P$33-M36)*O36)>0,IF(P$33>N36,(N36-M36)*O36,(P$33-M36)*O36),0) -> 0 | Q36: =IF(IF(Q$33>N36,(N36-M36)*O36,(Q$33-M36)*O36)>0,IF(Q$33>N36,(N36-M36)*O36,(Q$33-M36)*O36),0) -> #REF!
G37: ='Tax Tables'!B28 -> 0 | H37: ='Tax Tables'!C28 -> 0 | I37: ='Tax Tables'!D28 -> 0 | J37: =IF(IF(J$33>H37,(H37-G37)*I37,(J$33-G37)*I37)>0,IF(J$33>H37,(H37-G37)*I37,(J$33-G37)*I37),0) -> 0 | K37: =IF(IF(K$33>H37,(H37-G37)*I37,(K$33-G37)*I37)>0,IF(K$33>H37,(H37-G37)*I37,(K$33-G37)*I37),0) -> #REF! | M37: ='Tax Tables'!F28 -> 0 | N37: ='Tax Tables'!G28 -> 0 | O37: ='Tax Tables'!H28 -> 0 | P37: =IF(IF(P$33>N37,(N37-M37)*O37,(P$33-M37)*O37)>0,IF(P$33>N37,(N37-M37)*O37,(P$33-M37)*O37),0) -> 0 | Q37: =IF(IF(Q$33>N37,(N37-M37)*O37,(Q$33-M37)*O37)>0,IF(Q$33>N37,(N37-M37)*O37,(Q$33-M37)*O37),0) -> #REF!
G38: ='Tax Tables'!B29 -> 0 | H38: ='Tax Tables'!C29 -> 0 | I38: ='Tax Tables'!D29 -> 0 | J38: =IF(IF(J$33>H38,(H38-G38)*I38,(J$33-G38)*I38)>0,IF(J$33>H38,(H38-G38)*I38,(J$33-G38)*I38),0) -> 0 | K38: =IF(IF(K$33>H38,(H38-G38)*I38,(K$33-G38)*I38)>0,IF(K$33>H38,(H38-G38)*I38,(K$33-G38)*I38),0) -> #REF! | M38: ='Tax Tables'!F29 -> 0 | N38: ='Tax Tables'!G29 -> 0 | O38: ='Tax Tables'!H29 -> 0 | P38: =IF(IF(P$33>N38,(N38-M38)*O38,(P$33-M38)*O38)>0,IF(P$33>N38,(N38-M38)*O38,(P$33-M38)*O38),0) -> 0 | Q38: =IF(IF(Q$33>N38,(N38-M38)*O38,(Q$33-M38)*O38)>0,IF(Q$33>N38,(N38-M38)*O38,(Q$33-M38)*O38),0) -> #REF!
G39: ='Tax Tables'!B30 -> 0 | H39: ='Tax Tables'!C30 -> 0 | I39: ='Tax Tables'!D30 -> 0 | J39: =IF(J33>=G39,(J33-G39)*I39,0) -> 0 | K39: =IF(K33>=G39,(K33-G39)*I39,0) -> #REF! | M39: ='Tax Tables'!F30 -> 0 | N39: ='Tax Tables'!G30 -> 0 | O39: ='Tax Tables'!H30 -> 0 | P39: =IF(P33>=M39,(P33-M39)*O39,0) -> 0 | Q39: =IF(Q33>=M39,(Q33-M39)*O39,0) -> #REF!
I41: Est. Tax Expense | K41: Difference | O41: Est. Tax Expense | Q41: Difference
I42: =SUM(J34:J39) -> 12000 | J42: =SUM(K34:K39) -> #REF! | K42: =I42-J42 -> #REF! | O42: =SUM(P34:P39) -> 12000 | P42: =SUM(Q34:Q39) -> #REF! | Q42: =O42-P42 -> #REF!
H44: NIIT | I44: ='Tax Tables'!$C$34 -> 0.038
H45: =SUM(C8:C11)+C13 -> 0 | I45: =IF(C15-IF(C5="Married-Joint",250000,200000)>H45,(C15-IF(C5="Married-Joint",250000,200000))*I44, H45*I44) -> 5700

Sheet Roth only
B4: Inputs | G4: Federal Ordinary Income Tax
B5: Filing Status - LA | C5: ='Strategy comparison'!C4 -> Married-Joint
B6: W2 Income | C6: ='Strategy comparison'!C5+'Roth comparison'!C2 -> 850000 | G6: Married Filing Joint | J6: Ordinary Income | K6: Non-LTCG AGI w Gift | M6: Unmarried/Single | P6: Ordinary Income | Q6: Non-LTCG AGI w Gift
B7: Business Income | C7: ='Strategy comparison'!C6 -> 0 | J7: =C12 -> 850000 | K7: =J7-MIN(C15*#REF!,J7) -> #REF! | P7: =J7 -> 850000 | Q7: =K7 -> #REF!
B8: ST Capital Gains | C8: ='Strategy comparison'!C7 -> 0 | G8: ='Tax Tables'!B6 -> 0 | H8: ='Tax Tables'!C6 -> 24800 | I8: ='Tax Tables'!D6 -> 0.1 | J8: =IF(IF(J$7>H8,(H8-G8)*I8,(J$7-G8)*I8)>0,IF(J$7>H8,(H8-G8)*I8,(J$7-G8)*I8),0) -> 2480 | K8: =IF(IF(K$7>H8,(H8-G8)*I8,(K$7-G8)*I8)>0,IF(K$7>H8,(H8-G8)*I8,(K$7-G8)*I8),0) -> #REF! | M8: ='Tax Tables'!F6 -> 0 | N8: ='Tax Tables'!G6 -> 12400 | O8: ='Tax Tables'!H6 -> 0.1 | P8: =IF(IF(P$7>N8,(N8-M8)*O8,(P$7-M8)*O8)>0,IF(P$7>N8,(N8-M8)*O8,(P$7-M8)*O8),0) -> 1240 | Q8: =IF(IF(Q$7>N8,(N8-M8)*O8,(Q$7-M8)*O8)>0,IF(Q$7>N8,(N8-M8)*O8,(Q$7-M8)*O8),0) -> #REF!
B9: Interest | C9: ='Strategy comparison'!$C$9 -> 0 | G9: ='Tax Tables'!B7 -> 24801 | H9: ='Tax Tables'!C7 -> 100800 | I9: ='Tax Tables'!D7 -> 0.12 | J9: =IF(IF(J$7>H9,(H9-G9)*I9,(J$7-G9)*I9)>0,IF(J$7>H9,(H9-G9)*I9,(J$7-G9)*I9),0) -> 9119.88 | K9: =IF(IF(K$7>H9,(H9-G9)*I9,(K$7-G9)*I9)>0,IF(K$7>H9,(H9-G9)*I9,(K$7-G9)*I9),0) -> #REF! | M9: ='Tax Tables'!F7 -> 12401 | N9: ='Tax Tables'!G7 -> 50400 | O9: ='Tax Tables'!H7 -> 0.12 | P9: =IF(IF(P$7>N9,(N9-M9)*O9,(P$7-M9)*O9)>0,IF(P$7>N9,(N9-M9)*O9,(P$7-M9)*O9),0) -> 4559.88 | Q9: =IF(IF(Q$7>N9,(N9-M9)*O9,(Q$7-M9)*O9)>0,IF(Q$7>N9,(N9-M9)*O9,(Q$7-M9)*O9),0) -> #REF!
B10: Qualified Dividends | C10: ='Strategy comparison'!$C$10 -> 0 | G10: ='Tax Tables'!B8 -> 100801 | H10: ='Tax Tables'!C8 -> 211400 | I10: ='Tax Tables'!D8 -> 0.22 | J10: =IF(IF(J$7>H10,(H10-G10)*I10,(J$7-G10)*I10)>0,IF(J$7>H10,(H10-G10)*I10,(J$7-G10)*I10),0) -> 24331.78 | K10: =IF(IF(K$7>H10,(H10-G10)*I10,(K$7-G10)*I10)>0,IF(K$7>H10,(H10-G10)*I10,(K$7-G10)*I10),0) -> #REF! | M10: ='Tax Tables'!F8 -> 50401 | N10: ='Tax Tables'!G8 -> 105700 | O10: ='Tax Tables'!H8 -> 0.22 | P10: =IF(IF(P$7>N10,(N10-M10)*O10,(P$7-M10)*O10)>0,IF(P$7>N10,(N10-M10)*O10,(P$7-M10)*O10),0) -> 12165.78 | Q10: =IF(IF(Q$7>N10,(N10-M10)*O10,(Q$7-M10)*O10)>0,IF(Q$7>N10,(N10-M10)*O10,(Q$7-M10)*O10),0) -> #REF!
B11: Nonqualified Dividends | C11: ='Strategy comparison'!$C$11 -> 0 | G11: ='Tax Tables'!B9 -> 211401 | H11: ='Tax Tables'!C9 -> 403550 | I11: ='Tax Tables'!D9 -> 0.24 | J11: =IF(IF(J$7>H11,(H11-G11)*I11,(J$7-G11)*I11)>0,IF(J$7>H11,(H11-G11)*I11,(J$7-G11)*I11),0) -> 46115.76 | K11: =IF(IF(K$7>H11,(H11-G11)*I11,(K$7-G11)*I11)>0,IF(K$7>H11,(H11-G11)*I11,(K$7-G11)*I11),0) -> #REF! | M11: ='Tax Tables'!F9 -> 105701 | N11: ='Tax Tables'!G9 -> 201775 | O11: ='Tax Tables'!H9 -> 0.24 | P11: =IF(IF(P$7>N11,(N11-M11)*O11,(P$7-M11)*O11)>0,IF(P$7>N11,(N11-M11)*O11,(P$7-M11)*O11),0) -> 23057.76 | Q11: =IF(IF(Q$7>N11,(N11-M11)*O11,(Q$7-M11)*O11)>0,IF(Q$7>N11,(N11-M11)*O11,(Q$7-M11)*O11),0) -> #REF!
B12: Ordinary Income | C12: =SUM(C6:C9)+C11 -> 850000 | G12: ='Tax Tables'!B10 -> 403551 | H12: ='Tax Tables'!C10 -> 512450 | I12: ='Tax Tables'!D10 -> 0.32 | J12: =IF(IF(J$7>H12,(H12-G12)*I12,(J$7-G12)*I12)>0,IF(J$7>H12,(H12-G12)*I12,(J$7-G12)*I12),0) -> 34847.68 | K12: =IF(IF(K$7>H12,(H12-G12)*I12,(K$7-G12)*I12)>0,IF(K$7>H12,(H12-G12)*I12,(K$7-G12)*I12),0) -> #REF! | M12: ='Tax Tables'!F10 -> 201776 | N12: ='Tax Tables'!G10 -> 256225 | O12: ='Tax Tables'!H10 -> 0.32 | P12: =IF(IF(P$7>N12,(N12-M12)*O12,(P$7-M12)*O12)>0,IF(P$7>N12,(N12-M12)*O12,(P$7-M12)*O12),0) -> 17423.68 | Q12: =IF(IF(Q$7>N12,(N12-M12)*O12,(Q$7-M12)*O12)>0,IF(Q$7>N12,(N12-M12)*O12,(Q$7-M12)*O12),0) -> #REF!
B13: LTCG | C13: ='Strategy comparison'!C8 -> 0 | G13: ='Tax Tables'!B11 -> 512451 | H13: ='Tax Tables'!C11 -> 768700 | I13: ='Tax Tables'!D11 -> 0.35 | J13: =IF(IF(J$7>H13,(H13-G13)*I13,(J$7-G13)*I13)>0,IF(J$7>H13,(H13-G13)*I13,(J$7-G13)*I13),0) -> 89687.15 | K13: =IF(IF(K$7>H13,(H13-G13)*I13,(K$7-G13)*I13)>0,IF(K$7>H13,(H13-G13)*I13,(K$7-G13)*I13),0) -> #REF! | M13: ='Tax Tables'!F11 -> 256226 | N13: ='Tax Tables'!G11 -> 640600 | O13: ='Tax Tables'!H11 -> 0.35 | P13: =IF(IF(P$7>N13,(N13-M13)*O13,(P$7-M13)*O13)>0,IF(P$7>N13,(N13-M13)*O13,(P$7-M13)*O13),0) -> 134530.9 | Q13: =IF(IF(Q$7>N13,(N13-M13)*O13,(Q$7-M13)*O13)>0,IF(Q$7>N13,(N13-M13)*O13,(Q$7-M13)*O13),0) -> #REF!
B14: LTCG & Qualified Dividends | C14: =C13+C10 -> 0 | G14: ='Tax Tables'!B12 -> 768701 | H14: ='Tax Tables'!C12 -> 99999999999 | I14: ='Tax Tables'!D12 -> 0.37 | J14: =IF(J7>=G14,(J7-G14)*I14,0) -> 30080.63 | K14: =IF(K7>=G14,(K7-G14)*I14,0) -> #REF! | M14: ='Tax Tables'!F12 -> 640601 | N14: ='Tax Tables'!G12 -> 99999999999 | O14: ='Tax Tables'!H12 -> 0.37 | P14: =IF(P7>=M14,(P7-M14)*O14,0) -> 77477.63 | Q14: =IF(Q7>=M14,(Q7-M14)*O14,0) -> #REF!
B15: AGI | C15: =C12+C14 -> 850000
I16: Est. Tax Expense | K16: Difference | O16: Est. Tax Expense | Q16: Difference
I17: =SUM(J8:J14) -> 236662.88 | J17: =SUM(K8:K14) -> #REF! | K17: =I17-J17 -> #REF! | O17: =SUM(P8:P14) -> 270455.63 | P17: =SUM(Q8:Q14) -> #REF! | Q17: =O17-P17 -> #REF!
B18: Summary
B19: Fed Ord. Income Tax | C19: =IF(C5="Married-Joint", I17,O17) -> 236662.88 | G19: Long Term Capital Gains & Qualified Dividends Tax
B20: Fed LTCG & QD Tax | C20: =IF(C5="Married-Joint", I28,O28) -> 0
B21: State Tax | C21: =I42 -> 25500 | G21: Married Filing Joint | J21: LTCG & QD | K21: AGI w Gift | M21: Unmarried/Single | P21: LTCG & QD | Q21: AGI w Gift
B22: NIIT | C22: =I45 -> 22800 | J22: =C14 -> 0 | K22: =J22-IF((#REF!*#REF!)>J7, (#REF!*#REF!)-J7,0) -> #REF! | P22: =J22 -> 0 | Q22: =P22-IF((#REF!*#REF!)>P7, (#REF!*#REF!)-P7,0) -> #REF!
B23: Total | C23: =SUM(C19:C22) -> 284962.88 | G23: ='Tax Tables'!B18 -> 0 | H23: ='Tax Tables'!C18 -> 98900 | I23: ='Tax Tables'!D18 -> 0 | J23: =IF(J$22>$H23,($H23-$G23)*$I23,MAX((J$22-$G23),0)*$I23) -> 0 | K23: =IF(K$22>$H23,($H23-$G23)*$I23,MAX((K$22-$G23),0)*$I23) -> #REF! | M23: ='Tax Tables'!F18 -> 0 | N23: ='Tax Tables'!G18 -> 49450 | O23: ='Tax Tables'!H18 -> 0 | P23: =IF(P$22>$N23,($N23-$M23)*$O23,MAX((P$22-$M23),0)*$O23) -> 0 | Q23: =IF(Q$22>$N23,($N23-$M23)*$O23,MAX((Q$22-$M23),0)*$O23) -> #REF!
G24: ='Tax Tables'!B19 -> 98901 | H24: ='Tax Tables'!C19 -> 613700 | I24: ='Tax Tables'!D19 -> 0.15 | J24: =IF(J$22>$H24,($H24-$G24)*$I24,MAX((J$22-$G24),0)*$I24) -> 0 | K24: =IF(K$22>$H24,($H24-$G24)*$I24,MAX((K$22-$G24),0)*$I24) -> #REF! | M24: ='Tax Tables'!F19 -> 49451 | N24: ='Tax Tables'!G19 -> 545500 | O24: ='Tax Tables'!H19 -> 0.15 | P24: =IF(P$22>$N24,($N24-$M24)*$O24,MAX((P$22-$M24),0)*$O24) -> 0 | Q24: =IF(Q$22>$N24,($N24-$M24)*$O24,MAX((Q$22-$M24),0)*$O24) -> #REF!
G25: ='Tax Tables'!B20 -> 613701 | H25: ='Tax Tables'!C20 -> 99999999999 | I25: ='Tax Tables'!D20 -> 0.2 | J25: =IF(J$22>$H25,($H25-$G25)*$I25,MAX((J$22-$G25),0)*$I25) -> 0 | K25: =IF(K$22>$H25,($H25-$G25)*$I25,MAX((K$22-$G25),0)*$I25) -> #REF! | M25: ='Tax Tables'!F20 -> 545501 | N25: ='Tax Tables'!G20 -> 99999999999 | O25: ='Tax Tables'!H20 -> 0.2 | P25: =IF(P$22>$N25,($N25-$M25)*$O25,MAX((P$22-$M25),0)*$O25) -> 0 | Q25: =IF(Q$22>$N25,($N25-$M25)*$O25,MAX((Q$22-$M25),0)*$O25) -> #REF!
I27: Est. Tax Expense | K27: Difference | O27: Est. Tax Expense | Q27: Difference
I28: =SUM(J23:J25) -> 0 | J28: =SUM(K23:K25) -> #REF! | K28: =I28-J28 -> #REF! | O28: =SUM(P23:P25) -> 0 | P28: =SUM(Q23:Q25) -> #REF! | Q28: =O28-P28 -> #REF!
G30: State Income Tax - Louisiana
G32: Married Filing Joint | J32: AGI | K32: AGI w Depreciation | M32: Unmarried/Single | P32: AGI | Q32: AGI w Depreciation
J33: =C15 -> 850000 | K33: =J33-#REF! -> #REF! | P33: =J33 -> 850000 | Q33: =P33-#REF! -> #REF!
G34: ='Tax Tables'!B25 -> 0 | H34: ='Tax Tables'!C25 -> 100000000 | I34: ='Tax Tables'!D25 -> 0.03 | J34: =IF(IF(J$33>H34,(H34-G34)*I34,(J$33-G34)*I34)>0,IF(J$33>H34,(H34-G34)*I34,(J$33-G34)*I34),0) -> 25500 | K34: =IF(IF(K$33>H34,(H34-G34)*I34,(K$33-G34)*I34)>0,IF(K$33>H34,(H34-G34)*I34,(K$33-G34)*I34),0) -> #REF! | M34: ='Tax Tables'!F25 -> 0 | N34: ='Tax Tables'!G25 -> 100000000 | O34: ='Tax Tables'!H25 -> 0.03 | P34: =IF(IF(P$33>N34,(N34-M34)*O34,(P$33-M34)*O34)>0,IF(P$33>N34,(N34-M34)*O34,(P$33-M34)*O34),0) -> 25500 | Q34: =IF(IF(Q$33>N34,(N34-M34)*O34,(Q$33-M34)*O34)>0,IF(Q$33>N34,(N34-M34)*O34,(Q$33-M34)*O34),0) -> #REF!
G35: ='Tax Tables'!B26 -> 0 | H35: ='Tax Tables'!C26 -> 0 | I35: ='Tax Tables'!D26 -> 0 | J35: =IF(IF(J$33>H35,(H35-G35)*I35,(J$33-G35)*I35)>0,IF(J$33>H35,(H35-G35)*I35,(J$33-G35)*I35),0) -> 0 | K35: =IF(IF(K$33>H35,(H35-G35)*I35,(K$33-G35)*I35)>0,IF(K$33>H35,(H35-G35)*I35,(K$33-G35)*I35),0) -> #REF! | M35: ='Tax Tables'!F26 -> 0 | N35: ='Tax Tables'!G26 -> 0 | O35: ='Tax Tables'!H26 -> 0 | P35: =IF(IF(P$33>N35,(N35-M35)*O35,(P$33-M35)*O35)>0,IF(P$33>N35,(N35-M35)*O35,(P$33-M35)*O35),0) -> 0 | Q35: =IF(IF(Q$33>N35,(N35-M35)*O35,(Q$33-M35)*O35)>0,IF(Q$33>N35,(N35-M35)*O35,(Q$33-M35)*O35),0) -> #REF!
G36: ='Tax Tables'!B27 -> 0 | H36: ='Tax Tables'!C27 -> 0 | I36: ='Tax Tables'!D27 -> 0 | J36: =IF(IF(J$33>H36,(H36-G36)*I36,(J$33-G36)*I36)>0,IF(J$33>H36,(H36-G36)*I36,(J$33-G36)*I36),0) -> 0 | K36: =IF(IF(K$33>H36,(H36-G36)*I36,(K$33-G36)*I36)>0,IF(K$33>H36,(H36-G36)*I36,(K$33-G36)*I36),0) -> #REF! | M36: ='Tax Tables'!F27 -> 0 | N36: ='Tax Tables'!G27 -> 0 | O36: ='Tax Tables'!H27 -> 0 | P36: =IF(IF(P$33>N36,(N36-M36)*O36,(P$33-M36)*O36)>0,IF(P$33>N36,(N36-M36)*O36,(P$33-M36)*O36),0) -> 0 | Q36: =IF(IF(Q$33>N36,(N36-M36)*O36,(Q$33-M36)*O36)>0,IF(Q$33>N36,(N36-M36)*O36,(Q$33-M36)*O36),0) -> #REF!
G37: ='Tax Tables'!B28 -> 0 | H37: ='Tax Tables'!C28 -> 0 | I37: ='Tax Tables'!D28 -> 0 | J37: =IF(IF(J$33>H37,(H37-G37)*I37,(J$33-G37)*I37)>0,IF(J$33>H37,(H37-G37)*I37,(J$33-G37)*I37),0) -> 0 | K37: =IF(IF(K$33>H37,(H37-G37)*I37,(K$33-G37)*I37)>0,IF(K$33>H37,(H37-G37)*I37,(K$33-G37)*I37),0) -> #REF! | M37: ='Tax Tables'!F28 -> 0 | N37: ='Tax Tables'!G28 -> 0 | O37: ='Tax Tables'!H28 -> 0 | P37: =IF(IF(P$33>N37,(N37-M37)*O37,(P$33-M37)*O37)>0,IF(P$33>N37,(N37-M37)*O37,(P$33-M37)*O37),0) -> 0 | Q37: =IF(IF(Q$33>N37,(N37-M37)*O37,(Q$33-M37)*O37)>0,IF(Q$33>N37,(N37-M37)*O37,(Q$33-M37)*O37),0) -> #REF!
G38: ='Tax Tables'!B29 -> 0 | H38: ='Tax Tables'!C29 -> 0 | I38: ='Tax Tables'!D29 -> 0 | J38: =IF(IF(J$33>H38,(H38-G38)*I38,(J$33-G38)*I38)>0,IF(J$33>H38,(H38-G38)*I38,(J$33-G38)*I38),0) -> 0 | K38: =IF(IF(K$33>H38,(H38-G38)*I38,(K$33-G38)*I38)>0,IF(K$33>H38,(H38-G38)*I38,(K$33-G38)*I38),0) -> #REF! | M38: ='Tax Tables'!F29 -> 0 | N38: ='Tax Tables'!G29 -> 0 | O38: ='Tax Tables'!H29 -> 0 | P38: =IF(IF(P$33>N38,(N38-M38)*O38,(P$33-M38)*O38)>0,IF(P$33>N38,(N38-M38)*O38,(P$33-M38)*O38),0) -> 0 | Q38: =IF(IF(Q$33>N38,(N38-M38)*O38,(Q$33-M38)*O38)>0,IF(Q$33>N38,(N38-M38)*O38,(Q$33-M38)*O38),0) -> #REF!
G39: ='Tax Tables'!B30 -> 0 | H39: ='Tax Tables'!C30 -> 0 | I39: ='Tax Tables'!D30 -> 0 | J39: =IF(J33>=G39,(J33-G39)*I39,0) -> 0 | K39: =IF(K33>=G39,(K33-G39)*I39,0) -> #REF! | M39: ='Tax Tables'!F30 -> 0 | N39: ='Tax Tables'!G30 -> 0 | O39: ='Tax Tables'!H30 -> 0 | P39: =IF(P33>=M39,(P33-M39)*O39,0) -> 0 | Q39: =IF(Q33>=M39,(Q33-M39)*O39,0) -> #REF!
I41: Est. Tax Expense | K41: Difference | O41: Est. Tax Expense | Q41: Difference
I42: =SUM(J34:J39) -> 25500 | J42: =SUM(K34:K39) -> #REF! | K42: =I42-J42 -> #REF! | O42: =SUM(P34:P39) -> 25500 | P42: =SUM(Q34:Q39) -> #REF! | Q42: =O42-P42 -> #REF!
H44: NIIT | I44: ='Tax Tables'!$C$34 -> 0.038
H45: =SUM(C8:C11)+C13 -> 0 | I45: =IF(C15-IF(C5="Married-Joint",250000,200000)>H45,(C15-IF(C5="Married-Joint",250000,200000))*I44, H45*I44) -> 22800

Sheet RMD Simulation
A1: Roth conversion calc (no savings) | P1: RMD calc | AA1: Roth calc (no tax savings) | AL1: Roth calc w/ Tax Savings
P2: Age | Q2: RMD % | R2: withdrawal rate | S2: non roth Account value (pre withdrawal) | T2: non roth Account value (post withdrawal) | U2: pre tax Income | V2: Incremental tax rate | W2: post tax income | X2: tax | Y2: taxable account | AA2: Age | AB2: RMD % | AC2: withdrawal rate | AD2: roth Account value (pre withdrawal) | AE2: roth Account value (post withdrawal) | AF2: pre tax Income | AG2: Incremental tax rate | AH2: post tax income | AI2: tax | AJ2: taxable account | AL2: Age | AM2: RMD % | AN2: withdrawal rate | AO2: roth Account value (pre withdrawal) | AP2: roth Account value (post withdrawal) | AQ2: pre tax Income | AR2: Incremental tax rate | AS2: post tax income | AT2: tax | AU2: taxable account
A3: Non Roth value | B3: ='Roth comparison'!C2 -> 450000 | P3: 35 | R3: =IF(P3<$B$9, 0, MAX(Q3,$B$10)) -> 0 | S3: =IF(P3=$B$4,$B$3,"") | T3: =IFERROR((1-R3)*S3,"") | U3: =IFERROR(R3*S3,0) -> 0 | V3: =$B$21 -> 0.35 | W3: =IF(P3<$B$4,0,(1-V3)*U3) -> 0 | X3: =IF(P3<$B$4,"",IF(P3=$B$4,"",IFERROR(U3*V3,0))) | Y3: =IF(W3>0, IF(Y2="",W3, (Y2*(1+$B$8)+W3)),"") | AA3: 35 | AC3: =IF(AA3<$B$9, 0, MAX(AB3,$B$10)) -> 0 | AD3: =IF(AA3=$B$4,$B$16,"") | AE3: =IFERROR((1-AC3)*AD3,"") | AF3: =IFERROR(AC3*AD3,0) -> 0 | AG3: 0 | AH3: =IF(AA3<$B$4,0,(1-AG3)*AF3) -> 0 | AI3: =IF(AA3=$B$4,$B$14,0) -> 0 | AJ3: =IF(AH3>0, IF(AJ2="",AH3, (AJ2*(1+$B$8)+AH3)),"") | AL3: 35 | AN3: =IF(AL3<$B$9, 0, MAX(AM3,$B$10)) -> 0 | AO3: =IF(AL3=$B$4,$B$16,"") | AP3: =IFERROR((1-AN3)*AO3,"") | AQ3: =IFERROR(AN3*AO3,0) -> 0 | AR3: 0 | AS3: =IF(AL3<$B$4,0,(1-AR3)*AQ3) -> 0 | AT3: =IF(AL3=$B$4,$B$14,0) -> 0 | AU3: =IF(AS3>0, IF(AU2="",AS3, (AU2*(1+$B$8)+AS3)),"")
A4: Age | B4: ='Roth comparison'!C3 -> 65 | D4: Federal Ordinary Income Tax | P4: 36 | R4: =IF(P4<$B$9, 0, MAX(Q4,$B$10)) -> 0 | S4: =IF(S3="",IF(P4=$B$4,$B$3,""),T3*(1+$B$8)) | T4: =IFERROR((1-R4)*S4,"") | U4: =IFERROR(R4*S4,0) -> 0 | V4: =$B$21 -> 0.35 | W4: =IF(P4<$B$4,0,(1-V4)*U4) -> 0 | X4: =IF(P4<$B$4,"",IF(P4=$B$4,"",IFERROR(U4*V4,0))) | Y4: =IF(W4>0, IF(Y3="",W4, (Y3*(1+$B$8)+W4)),"") | AA4: 36 | AC4: =IF(AA4<$B$9, 0, MAX(AB4,$B$10)) -> 0 | AD4: =IF(AA4=$B$4,$B$16,IF(AD3="","",AE3*(1+$B$8))) | AE4: =IFERROR((1-AC4)*AD4,"") | AF4: =IFERROR(AC4*AD4,0) -> 0 | AG4: 0 | AH4: =IF(AA4<$B$4,0,(1-AG4)*AF4) -> 0 | AI4: =IF(AA4=$B$4,$B$14,0) -> 0 | AJ4: =IF(AH4>0, IF(AJ3="",AH4, (AJ3*(1+$B$8)+AH4)),"") | AL4: 36 | AN4: =IF(AL4<$B$9, 0, MAX(AM4,$B$10)) -> 0 | AO4: =IF(AL4=$B$4,$B$16+$B$28,IF(AO3="","",AP3*(1+$B$8))) | AP4: =IFERROR((1-AN4)*AO4,"") | AQ4: =IFERROR(AN4*AO4,0) -> 0 | AR4: 0 | AS4: =IF(AL4<$B$4,0,(1-AR4)*AQ4) -> 0 | AT4: =IF(AL4=$B$4,$B$14,0) -> 0 | AU4: =IF(AS4>0, IF(AU3="",AS4, (AU3*(1+$B$8)+AS4)),"")
A5: Other income | B5: ='No planning'!C15 -> 400000 | P5: 37 | R5: =IF(P5<$B$9, 0, MAX(Q5,$B$10)) -> 0 | S5: =IF(S4="",IF(P5=$B$4,$B$3,""),T4*(1+$B$8)) | T5: =IFERROR((1-R5)*S5,"") | U5: =IFERROR(R5*S5,0) -> 0 | V5: =$B$21 -> 0.35 | W5: =IF(P5<$B$4,0,(1-V5)*U5) -> 0 | X5: =IF(P5<$B$4,"",IF(P5=$B$4,"",IFERROR(U5*V5,0))) | Y5: =IF(W5>0, IF(Y4="",W5, (Y4*(1+$B$8)+W5)),"") | AA5: 37 | AC5: =IF(AA5<$B$9, 0, MAX(AB5,$B$10)) -> 0 | AD5: =IF(AA5=$B$4,$B$16,IF(AD4="","",AE4*(1+$B$8))) | AE5: =IFERROR((1-AC5)*AD5,"") | AF5: =IFERROR(AC5*AD5,0) -> 0 | AG5: 0 | AH5: =IF(AA5<$B$4,0,(1-AG5)*AF5) -> 0 | AI5: =IF(AA5=$B$4,$B$14,0) -> 0 | AJ5: =IF(AH5>0, IF(AJ4="",AH5, (AJ4*(1+$B$8)+AH5)),"") | AL5: 37 | AN5: =IF(AL5<$B$9, 0, MAX(AM5,$B$10)) -> 0 | AO5: =IF(AL5=$B$4,$B$16+$B$28,IF(AO4="","",AP4*(1+$B$8))) | AP5: =IFERROR((1-AN5)*AO5,"") | AQ5: =IFERROR(AN5*AO5,0) -> 0 | AR5: 0 | AS5: =IF(AL5<$B$4,0,(1-AR5)*AQ5) -> 0 | AT5: =IF(AL5=$B$4,$B$14,0) -> 0 | AU5: =IF(AS5>0, IF(AU4="",AS5, (AU4*(1+$B$8)+AS5)),"")
A6: Total income | B6: =B3+B5 -> 850000 | D6: Married Filing Joint | G6: Total income | H6: Other income | J6: Unmarried/Single | M6: Ordinary Income | N6: Ordinary Income w Filn | P6: 38 | R6: =IF(P6<$B$9, 0, MAX(Q6,$B$10)) -> 0 | S6: =IF(S5="",IF(P6=$B$4,$B$3,""),T5*(1+$B$8)) | T6: =IFERROR((1-R6)*S6,"") | U6: =IFERROR(R6*S6,0) -> 0 | V6: =$B$21 -> 0.35 | W6: =IF(P6<$B$4,0,(1-V6)*U6) -> 0 | X6: =IF(P6<$B$4,"",IF(P6=$B$4,"",IFERROR(U6*V6,0))) | Y6: =IF(W6>0, IF(Y5="",W6, (Y5*(1+$B$8)+W6)),"") | AA6: 38 | AC6: =IF(AA6<$B$9, 0, MAX(AB6,$B$10)) -> 0 | AD6: =IF(AA6=$B$4,$B$16,IF(AD5="","",AE5*(1+$B$8))) | AE6: =IFERROR((1-AC6)*AD6,"") | AF6: =IFERROR(AC6*AD6,0) -> 0 | AG6: 0 | AH6: =IF(AA6<$B$4,0,(1-AG6)*AF6) -> 0 | AI6: =IF(AA6=$B$4,$B$14,0) -> 0 | AJ6: =IF(AH6>0, IF(AJ5="",AH6, (AJ5*(1+$B$8)+AH6)),"") | AL6: 38 | AN6: =IF(AL6<$B$9, 0, MAX(AM6,$B$10)) -> 0 | AO6: =IF(AL6=$B$4,$B$16+$B$28,IF(AO5="","",AP5*(1+$B$8))) | AP6: =IFERROR((1-AN6)*AO6,"") | AQ6: =IFERROR(AN6*AO6,0) -> 0 | AR6: 0 | AS6: =IF(AL6<$B$4,0,(1-AR6)*AQ6) -> 0 | AT6: =IF(AL6=$B$4,$B$14,0) -> 0 | AU6: =IF(AS6>0, IF(AU5="",AS6, (AU5*(1+$B$8)+AS6)),"")
A7: Filing status | B7: ='Strategy comparison'!C4 -> Married-Joint | G7: =B6 -> 850000 | H7: =B5 -> 400000 | M7: =G7 -> 850000 | N7: =H7 -> 400000 | P7: 39 | R7: =IF(P7<$B$9, 0, MAX(Q7,$B$10)) -> 0 | S7: =IF(S6="",IF(P7=$B$4,$B$3,""),T6*(1+$B$8)) | T7: =IFERROR((1-R7)*S7,"") | U7: =IFERROR(R7*S7,0) -> 0 | V7: =$B$21 -> 0.35 | W7: =IF(P7<$B$4,0,(1-V7)*U7) -> 0 | X7: =IF(P7<$B$4,"",IF(P7=$B$4,"",IFERROR(U7*V7,0))) | Y7: =IF(W7>0, IF(Y6="",W7, (Y6*(1+$B$8)+W7)),"") | AA7: 39 | AC7: =IF(AA7<$B$9, 0, MAX(AB7,$B$10)) -> 0 | AD7: =IF(AA7=$B$4,$B$16,IF(AD6="","",AE6*(1+$B$8))) | AE7: =IFERROR((1-AC7)*AD7,"") | AF7: =IFERROR(AC7*AD7,0) -> 0 | AG7: 0 | AH7: =IF(AA7<$B$4,0,(1-AG7)*AF7) -> 0 | AI7: =IF(AA7=$B$4,$B$14,0) -> 0 | AJ7: =IF(AH7>0, IF(AJ6="",AH7, (AJ6*(1+$B$8)+AH7)),"") | AL7: 39 | AN7: =IF(AL7<$B$9, 0, MAX(AM7,$B$10)) -> 0 | AO7: =IF(AL7=$B$4,$B$16+$B$28,IF(AO6="","",AP6*(1+$B$8))) | AP7: =IFERROR((1-AN7)*AO7,"") | AQ7: =IFERROR(AN7*AO7,0) -> 0 | AR7: 0 | AS7: =IF(AL7<$B$4,0,(1-AR7)*AQ7) -> 0 | AT7: =IF(AL7=$B$4,$B$14,0) -> 0 | AU7: =IF(AS7>0, IF(AU6="",AS7, (AU6*(1+$B$8)+AS7)),"")
A8: IRR | B8: =IF('Roth comparison'!C9="", 0.07,'Roth comparison'!C9) -> 0.07 | D8: ='Tax Tables'!B6 -> 0 | E8: ='Tax Tables'!C6 -> 24800 | F8: ='Tax Tables'!D6 -> 0.1 | G8: =IF(IF(G$7>E8,(E8-D8)*F8,(G$7-D8)*F8)>0,IF(G$7>E8,(E8-D8)*F8,(G$7-D8)*F8),0) -> 2480 | H8: =IF(IF(H$7>E8,(E8-D8)*F8,(H$7-D8)*F8)>0,IF(H$7>E8,(E8-D8)*F8,(H$7-D8)*F8),0) -> 2480 | J8: ='Tax Tables'!F6 -> 0 | K8: ='Tax Tables'!G6 -> 12400 | L8: ='Tax Tables'!H6 -> 0.1 | M8: =IF(IF(M$7>K8,(K8-J8)*L8,(M$7-J8)*L8)>0,IF(M$7>K8,(K8-J8)*L8,(M$7-J8)*L8),0) -> 1240 | N8: =IF(IF(N$7>K8,(K8-J8)*L8,(N$7-J8)*L8)>0,IF(N$7>K8,(K8-J8)*L8,(N$7-J8)*L8),0) -> 1240 | P8: 40 | R8: =IF(P8<$B$9, 0, MAX(Q8,$B$10)) -> 0 | S8: =IF(S7="",IF(P8=$B$4,$B$3,""),T7*(1+$B$8)) | T8: =IFERROR((1-R8)*S8,"") | U8: =IFERROR(R8*S8,0) -> 0 | V8: =$B$21 -> 0.35 | W8: =IF(P8<$B$4,0,(1-V8)*U8) -> 0 | X8: =IF(P8<$B$4,"",IF(P8=$B$4,"",IFERROR(U8*V8,0))) | Y8: =IF(W8>0, IF(Y7="",W8, (Y7*(1+$B$8)+W8)),"") | AA8: 40 | AC8: =IF(AA8<$B$9, 0, MAX(AB8,$B$10)) -> 0 | AD8: =IF(AA8=$B$4,$B$16,IF(AD7="","",AE7*(1+$B$8))) | AE8: =IFERROR((1-AC8)*AD8,"") | AF8: =IFERROR(AC8*AD8,0) -> 0 | AG8: 0 | AH8: =IF(AA8<$B$4,0,(1-AG8)*AF8) -> 0 | AI8: =IF(AA8=$B$4,$B$14,0) -> 0 | AJ8: =IF(AH8>0, IF(AJ7="",AH8, (AJ7*(1+$B$8)+AH8)),"") | AL8: 40 | AN8: =IF(AL8<$B$9, 0, MAX(AM8,$B$10)) -> 0 | AO8: =IF(AL8=$B$4,$B$16+$B$28,IF(AO7="","",AP7*(1+$B$8))) | AP8: =IFERROR((1-AN8)*AO8,"") | AQ8: =IFERROR(AN8*AO8,0) -> 0 | AR8: 0 | AS8: =IF(AL8<$B$4,0,(1-AR8)*AQ8) -> 0 | AT8: =IF(AL8=$B$4,$B$14,0) -> 0 | AU8: =IF(AS8>0, IF(AU7="",AS8, (AU7*(1+$B$8)+AS8)),"")
A9: ='Roth comparison'!B4 -> Retirement age | B9: ='Roth comparison'!C4 -> 65 | D9: ='Tax Tables'!B7 -> 24801 | E9: ='Tax Tables'!C7 -> 100800 | F9: ='Tax Tables'!D7 -> 0.12 | G9: =IF(IF(G$7>E9,(E9-D9)*F9,(G$7-D9)*F9)>0,IF(G$7>E9,(E9-D9)*F9,(G$7-D9)*F9),0) -> 9119.88 | H9: =IF(IF(H$7>E9,(E9-D9)*F9,(H$7-D9)*F9)>0,IF(H$7>E9,(E9-D9)*F9,(H$7-D9)*F9),0) -> 9119.88 | J9: ='Tax Tables'!F7 -> 12401 | K9: ='Tax Tables'!G7 -> 50400 | L9: ='Tax Tables'!H7 -> 0.12 | M9: =IF(IF(M$7>K9,(K9-J9)*L9,(M$7-J9)*L9)>0,IF(M$7>K9,(K9-J9)*L9,(M$7-J9)*L9),0) -> 4559.88 | N9: =IF(IF(N$7>K9,(K9-J9)*L9,(N$7-J9)*L9)>0,IF(N$7>K9,(K9-J9)*L9,(N$7-J9)*L9),0) -> 4559.88 | P9: 41 | R9: =IF(P9<$B$9, 0, MAX(Q9,$B$10)) -> 0 | S9: =IF(S8="",IF(P9=$B$4,$B$3,""),T8*(1+$B$8)) | T9: =IFERROR((1-R9)*S9,"") | U9: =IFERROR(R9*S9,0) -> 0 | V9: =$B$21 -> 0.35 | W9: =IF(P9<$B$4,0,(1-V9)*U9) -> 0 | X9: =IF(P9<$B$4,"",IF(P9=$B$4,"",IFERROR(U9*V9,0))) | Y9: =IF(W9>0, IF(Y8="",W9, (Y8*(1+$B$8)+W9)),"") | AA9: 41 | AC9: =IF(AA9<$B$9, 0, MAX(AB9,$B$10)) -> 0 | AD9: =IF(AA9=$B$4,$B$16,IF(AD8="","",AE8*(1+$B$8))) | AE9: =IFERROR((1-AC9)*AD9,"") | AF9: =IFERROR(AC9*AD9,0) -> 0 | AG9: 0 | AH9: =IF(AA9<$B$4,0,(1-AG9)*AF9) -> 0 | AI9: =IF(AA9=$B$4,$B$14,0) -> 0 | AJ9: =IF(AH9>0, IF(AJ8="",AH9, (AJ8*(1+$B$8)+AH9)),"") | AL9: 41 | AN9: =IF(AL9<$B$9, 0, MAX(AM9,$B$10)) -> 0 | AO9: =IF(AL9=$B$4,$B$16+$B$28,IF(AO8="","",AP8*(1+$B$8))) | AP9: =IFERROR((1-AN9)*AO9,"") | AQ9: =IFERROR(AN9*AO9,0) -> 0 | AR9: 0 | AS9: =IF(AL9<$B$4,0,(1-AR9)*AQ9) -> 0 | AT9: =IF(AL9=$B$4,$B$14,0) -> 0 | AU9: =IF(AS9>0, IF(AU8="",AS9, (AU8*(1+$B$8)+AS9)),"")
A10: ='Roth comparison'!B5 -> Minimum withdrawal rate | B10: ='Roth comparison'!C5 -> 0.04 | D10: ='Tax Tables'!B8 -> 100801 | E10: ='Tax Tables'!C8 -> 211400 | F10: ='Tax Tables'!D8 -> 0.22 | G10: =IF(IF(G$7>E10,(E10-D10)*F10,(G$7-D10)*F10)>0,IF(G$7>E10,(E10-D10)*F10,(G$7-D10)*F10),0) -> 24331.78 | H10: =IF(IF(H$7>E10,(E10-D10)*F10,(H$7-D10)*F10)>0,IF(H$7>E10,(E10-D10)*F10,(H$7-D10)*F10),0) -> 24331.78 | J10: ='Tax Tables'!F8 -> 50401 | K10: ='Tax Tables'!G8 -> 105700 | L10: ='Tax Tables'!H8 -> 0.22 | M10: =IF(IF(M$7>K10,(K10-J10)*L10,(M$7-J10)*L10)>0,IF(M$7>K10,(K10-J10)*L10,(M$7-J10)*L10),0) -> 12165.78 | N10: =IF(IF(N$7>K10,(K10-J10)*L10,(N$7-J10)*L10)>0,IF(N$7>K10,(K10-J10)*L10,(N$7-J10)*L10),0) -> 12165.78 | P10: 42 | R10: =IF(P10<$B$9, 0, MAX(Q10,$B$10)) -> 0 | S10: =IF(S9="",IF(P10=$B$4,$B$3,""),T9*(1+$B$8)) | T10: =IFERROR((1-R10)*S10,"") | U10: =IFERROR(R10*S10,0) -> 0 | V10: =$B$21 -> 0.35 | W10: =IF(P10<$B$4,0,(1-V10)*U10) -> 0 | X10: =IF(P10<$B$4,"",IF(P10=$B$4,"",IFERROR(U10*V10,0))) | Y10: =IF(W10>0, IF(Y9="",W10, (Y9*(1+$B$8)+W10)),"") | AA10: 42 | AC10: =IF(AA10<$B$9, 0, MAX(AB10,$B$10)) -> 0 | AD10: =IF(AA10=$B$4,$B$16,IF(AD9="","",AE9*(1+$B$8))) | AE10: =IFERROR((1-AC10)*AD10,"") | AF10: =IFERROR(AC10*AD10,0) -> 0 | AG10: 0 | AH10: =IF(AA10<$B$4,0,(1-AG10)*AF10) -> 0 | AI10: =IF(AA10=$B$4,$B$14,0) -> 0 | AJ10: =IF(AH10>0, IF(AJ9="",AH10, (AJ9*(1+$B$8)+AH10)),"") | AL10: 42 | AN10: =IF(AL10<$B$9, 0, MAX(AM10,$B$10)) -> 0 | AO10: =IF(AL10=$B$4,$B$16+$B$28,IF(AO9="","",AP9*(1+$B$8))) | AP10: =IFERROR((1-AN10)*AO10,"") | AQ10: =IFERROR(AN10*AO10,0) -> 0 | AR10: 0 | AS10: =IF(AL10<$B$4,0,(1-AR10)*AQ10) -> 0 | AT10: =IF(AL10=$B$4,$B$14,0) -> 0 | AU10: =IF(AS10>0, IF(AU9="",AS10, (AU9*(1+$B$8)+AS10)),"")
D11: ='Tax Tables'!B9 -> 211401 | E11: ='Tax Tables'!C9 -> 403550 | F11: ='Tax Tables'!D9 -> 0.24 | G11: =IF(IF(G$7>E11,(E11-D11)*F11,(G$7-D11)*F11)>0,IF(G$7>E11,(E11-D11)*F11,(G$7-D11)*F11),0) -> 46115.76 | H11: =IF(IF(H$7>E11,(E11-D11)*F11,(H$7-D11)*F11)>0,IF(H$7>E11,(E11-D11)*F11,(H$7-D11)*F11),0) -> 45263.76 | J11: ='Tax Tables'!F9 -> 105701 | K11: ='Tax Tables'!G9 -> 201775 | L11: ='Tax Tables'!H9 -> 0.24 | M11: =IF(IF(M$7>K11,(K11-J11)*L11,(M$7-J11)*L11)>0,IF(M$7>K11,(K11-J11)*L11,(M$7-J11)*L11),0) -> 23057.76 | N11: =IF(IF(N$7>K11,(K11-J11)*L11,(N$7-J11)*L11)>0,IF(N$7>K11,(K11-J11)*L11,(N$7-J11)*L11),0) -> 23057.76 | P11: 43 | R11: =IF(P11<$B$9, 0, MAX(Q11,$B$10)) -> 0 | S11: =IF(S10="",IF(P11=$B$4,$B$3,""),T10*(1+$B$8)) | T11: =IFERROR((1-R11)*S11,"") | U11: =IFERROR(R11*S11,0) -> 0 | V11: =$B$21 -> 0.35 | W11: =IF(P11<$B$4,0,(1-V11)*U11) -> 0 | X11: =IF(P11<$B$4,"",IF(P11=$B$4,"",IFERROR(U11*V11,0))) | Y11: =IF(W11>0, IF(Y10="",W11, (Y10*(1+$B$8)+W11)),"") | AA11: 43 | AC11: =IF(AA11<$B$9, 0, MAX(AB11,$B$10)) -> 0 | AD11: =IF(AA11=$B$4,$B$16,IF(AD10="","",AE10*(1+$B$8))) | AE11: =IFERROR((1-AC11)*AD11,"") | AF11: =IFERROR(AC11*AD11,0) -> 0 | AG11: 0 | AH11: =IF(AA11<$B$4,0,(1-AG11)*AF11) -> 0 | AI11: =IF(AA11=$B$4,$B$14,0) -> 0 | AJ11: =IF(AH11>0, IF(AJ10="",AH11, (AJ10*(1+$B$8)+AH11)),"") | AL11: 43 | AN11: =IF(AL11<$B$9, 0, MAX(AM11,$B$10)) -> 0 | AO11: =IF(AL11=$B$4,$B$16+$B$28,IF(AO10="","",AP10*(1+$B$8))) | AP11: =IFERROR((1-AN11)*AO11,"") | AQ11: =IFERROR(AN11*AO11,0) -> 0 | AR11: 0 | AS11: =IF(AL11<$B$4,0,(1-AR11)*AQ11) -> 0 | AT11: =IF(AL11=$B$4,$B$14,0) -> 0 | AU11: =IF(AS11>0, IF(AU10="",AS11, (AU10*(1+$B$8)+AS11)),"")
A12: incremental fed tax | B12: =IF(B7="Married-Joint", H17,IF(B7="Single",N17,"Filing status?")) -> 155467.46 | D12: ='Tax Tables'!B10 -> 403551 | E12: ='Tax Tables'!C10 -> 512450 | F12: ='Tax Tables'!D10 -> 0.32 | G12: =IF(IF(G$7>E12,(E12-D12)*F12,(G$7-D12)*F12)>0,IF(G$7>E12,(E12-D12)*F12,(G$7-D12)*F12),0) -> 34847.68 | H12: =IF(IF(H$7>E12,(E12-D12)*F12,(H$7-D12)*F12)>0,IF(H$7>E12,(E12-D12)*F12,(H$7-D12)*F12),0) -> 0 | J12: ='Tax Tables'!F10 -> 201776 | K12: ='Tax Tables'!G10 -> 256225 | L12: ='Tax Tables'!H10 -> 0.32 | M12: =IF(IF(M$7>K12,(K12-J12)*L12,(M$7-J12)*L12)>0,IF(M$7>K12,(K12-J12)*L12,(M$7-J12)*L12),0) -> 17423.68 | N12: =IF(IF(N$7>K12,(K12-J12)*L12,(N$7-J12)*L12)>0,IF(N$7>K12,(K12-J12)*L12,(N$7-J12)*L12),0) -> 17423.68 | P12: 44 | R12: =IF(P12<$B$9, 0, MAX(Q12,$B$10)) -> 0 | S12: =IF(S11="",IF(P12=$B$4,$B$3,""),T11*(1+$B$8)) | T12: =IFERROR((1-R12)*S12,"") | U12: =IFERROR(R12*S12,0) -> 0 | V12: =$B$21 -> 0.35 | W12: =IF(P12<$B$4,0,(1-V12)*U12) -> 0 | X12: =IF(P12<$B$4,"",IF(P12=$B$4,"",IFERROR(U12*V12,0))) | Y12: =IF(W12>0, IF(Y11="",W12, (Y11*(1+$B$8)+W12)),"") | AA12: 44 | AC12: =IF(AA12<$B$9, 0, MAX(AB12,$B$10)) -> 0 | AD12: =IF(AA12=$B$4,$B$16,IF(AD11="","",AE11*(1+$B$8))) | AE12: =IFERROR((1-AC12)*AD12,"") | AF12: =IFERROR(AC12*AD12,0) -> 0 | AG12: 0 | AH12: =IF(AA12<$B$4,0,(1-AG12)*AF12) -> 0 | AI12: =IF(AA12=$B$4,$B$14,0) -> 0 | AJ12: =IF(AH12>0, IF(AJ11="",AH12, (AJ11*(1+$B$8)+AH12)),"") | AL12: 44 | AN12: =IF(AL12<$B$9, 0, MAX(AM12,$B$10)) -> 0 | AO12: =IF(AL12=$B$4,$B$16+$B$28,IF(AO11="","",AP11*(1+$B$8))) | AP12: =IFERROR((1-AN12)*AO12,"") | AQ12: =IFERROR(AN12*AO12,0) -> 0 | AR12: 0 | AS12: =IF(AL12<$B$4,0,(1-AR12)*AQ12) -> 0 | AT12: =IF(AL12=$B$4,$B$14,0) -> 0 | AU12: =IF(AS12>0, IF(AU11="",AS12, (AU11*(1+$B$8)+AS12)),"")
A13: incremental state tax | B13: =IF(B7="Married-Joint", H32,IF(B7="Single",N32,"Filing status?")) -> 13500 | D13: ='Tax Tables'!B11 -> 512451 | E13: ='Tax Tables'!C11 -> 768700 | F13: ='Tax Tables'!D11 -> 0.35 | G13: =IF(IF(G$7>E13,(E13-D13)*F13,(G$7-D13)*F13)>0,IF(G$7>E13,(E13-D13)*F13,(G$7-D13)*F13),0) -> 89687.15 | H13: =IF(IF(H$7>E13,(E13-D13)*F13,(H$7-D13)*F13)>0,IF(H$7>E13,(E13-D13)*F13,(H$7-D13)*F13),0) -> 0 | J13: ='Tax Tables'!F11 -> 256226 | K13: ='Tax Tables'!G11 -> 640600 | L13: ='Tax Tables'!H11 -> 0.35 | M13: =IF(IF(M$7>K13,(K13-J13)*L13,(M$7-J13)*L13)>0,IF(M$7>K13,(K13-J13)*L13,(M$7-J13)*L13),0) -> 134530.9 | N13: =IF(IF(N$7>K13,(K13-J13)*L13,(N$7-J13)*L13)>0,IF(N$7>K13,(K13-J13)*L13,(N$7-J13)*L13),0) -> 50320.9 | P13: 45 | R13: =IF(P13<$B$9, 0, MAX(Q13,$B$10)) -> 0 | S13: =IF(S12="",IF(P13=$B$4,$B$3,""),T12*(1+$B$8)) | T13: =IFERROR((1-R13)*S13,"") | U13: =IFERROR(R13*S13,0) -> 0 | V13: =$B$21 -> 0.35 | W13: =IF(P13<$B$4,0,(1-V13)*U13) -> 0 | X13: =IF(P13<$B$4,"",IF(P13=$B$4,"",IFERROR(U13*V13,0))) | Y13: =IF(W13>0, IF(Y12="",W13, (Y12*(1+$B$8)+W13)),"") | AA13: 45 | AC13: =IF(AA13<$B$9, 0, MAX(AB13,$B$10)) -> 0 | AD13: =IF(AA13=$B$4,$B$16,IF(AD12="","",AE12*(1+$B$8))) | AE13: =IFERROR((1-AC13)*AD13,"") | AF13: =IFERROR(AC13*AD13,0) -> 0 | AG13: 0 | AH13: =IF(AA13<$B$4,0,(1-AG13)*AF13) -> 0 | AI13: =IF(AA13=$B$4,$B$14,0) -> 0 | AJ13: =IF(AH13>0, IF(AJ12="",AH13, (AJ12*(1+$B$8)+AH13)),"") | AL13: 45 | AN13: =IF(AL13<$B$9, 0, MAX(AM13,$B$10)) -> 0 | AO13: =IF(AL13=$B$4,$B$16+$B$28,IF(AO12="","",AP12*(1+$B$8))) | AP13: =IFERROR((1-AN13)*AO13,"") | AQ13: =IFERROR(AN13*AO13,0) -> 0 | AR13: 0 | AS13: =IF(AL13<$B$4,0,(1-AR13)*AQ13) -> 0 | AT13: =IF(AL13=$B$4,$B$14,0) -> 0 | AU13: =IF(AS13>0, IF(AU12="",AS13, (AU12*(1+$B$8)+AS13)),"")
A14: total incremental tax | B14: =SUM(B12:B13) -> 168967.46 | D14: ='Tax Tables'!B12 -> 768701 | E14: ='Tax Tables'!C12 -> 99999999999 | F14: ='Tax Tables'!D12 -> 0.37 | G14: =IF(G7>=D14,(G7-D14)*F14,0) -> 30080.63 | H14: =IF(H7>=D14,(H7-D14)*F14,0) -> 0 | J14: ='Tax Tables'!F12 -> 640601 | K14: ='Tax Tables'!G12 -> 99999999999 | L14: ='Tax Tables'!H12 -> 0.37 | M14: =IF(M7>=J14,(M7-J14)*L14,0) -> 77477.63 | N14: =IF(N7>=J14,(N7-J14)*L14,0) -> 0 | P14: 46 | R14: =IF(P14<$B$9, 0, MAX(Q14,$B$10)) -> 0 | S14: =IF(S13="",IF(P14=$B$4,$B$3,""),T13*(1+$B$8)) | T14: =IFERROR((1-R14)*S14,"") | U14: =IFERROR(R14*S14,0) -> 0 | V14: =$B$21 -> 0.35 | W14: =IF(P14<$B$4,0,(1-V14)*U14) -> 0 | X14: =IF(P14<$B$4,"",IF(P14=$B$4,"",IFERROR(U14*V14,0))) | Y14: =IF(W14>0, IF(Y13="",W14, (Y13*(1+$B$8)+W14)),"") | AA14: 46 | AC14: =IF(AA14<$B$9, 0, MAX(AB14,$B$10)) -> 0 | AD14: =IF(AA14=$B$4,$B$16,IF(AD13="","",AE13*(1+$B$8))) | AE14: =IFERROR((1-AC14)*AD14,"") | AF14: =IFERROR(AC14*AD14,0) -> 0 | AG14: 0 | AH14: =IF(AA14<$B$4,0,(1-AG14)*AF14) -> 0 | AI14: =IF(AA14=$B$4,$B$14,0) -> 0 | AJ14: =IF(AH14>0, IF(AJ13="",AH14, (AJ13*(1+$B$8)+AH14)),"") | AL14: 46 | AN14: =IF(AL14<$B$9, 0, MAX(AM14,$B$10)) -> 0 | AO14: =IF(AL14=$B$4,$B$16+$B$28,IF(AO13="","",AP13*(1+$B$8))) | AP14: =IFERROR((1-AN14)*AO14,"") | AQ14: =IFERROR(AN14*AO14,0) -> 0 | AR14: 0 | AS14: =IF(AL14<$B$4,0,(1-AR14)*AQ14) -> 0 | AT14: =IF(AL14=$B$4,$B$14,0) -> 0 | AU14: =IF(AS14>0, IF(AU13="",AS14, (AU13*(1+$B$8)+AS14)),"")
A15: effective marginal tax rate | B15: =B14/B3 -> 0.37548324 | P15: 47 | R15: =IF(P15<$B$9, 0, MAX(Q15,$B$10)) -> 0 | S15: =IF(S14="",IF(P15=$B$4,$B$3,""),T14*(1+$B$8)) | T15: =IFERROR((1-R15)*S15,"") | U15: =IFERROR(R15*S15,0) -> 0 | V15: =$B$21 -> 0.35 | W15: =IF(P15<$B$4,0,(1-V15)*U15) -> 0 | X15: =IF(P15<$B$4,"",IF(P15=$B$4,"",IFERROR(U15*V15,0))) | Y15: =IF(W15>0, IF(Y14="",W15, (Y14*(1+$B$8)+W15)),"") | AA15: 47 | AC15: =IF(AA15<$B$9, 0, MAX(AB15,$B$10)) -> 0 | AD15: =IF(AA15=$B$4,$B$16,IF(AD14="","",AE14*(1+$B$8))) | AE15: =IFERROR((1-AC15)*AD15,"") | AF15: =IFERROR(AC15*AD15,0) -> 0 | AG15: 0 | AH15: =IF(AA15<$B$4,0,(1-AG15)*AF15) -> 0 | AI15: =IF(AA15=$B$4,$B$14,0) -> 0 | AJ15: =IF(AH15>0, IF(AJ14="",AH15, (AJ14*(1+$B$8)+AH15)),"") | AL15: 47 | AN15: =IF(AL15<$B$9, 0, MAX(AM15,$B$10)) -> 0 | AO15: =IF(AL15=$B$4,$B$16+$B$28,IF(AO14="","",AP14*(1+$B$8))) | AP15: =IFERROR((1-AN15)*AO15,"") | AQ15: =IFERROR(AN15*AO15,0) -> 0 | AR15: 0 | AS15: =IF(AL15<$B$4,0,(1-AR15)*AQ15) -> 0 | AT15: =IF(AL15=$B$4,$B$14,0) -> 0 | AU15: =IF(AS15>0, IF(AU14="",AS15, (AU14*(1+$B$8)+AS15)),"")
A16: Proceeds | B16: =B3-B14 -> 281032.54 | F16: Est. Tax Expense | H16: Difference | L16: Est. Tax Expense | N16: Difference | P16: 48 | R16: =IF(P16<$B$9, 0, MAX(Q16,$B$10)) -> 0 | S16: =IF(S15="",IF(P16=$B$4,$B$3,""),T15*(1+$B$8)) | T16: =IFERROR((1-R16)*S16,"") | U16: =IFERROR(R16*S16,0) -> 0 | V16: =$B$21 -> 0.35 | W16: =IF(P16<$B$4,0,(1-V16)*U16) -> 0 | X16: =IF(P16<$B$4,"",IF(P16=$B$4,"",IFERROR(U16*V16,0))) | Y16: =IF(W16>0, IF(Y15="",W16, (Y15*(1+$B$8)+W16)),"") | AA16: 48 | AC16: =IF(AA16<$B$9, 0, MAX(AB16,$B$10)) -> 0 | AD16: =IF(AA16=$B$4,$B$16,IF(AD15="","",AE15*(1+$B$8))) | AE16: =IFERROR((1-AC16)*AD16,"") | AF16: =IFERROR(AC16*AD16,0) -> 0 | AG16: 0 | AH16: =IF(AA16<$B$4,0,(1-AG16)*AF16) -> 0 | AI16: =IF(AA16=$B$4,$B$14,0) -> 0 | AJ16: =IF(AH16>0, IF(AJ15="",AH16, (AJ15*(1+$B$8)+AH16)),"") | AL16: 48 | AN16: =IF(AL16<$B$9, 0, MAX(AM16,$B$10)) -> 0 | AO16: =IF(AL16=$B$4,$B$16+$B$28,IF(AO15="","",AP15*(1+$B$8))) | AP16: =IFERROR((1-AN16)*AO16,"") | AQ16: =IFERROR(AN16*AO16,0) -> 0 | AR16: 0 | AS16: =IF(AL16<$B$4,0,(1-AR16)*AQ16) -> 0 | AT16: =IF(AL16=$B$4,$B$14,0) -> 0 | AU16: =IF(AS16>0, IF(AU15="",AS16, (AU15*(1+$B$8)+AS16)),"")
A17: FV at 100 (proceeds invested) | B17: =FV(B8,100-B4,0,-B16) -> 3000466.8 | F17: =SUM(G8:G14) -> 236662.88 | G17: =SUM(H8:H14) -> 81195.42 | H17: =F17-G17 -> 155467.46 | L17: =SUM(M8:M14) -> 270455.63 | M17: =SUM(N8:N14) -> 108768 | N17: =L17-M17 -> 161687.63 | P17: =P16+1 -> 49 | R17: =IF(P17<$B$9, 0, MAX(Q17,$B$10)) -> 0 | S17: =IF(S16="",IF(P17=$B$4,$B$3,""),T16*(1+$B$8)) | T17: =IFERROR((1-R17)*S17,"") | U17: =IFERROR(R17*S17,0) -> 0 | V17: =$B$21 -> 0.35 | W17: =IF(P17<$B$4,0,(1-V17)*U17) -> 0 | X17: =IF(P17<$B$4,"",IF(P17=$B$4,"",IFERROR(U17*V17,0))) | Y17: =IF(W17>0, IF(Y16="",W17, (Y16*(1+$B$8)+W17)),"") | AA17: =AA16+1 -> 49 | AC17: =IF(AA17<$B$9, 0, MAX(AB17,$B$10)) -> 0 | AD17: =IF(AA17=$B$4,$B$16,IF(AD16="","",AE16*(1+$B$8))) | AE17: =IFERROR((1-AC17)*AD17,"") | AF17: =IFERROR(AC17*AD17,0) -> 0 | AG17: 0 | AH17: =IF(AA17<$B$4,0,(1-AG17)*AF17) -> 0 | AI17: =IF(AA17=$B$4,$B$14,0) -> 0 | AJ17: =IF(AH17>0, IF(AJ16="",AH17, (AJ16*(1+$B$8)+AH17)),"") | AL17: =AL16+1 -> 49 | AN17: =IF(AL17<$B$9, 0, MAX(AM17,$B$10)) -> 0 | AO17: =IF(AL17=$B$4,$B$16+$B$28,IF(AO16="","",AP16*(1+$B$8))) | AP17: =IFERROR((1-AN17)*AO17,"") | AQ17: =IFERROR(AN17*AO17,0) -> 0 | AR17: 0 | AS17: =IF(AL17<$B$4,0,(1-AR17)*AQ17) -> 0 | AT17: =IF(AL17=$B$4,$B$14,0) -> 0 | AU17: =IF(AS17>0, IF(AU16="",AS17, (AU16*(1+$B$8)+AS17)),"")
P18: =P17+1 -> 50 | R18: =IF(P18<$B$9, 0, MAX(Q18,$B$10)) -> 0 | S18: =IF(S17="",IF(P18=$B$4,$B$3,""),T17*(1+$B$8)) | T18: =IFERROR((1-R18)*S18,"") | U18: =IFERROR(R18*S18,0) -> 0 | V18: =$B$21 -> 0.35 | W18: =IF(P18<$B$4,0,(1-V18)*U18) -> 0 | X18: =IF(P18<$B$4,"",IF(P18=$B$4,"",IFERROR(U18*V18,0))) | Y18: =IF(W18>0, IF(Y17="",W18, (Y17*(1+$B$8)+W18)),"") | AA18: =AA17+1 -> 50 | AC18: =IF(AA18<$B$9, 0, MAX(AB18,$B$10)) -> 0 | AD18: =IF(AA18=$B$4,$B$16,IF(AD17="","",AE17*(1+$B$8))) | AE18: =IFERROR((1-AC18)*AD18,"") | AF18: =IFERROR(AC18*AD18,0) -> 0 | AG18: 0 | AH18: =IF(AA18<$B$4,0,(1-AG18)*AF18) -> 0 | AI18: =IF(AA18=$B$4,$B$14,0) -> 0 | AJ18: =IF(AH18>0, IF(AJ17="",AH18, (AJ17*(1+$B$8)+AH18)),"") | AL18: =AL17+1 -> 50 | AN18: =IF(AL18<$B$9, 0, MAX(AM18,$B$10)) -> 0 | AO18: =IF(AL18=$B$4,$B$16+$B$28,IF(AO17="","",AP17*(1+$B$8))) | AP18: =IFERROR((1-AN18)*AO18,"") | AQ18: =IFERROR(AN18*AO18,0) -> 0 | AR18: 0 | AS18: =IF(AL18<$B$4,0,(1-AR18)*AQ18) -> 0 | AT18: =IF(AL18=$B$4,$B$14,0) -> 0 | AU18: =IF(AS18>0, IF(AU17="",AS18, (AU17*(1+$B$8)+AS18)),"")
P19: =P18+1 -> 51 | R19: =IF(P19<$B$9, 0, MAX(Q19,$B$10)) -> 0 | S19: =IF(S18="",IF(P19=$B$4,$B$3,""),T18*(1+$B$8)) | T19: =IFERROR((1-R19)*S19,"") | U19: =IFERROR(R19*S19,0) -> 0 | V19: =$B$21 -> 0.35 | W19: =IF(P19<$B$4,0,(1-V19)*U19) -> 0 | X19: =IF(P19<$B$4,"",IF(P19=$B$4,"",IFERROR(U19*V19,0))) | Y19: =IF(W19>0, IF(Y18="",W19, (Y18*(1+$B$8)+W19)),"") | AA19: =AA18+1 -> 51 | AC19: =IF(AA19<$B$9, 0, MAX(AB19,$B$10)) -> 0 | AD19: =IF(AA19=$B$4,$B$16,IF(AD18="","",AE18*(1+$B$8))) | AE19: =IFERROR((1-AC19)*AD19,"") | AF19: =IFERROR(AC19*AD19,0) -> 0 | AG19: 0 | AH19: =IF(AA19<$B$4,0,(1-AG19)*AF19) -> 0 | AI19: =IF(AA19=$B$4,$B$14,0) -> 0 | AJ19: =IF(AH19>0, IF(AJ18="",AH19, (AJ18*(1+$B$8)+AH19)),"") | AL19: =AL18+1 -> 51 | AN19: =IF(AL19<$B$9, 0, MAX(AM19,$B$10)) -> 0 | AO19: =IF(AL19=$B$4,$B$16+$B$28,IF(AO18="","",AP18*(1+$B$8))) | AP19: =IFERROR((1-AN19)*AO19,"") | AQ19: =IFERROR(AN19*AO19,0) -> 0 | AR19: 0 | AS19: =IF(AL19<$B$4,0,(1-AR19)*AQ19) -> 0 | AT19: =IF(AL19=$B$4,$B$14,0) -> 0 | AU19: =IF(AS19>0, IF(AU18="",AS19, (AU18*(1+$B$8)+AS19)),"")
A20: RMD calc | D20: State Income Tax - Louisiana | P20: =P19+1 -> 52 | R20: =IF(P20<$B$9, 0, MAX(Q20,$B$10)) -> 0 | S20: =IF(S19="",IF(P20=$B$4,$B$3,""),T19*(1+$B$8)) | T20: =IFERROR((1-R20)*S20,"") | U20: =IFERROR(R20*S20,0) -> 0 | V20: =$B$21 -> 0.35 | W20: =IF(P20<$B$4,0,(1-V20)*U20) -> 0 | X20: =IF(P20<$B$4,"",IF(P20=$B$4,"",IFERROR(U20*V20,0))) | Y20: =IF(W20>0, IF(Y19="",W20, (Y19*(1+$B$8)+W20)),"") | AA20: =AA19+1 -> 52 | AC20: =IF(AA20<$B$9, 0, MAX(AB20,$B$10)) -> 0 | AD20: =IF(AA20=$B$4,$B$16,IF(AD19="","",AE19*(1+$B$8))) | AE20: =IFERROR((1-AC20)*AD20,"") | AF20: =IFERROR(AC20*AD20,0) -> 0 | AG20: 0 | AH20: =IF(AA20<$B$4,0,(1-AG20)*AF20) -> 0 | AI20: =IF(AA20=$B$4,$B$14,0) -> 0 | AJ20: =IF(AH20>0, IF(AJ19="",AH20, (AJ19*(1+$B$8)+AH20)),"") | AL20: =AL19+1 -> 52 | AN20: =IF(AL20<$B$9, 0, MAX(AM20,$B$10)) -> 0 | AO20: =IF(AL20=$B$4,$B$16+$B$28,IF(AO19="","",AP19*(1+$B$8))) | AP20: =IFERROR((1-AN20)*AO20,"") | AQ20: =IFERROR(AN20*AO20,0) -> 0 | AR20: 0 | AS20: =IF(AL20<$B$4,0,(1-AR20)*AQ20) -> 0 | AT20: =IF(AL20=$B$4,$B$14,0) -> 0 | AU20: =IF(AS20>0, IF(AU19="",AS20, (AU19*(1+$B$8)+AS20)),"")
A21: incremental tax rate (federal + state) | B21: =IF('Roth comparison'!C8="",B15,'Roth comparison'!C8) -> 0.35 | P21: =P20+1 -> 53 | R21: =IF(P21<$B$9, 0, MAX(Q21,$B$10)) -> 0 | S21: =IF(S20="",IF(P21=$B$4,$B$3,""),T20*(1+$B$8)) | T21: =IFERROR((1-R21)*S21,"") | U21: =IFERROR(R21*S21,0) -> 0 | V21: =$B$21 -> 0.35 | W21: =IF(P21<$B$4,0,(1-V21)*U21) -> 0 | X21: =IF(P21<$B$4,"",IF(P21=$B$4,"",IFERROR(U21*V21,0))) | Y21: =IF(W21>0, IF(Y20="",W21, (Y20*(1+$B$8)+W21)),"") | AA21: =AA20+1 -> 53 | AC21: =IF(AA21<$B$9, 0, MAX(AB21,$B$10)) -> 0 | AD21: =IF(AA21=$B$4,$B$16,IF(AD20="","",AE20*(1+$B$8))) | AE21: =IFERROR((1-AC21)*AD21,"") | AF21: =IFERROR(AC21*AD21,0) -> 0 | AG21: 0 | AH21: =IF(AA21<$B$4,0,(1-AG21)*AF21) -> 0 | AI21: =IF(AA21=$B$4,$B$14,0) -> 0 | AJ21: =IF(AH21>0, IF(AJ20="",AH21, (AJ20*(1+$B$8)+AH21)),"") | AL21: =AL20+1 -> 53 | AN21: =IF(AL21<$B$9, 0, MAX(AM21,$B$10)) -> 0 | AO21: =IF(AL21=$B$4,$B$16+$B$28,IF(AO20="","",AP20*(1+$B$8))) | AP21: =IFERROR((1-AN21)*AO21,"") | AQ21: =IFERROR(AN21*AO21,0) -> 0 | AR21: 0 | AS21: =IF(AL21<$B$4,0,(1-AR21)*AQ21) -> 0 | AT21: =IF(AL21=$B$4,$B$14,0) -> 0 | AU21: =IF(AS21>0, IF(AU20="",AS21, (AU20*(1+$B$8)+AS21)),"")
A22: pv tax | B22: =NPV(B8,X3:X68) -> 151200 | D22: Married Filing Joint | G22: Total income | H22: Other income | J22: Unmarried/Single | M22: Total income | N22: Other income | P22: =P21+1 -> 54 | R22: =IF(P22<$B$9, 0, MAX(Q22,$B$10)) -> 0 | S22: =IF(S21="",IF(P22=$B$4,$B$3,""),T21*(1+$B$8)) | T22: =IFERROR((1-R22)*S22,"") | U22: =IFERROR(R22*S22,0) -> 0 | V22: =$B$21 -> 0.35 | W22: =IF(P22<$B$4,0,(1-V22)*U22) -> 0 | X22: =IF(P22<$B$4,"",IF(P22=$B$4,"",IFERROR(U22*V22,0))) | Y22: =IF(W22>0, IF(Y21="",W22, (Y21*(1+$B$8)+W22)),"") | AA22: =AA21+1 -> 54 | AC22: =IF(AA22<$B$9, 0, MAX(AB22,$B$10)) -> 0 | AD22: =IF(AA22=$B$4,$B$16,IF(AD21="","",AE21*(1+$B$8))) | AE22: =IFERROR((1-AC22)*AD22,"") | AF22: =IFERROR(AC22*AD22,0) -> 0 | AG22: 0 | AH22: =IF(AA22<$B$4,0,(1-AG22)*AF22) -> 0 | AI22: =IF(AA22=$B$4,$B$14,0) -> 0 | AJ22: =IF(AH22>0, IF(AJ21="",AH22, (AJ21*(1+$B$8)+AH22)),"") | AL22: =AL21+1 -> 54 | AN22: =IF(AL22<$B$9, 0, MAX(AM22,$B$10)) -> 0 | AO22: =IF(AL22=$B$4,$B$16+$B$28,IF(AO21="","",AP21*(1+$B$8))) | AP22: =IFERROR((1-AN22)*AO22,"") | AQ22: =IFERROR(AN22*AO22,0) -> 0 | AR22: 0 | AS22: =IF(AL22<$B$4,0,(1-AR22)*AQ22) -> 0 | AT22: =IF(AL22=$B$4,$B$14,0) -> 0 | AU22: =IF(AS22>0, IF(AU21="",AS22, (AU21*(1+$B$8)+AS22)),"")
A23: fv @ 100 (proceeds invested) | B23: =Y68 -> 3122900.1 | G23: =G7 -> 850000 | H23: =H7 -> 400000 | M23: =G23 -> 850000 | N23: =H23 -> 400000 | P23: =P22+1 -> 55 | R23: =IF(P23<$B$9, 0, MAX(Q23,$B$10)) -> 0 | S23: =IF(S22="",IF(P23=$B$4,$B$3,""),T22*(1+$B$8)) | T23: =IFERROR((1-R23)*S23,"") | U23: =IFERROR(R23*S23,0) -> 0 | V23: =$B$21 -> 0.35 | W23: =IF(P23<$B$4,0,(1-V23)*U23) -> 0 | X23: =IF(P23<$B$4,"",IF(P23=$B$4,"",IFERROR(U23*V23,0))) | Y23: =IF(W23>0, IF(Y22="",W23, (Y22*(1+$B$8)+W23)),"") | AA23: =AA22+1 -> 55 | AC23: =IF(AA23<$B$9, 0, MAX(AB23,$B$10)) -> 0 | AD23: =IF(AA23=$B$4,$B$16,IF(AD22="","",AE22*(1+$B$8))) | AE23: =IFERROR((1-AC23)*AD23,"") | AF23: =IFERROR(AC23*AD23,0) -> 0 | AG23: 0 | AH23: =IF(AA23<$B$4,0,(1-AG23)*AF23) -> 0 | AI23: =IF(AA23=$B$4,$B$14,0) -> 0 | AJ23: =IF(AH23>0, IF(AJ22="",AH23, (AJ22*(1+$B$8)+AH23)),"") | AL23: =AL22+1 -> 55 | AN23: =IF(AL23<$B$9, 0, MAX(AM23,$B$10)) -> 0 | AO23: =IF(AL23=$B$4,$B$16+$B$28,IF(AO22="","",AP22*(1+$B$8))) | AP23: =IFERROR((1-AN23)*AO23,"") | AQ23: =IFERROR(AN23*AO23,0) -> 0 | AR23: 0 | AS23: =IF(AL23<$B$4,0,(1-AR23)*AQ23) -> 0 | AT23: =IF(AL23=$B$4,$B$14,0) -> 0 | AU23: =IF(AS23>0, IF(AU22="",AS23, (AU22*(1+$B$8)+AS23)),"")
D24: ='Tax Tables'!B25 -> 0 | E24: ='Tax Tables'!C25 -> 100000000 | F24: ='Tax Tables'!D25 -> 0.03 | G24: =IF(IF(G$23>E24,(E24-D24)*F24,(G$23-D24)*F24)>0,IF(G$23>E24,(E24-D24)*F24,(G$23-D24)*F24),0) -> 25500 | H24: =IF(IF(H$23>E24,(E24-D24)*F24,(H$23-D24)*F24)>0,IF(H$23>E24,(E24-D24)*F24,(H$23-D24)*F24),0) -> 12000 | J24: ='Tax Tables'!F25 -> 0 | K24: ='Tax Tables'!G25 -> 100000000 | L24: ='Tax Tables'!H25 -> 0.03 | M24: =IF(IF(M$23>K24,(K24-J24)*L24,(M$23-J24)*L24)>0,IF(M$23>K24,(K24-J24)*L24,(M$23-J24)*L24),0) -> 25500 | N24: =IF(IF(N$23>K24,(K24-J24)*L24,(N$23-J24)*L24)>0,IF(N$23>K24,(K24-J24)*L24,(N$23-J24)*L24),0) -> 12000 | P24: =P23+1 -> 56 | R24: =IF(P24<$B$9, 0, MAX(Q24,$B$10)) -> 0 | S24: =IF(S23="",IF(P24=$B$4,$B$3,""),T23*(1+$B$8)) | T24: =IFERROR((1-R24)*S24,"") | U24: =IFERROR(R24*S24,0) -> 0 | V24: =$B$21 -> 0.35 | W24: =IF(P24<$B$4,0,(1-V24)*U24) -> 0 | X24: =IF(P24<$B$4,"",IF(P24=$B$4,"",IFERROR(U24*V24,0))) | Y24: =IF(W24>0, IF(Y23="",W24, (Y23*(1+$B$8)+W24)),"") | AA24: =AA23+1 -> 56 | AC24: =IF(AA24<$B$9, 0, MAX(AB24,$B$10)) -> 0 | AD24: =IF(AA24=$B$4,$B$16,IF(AD23="","",AE23*(1+$B$8))) | AE24: =IFERROR((1-AC24)*AD24,"") | AF24: =IFERROR(AC24*AD24,0) -> 0 | AG24: 0 | AH24: =IF(AA24<$B$4,0,(1-AG24)*AF24) -> 0 | AI24: =IF(AA24=$B$4,$B$14,0) -> 0 | AJ24: =IF(AH24>0, IF(AJ23="",AH24, (AJ23*(1+$B$8)+AH24)),"") | AL24: =AL23+1 -> 56 | AN24: =IF(AL24<$B$9, 0, MAX(AM24,$B$10)) -> 0 | AO24: =IF(AL24=$B$4,$B$16+$B$28,IF(AO23="","",AP23*(1+$B$8))) | AP24: =IFERROR((1-AN24)*AO24,"") | AQ24: =IFERROR(AN24*AO24,0) -> 0 | AR24: 0 | AS24: =IF(AL24<$B$4,0,(1-AR24)*AQ24) -> 0 | AT24: =IF(AL24=$B$4,$B$14,0) -> 0 | AU24: =IF(AS24>0, IF(AU23="",AS24, (AU23*(1+$B$8)+AS24)),"")
D25: ='Tax Tables'!B26 -> 0 | E25: ='Tax Tables'!C26 -> 0 | F25: ='Tax Tables'!D26 -> 0 | G25: =IF(IF(G$23>E25,(E25-D25)*F25,(G$23-D25)*F25)>0,IF(G$23>E25,(E25-D25)*F25,(G$23-D25)*F25),0) -> 0 | H25: =IF(IF(H$23>E25,(E25-D25)*F25,(H$23-D25)*F25)>0,IF(H$23>E25,(E25-D25)*F25,(H$23-D25)*F25),0) -> 0 | J25: ='Tax Tables'!F26 -> 0 | K25: ='Tax Tables'!G26 -> 0 | L25: ='Tax Tables'!H26 -> 0 | M25: =IF(IF(M$23>K25,(K25-J25)*L25,(M$23-J25)*L25)>0,IF(M$23>K25,(K25-J25)*L25,(M$23-J25)*L25),0) -> 0 | N25: =IF(IF(N$23>K25,(K25-J25)*L25,(N$23-J25)*L25)>0,IF(N$23>K25,(K25-J25)*L25,(N$23-J25)*L25),0) -> 0 | P25: =P24+1 -> 57 | R25: =IF(P25<$B$9, 0, MAX(Q25,$B$10)) -> 0 | S25: =IF(S24="",IF(P25=$B$4,$B$3,""),T24*(1+$B$8)) | T25: =IFERROR((1-R25)*S25,"") | U25: =IFERROR(R25*S25,0) -> 0 | V25: =$B$21 -> 0.35 | W25: =IF(P25<$B$4,0,(1-V25)*U25) -> 0 | X25: =IF(P25<$B$4,"",IF(P25=$B$4,"",IFERROR(U25*V25,0))) | Y25: =IF(W25>0, IF(Y24="",W25, (Y24*(1+$B$8)+W25)),"") | AA25: =AA24+1 -> 57 | AC25: =IF(AA25<$B$9, 0, MAX(AB25,$B$10)) -> 0 | AD25: =IF(AA25=$B$4,$B$16,IF(AD24="","",AE24*(1+$B$8))) | AE25: =IFERROR((1-AC25)*AD25,"") | AF25: =IFERROR(AC25*AD25,0) -> 0 | AG25: 0 | AH25: =IF(AA25<$B$4,0,(1-AG25)*AF25) -> 0 | AI25: =IF(AA25=$B$4,$B$14,0) -> 0 | AJ25: =IF(AH25>0, IF(AJ24="",AH25, (AJ24*(1+$B$8)+AH25)),"") | AL25: =AL24+1 -> 57 | AN25: =IF(AL25<$B$9, 0, MAX(AM25,$B$10)) -> 0 | AO25: =IF(AL25=$B$4,$B$16+$B$28,IF(AO24="","",AP24*(1+$B$8))) | AP25: =IFERROR((1-AN25)*AO25,"") | AQ25: =IFERROR(AN25*AO25,0) -> 0 | AR25: 0 | AS25: =IF(AL25<$B$4,0,(1-AR25)*AQ25) -> 0 | AT25: =IF(AL25=$B$4,$B$14,0) -> 0 | AU25: =IF(AS25>0, IF(AU24="",AS25, (AU24*(1+$B$8)+AS25)),"")
A26: Roth with Savings | D26: ='Tax Tables'!B27 -> 0 | E26: ='Tax Tables'!C27 -> 0 | F26: ='Tax Tables'!D27 -> 0 | G26: =IF(IF(G$23>E26,(E26-D26)*F26,(G$23-D26)*F26)>0,IF(G$23>E26,(E26-D26)*F26,(G$23-D26)*F26),0) -> 0 | H26: =IF(IF(H$23>E26,(E26-D26)*F26,(H$23-D26)*F26)>0,IF(H$23>E26,(E26-D26)*F26,(H$23-D26)*F26),0) -> 0 | J26: ='Tax Tables'!F27 -> 0 | K26: ='Tax Tables'!G27 -> 0 | L26: ='Tax Tables'!H27 -> 0 | M26: =IF(IF(M$23>K26,(K26-J26)*L26,(M$23-J26)*L26)>0,IF(M$23>K26,(K26-J26)*L26,(M$23-J26)*L26),0) -> 0 | N26: =IF(IF(N$23>K26,(K26-J26)*L26,(N$23-J26)*L26)>0,IF(N$23>K26,(K26-J26)*L26,(N$23-J26)*L26),0) -> 0 | P26: =P25+1 -> 58 | R26: =IF(P26<$B$9, 0, MAX(Q26,$B$10)) -> 0 | S26: =IF(S25="",IF(P26=$B$4,$B$3,""),T25*(1+$B$8)) | T26: =IFERROR((1-R26)*S26,"") | U26: =IFERROR(R26*S26,0) -> 0 | V26: =$B$21 -> 0.35 | W26: =IF(P26<$B$4,0,(1-V26)*U26) -> 0 | X26: =IF(P26<$B$4,"",IF(P26=$B$4,"",IFERROR(U26*V26,0))) | Y26: =IF(W26>0, IF(Y25="",W26, (Y25*(1+$B$8)+W26)),"") | AA26: =AA25+1 -> 58 | AC26: =IF(AA26<$B$9, 0, MAX(AB26,$B$10)) -> 0 | AD26: =IF(AA26=$B$4,$B$16,IF(AD25="","",AE25*(1+$B$8))) | AE26: =IFERROR((1-AC26)*AD26,"") | AF26: =IFERROR(AC26*AD26,0) -> 0 | AG26: 0 | AH26: =IF(AA26<$B$4,0,(1-AG26)*AF26) -> 0 | AI26: =IF(AA26=$B$4,$B$14,0) -> 0 | AJ26: =IF(AH26>0, IF(AJ25="",AH26, (AJ25*(1+$B$8)+AH26)),"") | AL26: =AL25+1 -> 58 | AN26: =IF(AL26<$B$9, 0, MAX(AM26,$B$10)) -> 0 | AO26: =IF(AL26=$B$4,$B$16+$B$28,IF(AO25="","",AP25*(1+$B$8))) | AP26: =IFERROR((1-AN26)*AO26,"") | AQ26: =IFERROR(AN26*AO26,0) -> 0 | AR26: 0 | AS26: =IF(AL26<$B$4,0,(1-AR26)*AQ26) -> 0 | AT26: =IF(AL26=$B$4,$B$14,0) -> 0 | AU26: =IF(AS26>0, IF(AU25="",AS26, (AU25*(1+$B$8)+AS26)),"")
A27: incremental tax rate (federal + state) | B27: =IF('Roth comparison'!C8="",B15,'Roth comparison'!C8) -> 0.35 | D27: ='Tax Tables'!B28 -> 0 | E27: ='Tax Tables'!C28 -> 0 | F27: ='Tax Tables'!D28 -> 0 | G27: =IF(IF(G$23>E27,(E27-D27)*F27,(G$23-D27)*F27)>0,IF(G$23>E27,(E27-D27)*F27,(G$23-D27)*F27),0) -> 0 | H27: =IF(IF(H$23>E27,(E27-D27)*F27,(H$23-D27)*F27)>0,IF(H$23>E27,(E27-D27)*F27,(H$23-D27)*F27),0) -> 0 | J27: ='Tax Tables'!F28 -> 0 | K27: ='Tax Tables'!G28 -> 0 | L27: ='Tax Tables'!H28 -> 0 | M27: =IF(IF(M$23>K27,(K27-J27)*L27,(M$23-J27)*L27)>0,IF(M$23>K27,(K27-J27)*L27,(M$23-J27)*L27),0) -> 0 | N27: =IF(IF(N$23>K27,(K27-J27)*L27,(N$23-J27)*L27)>0,IF(N$23>K27,(K27-J27)*L27,(N$23-J27)*L27),0) -> 0 | P27: =P26+1 -> 59 | R27: =IF(P27<$B$9, 0, MAX(Q27,$B$10)) -> 0 | S27: =IF(S26="",IF(P27=$B$4,$B$3,""),T26*(1+$B$8)) | T27: =IFERROR((1-R27)*S27,"") | U27: =IFERROR(R27*S27,0) -> 0 | V27: =$B$21 -> 0.35 | W27: =IF(P27<$B$4,0,(1-V27)*U27) -> 0 | X27: =IF(P27<$B$4,"",IF(P27=$B$4,"",IFERROR(U27*V27,0))) | Y27: =IF(W27>0, IF(Y26="",W27, (Y26*(1+$B$8)+W27)),"") | AA27: =AA26+1 -> 59 | AC27: =IF(AA27<$B$9, 0, MAX(AB27,$B$10)) -> 0 | AD27: =IF(AA27=$B$4,$B$16,IF(AD26="","",AE26*(1+$B$8))) | AE27: =IFERROR((1-AC27)*AD27,"") | AF27: =IFERROR(AC27*AD27,0) -> 0 | AG27: 0 | AH27: =IF(AA27<$B$4,0,(1-AG27)*AF27) -> 0 | AI27: =IF(AA27=$B$4,$B$14,0) -> 0 | AJ27: =IF(AH27>0, IF(AJ26="",AH27, (AJ26*(1+$B$8)+AH27)),"") | AL27: =AL26+1 -> 59 | AN27: =IF(AL27<$B$9, 0, MAX(AM27,$B$10)) -> 0 | AO27: =IF(AL27=$B$4,$B$16+$B$28,IF(AO26="","",AP26*(1+$B$8))) | AP27: =IFERROR((1-AN27)*AO27,"") | AQ27: =IFERROR(AN27*AO27,0) -> 0 | AR27: 0 | AS27: =IF(AL27<$B$4,0,(1-AR27)*AQ27) -> 0 | AT27: =IF(AL27=$B$4,$B$14,0) -> 0 | AU27: =IF(AS27>0, IF(AU26="",AS27, (AU26*(1+$B$8)+AS27)),"")
A28: tax savings | B28: ='Roth comparison'!C13 -> 49865.985 | D28: ='Tax Tables'!B29 -> 0 | E28: ='Tax Tables'!C29 -> 0 | F28: ='Tax Tables'!D29 -> 0 | G28: =IF(IF(G$23>E28,(E28-D28)*F28,(G$23-D28)*F28)>0,IF(G$23>E28,(E28-D28)*F28,(G$23-D28)*F28),0) -> 0 | H28: =IF(IF(H$23>E28,(E28-D28)*F28,(H$23-D28)*F28)>0,IF(H$23>E28,(E28-D28)*F28,(H$23-D28)*F28),0) -> 0 | J28: ='Tax Tables'!F29 -> 0 | K28: ='Tax Tables'!G29 -> 0 | L28: ='Tax Tables'!H29 -> 0 | M28: =IF(IF(M$23>K28,(K28-J28)*L28,(M$23-J28)*L28)>0,IF(M$23>K28,(K28-J28)*L28,(M$23-J28)*L28),0) -> 0 | N28: =IF(IF(N$23>K28,(K28-J28)*L28,(N$23-J28)*L28)>0,IF(N$23>K28,(K28-J28)*L28,(N$23-J28)*L28),0) -> 0 | P28: =P27+1 -> 60 | R28: =IF(P28<$B$9, 0, MAX(Q28,$B$10)) -> 0 | S28: =IF(S27="",IF(P28=$B$4,$B$3,""),T27*(1+$B$8)) | T28: =IFERROR((1-R28)*S28,"") | U28: =IFERROR(R28*S28,0) -> 0 | V28: =$B$21 -> 0.35 | W28: =IF(P28<$B$4,0,(1-V28)*U28) -> 0 | X28: =IF(P28<$B$4,"",IF(P28=$B$4,"",IFERROR(U28*V28,0))) | Y28: =IF(W28>0, IF(Y27="",W28, (Y27*(1+$B$8)+W28)),"") | AA28: =AA27+1 -> 60 | AC28: =IF(AA28<$B$9, 0, MAX(AB28,$B$10)) -> 0 | AD28: =IF(AA28=$B$4,$B$16,IF(AD27="","",AE27*(1+$B$8))) | AE28: =IFERROR((1-AC28)*AD28,"") | AF28: =IFERROR(AC28*AD28,0) -> 0 | AG28: 0 | AH28: =IF(AA28<$B$4,0,(1-AG28)*AF28) -> 0 | AI28: =IF(AA28=$B$4,$B$14,0) -> 0 | AJ28: =IF(AH28>0, IF(AJ27="",AH28, (AJ27*(1+$B$8)+AH28)),"") | AL28: =AL27+1 -> 60 | AN28: =IF(AL28<$B$9, 0, MAX(AM28,$B$10)) -> 0 | AO28: =IF(AL28=$B$4,$B$16+$B$28,IF(AO27="","",AP27*(1+$B$8))) | AP28: =IFERROR((1-AN28)*AO28,"") | AQ28: =IFERROR(AN28*AO28,0) -> 0 | AR28: 0 | AS28: =IF(AL28<$B$4,0,(1-AR28)*AQ28) -> 0 | AT28: =IF(AL28=$B$4,$B$14,0) -> 0 | AU28: =IF(AS28>0, IF(AU27="",AS28, (AU27*(1+$B$8)+AS28)),"")
A29: fv @ 100 (proceeds invested) | B29: =AU68 -> 3532865.1 | D29: ='Tax Tables'!B30 -> 0 | E29: ='Tax Tables'!C30 -> 0 | F29: ='Tax Tables'!D30 -> 0 | G29: =IF(G23>=D29,(G23-D29)*F29,0) -> 0 | H29: =IF(H23>=D29,(H23-D29)*F29,0) -> 0 | J29: ='Tax Tables'!F30 -> 0 | K29: ='Tax Tables'!G30 -> 0 | L29: ='Tax Tables'!H30 -> 0 | M29: =IF(M23>=J29,(M23-J29)*L29,0) -> 0 | N29: =IF(N23>=J29,(N23-J29)*L29,0) -> 0 | P29: =P28+1 -> 61 | R29: =IF(P29<$B$9, 0, MAX(Q29,$B$10)) -> 0 | S29: =IF(S28="",IF(P29=$B$4,$B$3,""),T28*(1+$B$8)) | T29: =IFERROR((1-R29)*S29,"") | U29: =IFERROR(R29*S29,0) -> 0 | V29: =$B$21 -> 0.35 | W29: =IF(P29<$B$4,0,(1-V29)*U29) -> 0 | X29: =IF(P29<$B$4,"",IF(P29=$B$4,"",IFERROR(U29*V29,0))) | Y29: =IF(W29>0, IF(Y28="",W29, (Y28*(1+$B$8)+W29)),"") | AA29: =AA28+1 -> 61 | AC29: =IF(AA29<$B$9, 0, MAX(AB29,$B$10)) -> 0 | AD29: =IF(AA29=$B$4,$B$16,IF(AD28="","",AE28*(1+$B$8))) | AE29: =IFERROR((1-AC29)*AD29,"") | AF29: =IFERROR(AC29*AD29,0) -> 0 | AG29: 0 | AH29: =IF(AA29<$B$4,0,(1-AG29)*AF29) -> 0 | AI29: =IF(AA29=$B$4,$B$14,0) -> 0 | AJ29: =IF(AH29>0, IF(AJ28="",AH29, (AJ28*(1+$B$8)+AH29)),"") | AL29: =AL28+1 -> 61 | AN29: =IF(AL29<$B$9, 0, MAX(AM29,$B$10)) -> 0 | AO29: =IF(AL29=$B$4,$B$16+$B$28,IF(AO28="","",AP28*(1+$B$8))) | AP29: =IFERROR((1-AN29)*AO29,"") | AQ29: =IFERROR(AN29*AO29,0) -> 0 | AR29: 0 | AS29: =IF(AL29<$B$4,0,(1-AR29)*AQ29) -> 0 | AT29: =IF(AL29=$B$4,$B$14,0) -> 0 | AU29: =IF(AS29>0, IF(AU28="",AS29, (AU28*(1+$B$8)+AS29)),"")
P30: =P29+1 -> 62 | R30: =IF(P30<$B$9, 0, MAX(Q30,$B$10)) -> 0 | S30: =IF(S29="",IF(P30=$B$4,$B$3,""),T29*(1+$B$8)) | T30: =IFERROR((1-R30)*S30,"") | U30: =IFERROR(R30*S30,0) -> 0 | V30: =$B$21 -> 0.35 | W30: =IF(P30<$B$4,0,(1-V30)*U30) -> 0 | X30: =IF(P30<$B$4,"",IF(P30=$B$4,"",IFERROR(U30*V30,0))) | Y30: =IF(W30>0, IF(Y29="",W30, (Y29*(1+$B$8)+W30)),"") | AA30: =AA29+1 -> 62 | AC30: =IF(AA30<$B$9, 0, MAX(AB30,$B$10)) -> 0 | AD30: =IF(AA30=$B$4,$B$16,IF(AD29="","",AE29*(1+$B$8))) | AE30: =IFERROR((1-AC30)*AD30,"") | AF30: =IFERROR(AC30*AD30,0) -> 0 | AG30: 0 | AH30: =IF(AA30<$B$4,0,(1-AG30)*AF30) -> 0 | AI30: =IF(AA30=$B$4,$B$14,0) -> 0 | AJ30: =IF(AH30>0, IF(AJ29="",AH30, (AJ29*(1+$B$8)+AH30)),"") | AL30: =AL29+1 -> 62 | AN30: =IF(AL30<$B$9, 0, MAX(AM30,$B$10)) -> 0 | AO30: =IF(AL30=$B$4,$B$16+$B$28,IF(AO29="","",AP29*(1+$B$8))) | AP30: =IFERROR((1-AN30)*AO30,"") | AQ30: =IFERROR(AN30*AO30,0) -> 0 | AR30: 0 | AS30: =IF(AL30<$B$4,0,(1-AR30)*AQ30) -> 0 | AT30: =IF(AL30=$B$4,$B$14,0) -> 0 | AU30: =IF(AS30>0, IF(AU29="",AS30, (AU29*(1+$B$8)+AS30)),"")
F31: Est. Tax Expense | H31: Difference | L31: Est. Tax Expense | N31: Difference | P31: =P30+1 -> 63 | R31: =IF(P31<$B$9, 0, MAX(Q31,$B$10)) -> 0 | S31: =IF(S30="",IF(P31=$B$4,$B$3,""),T30*(1+$B$8)) | T31: =IFERROR((1-R31)*S31,"") | U31: =IFERROR(R31*S31,0) -> 0 | V31: =$B$21 -> 0.35 | W31: =IF(P31<$B$4,0,(1-V31)*U31) -> 0 | X31: =IF(P31<$B$4,"",IF(P31=$B$4,"",IFERROR(U31*V31,0))) | Y31: =IF(W31>0, IF(Y30="",W31, (Y30*(1+$B$8)+W31)),"") | AA31: =AA30+1 -> 63 | AC31: =IF(AA31<$B$9, 0, MAX(AB31,$B$10)) -> 0 | AD31: =IF(AA31=$B$4,$B$16,IF(AD30="","",AE30*(1+$B$8))) | AE31: =IFERROR((1-AC31)*AD31,"") | AF31: =IFERROR(AC31*AD31,0) -> 0 | AG31: 0 | AH31: =IF(AA31<$B$4,0,(1-AG31)*AF31) -> 0 | AI31: =IF(AA31=$B$4,$B$14,0) -> 0 | AJ31: =IF(AH31>0, IF(AJ30="",AH31, (AJ30*(1+$B$8)+AH31)),"") | AL31: =AL30+1 -> 63 | AN31: =IF(AL31<$B$9, 0, MAX(AM31,$B$10)) -> 0 | AO31: =IF(AL31=$B$4,$B$16+$B$28,IF(AO30="","",AP30*(1+$B$8))) | AP31: =IFERROR((1-AN31)*AO31,"") | AQ31: =IFERROR(AN31*AO31,0) -> 0 | AR31: 0 | AS31: =IF(AL31<$B$4,0,(1-AR31)*AQ31) -> 0 | AT31: =IF(AL31=$B$4,$B$14,0) -> 0 | AU31: =IF(AS31>0, IF(AU30="",AS31, (AU30*(1+$B$8)+AS31)),"")
F32: =SUM(G24:G29) -> 25500 | G32: =SUM(H24:H29) -> 12000 | H32: =F32-G32 -> 13500 | L32: =SUM(M24:M29) -> 25500 | M32: =SUM(N24:N29) -> 12000 | N32: =L32-M32 -> 13500 | P32: =P31+1 -> 64 | R32: =IF(P32<$B$9, 0, MAX(Q32,$B$10)) -> 0 | S32: =IF(S31="",IF(P32=$B$4,$B$3,""),T31*(1+$B$8)) | T32: =IFERROR((1-R32)*S32,"") | U32: =IFERROR(R32*S32,0) -> 0 | V32: =$B$21 -> 0.35 | W32: =IF(P32<$B$4,0,(1-V32)*U32) -> 0 | X32: =IF(P32<$B$4,"",IF(P32=$B$4,"",IFERROR(U32*V32,0))) | Y32: =IF(W32>0, IF(Y31="",W32, (Y31*(1+$B$8)+W32)),"") | AA32: =AA31+1 -> 64 | AC32: =IF(AA32<$B$9, 0, MAX(AB32,$B$10)) -> 0 | AD32: =IF(AA32=$B$4,$B$16,IF(AD31="","",AE31*(1+$B$8))) | AE32: =IFERROR((1-AC32)*AD32,"") | AF32: =IFERROR(AC32*AD32,0) -> 0 | AG32: 0 | AH32: =IF(AA32<$B$4,0,(1-AG32)*AF32) -> 0 | AI32: =IF(AA32=$B$4,$B$14,0) -> 0 | AJ32: =IF(AH32>0, IF(AJ31="",AH32, (AJ31*(1+$B$8)+AH32)),"") | AL32: =AL31+1 -> 64 | AN32: =IF(AL32<$B$9, 0, MAX(AM32,$B$10)) -> 0 | AO32: =IF(AL32=$B$4,$B$16+$B$28,IF(AO31="","",AP31*(1+$B$8))) | AP32: =IFERROR((1-AN32)*AO32,"") | AQ32: =IFERROR(AN32*AO32,0) -> 0 | AR32: 0 | AS32: =IF(AL32<$B$4,0,(1-AR32)*AQ32) -> 0 | AT32: =IF(AL32=$B$4,$B$14,0) -> 0 | AU32: =IF(AS32>0, IF(AU31="",AS32, (AU31*(1+$B$8)+AS32)),"")
A33: *assume distributions prior to 73 for living | P33: =P32+1 -> 65 | R33: =IF(P33<$B$9, 0, MAX(Q33,$B$10)) -> 0.04 | S33: =IF(S32="",IF(P33=$B$4,$B$3,""),T32*(1+$B$8)) -> 450000 | T33: =IFERROR((1-R33)*S33,"") -> 432000 | U33: =IFERROR(R33*S33,0) -> 18000 | V33: =$B$21 -> 0.35 | W33: =IF(P33<$B$4,0,(1-V33)*U33) -> 11700 | X33: =IF(P33<$B$4,"",IF(P33=$B$4,"",IFERROR(U33*V33,0))) | Y33: =IF(W33>0, IF(Y32="",W33, (Y32*(1+$B$8)+W33)),"") -> 11700 | AA33: =AA32+1 -> 65 | AC33: =IF(AA33<$B$9, 0, MAX(AB33,$B$10)) -> 0.04 | AD33: =IF(AA33=$B$4,$B$16,IF(AD32="","",AE32*(1+$B$8))) -> 281032.54 | AE33: =IFERROR((1-AC33)*AD33,"") -> 269791.24 | AF33: =IFERROR(AC33*AD33,0) -> 11241.302 | AG33: 0 | AH33: =IF(AA33<$B$4,0,(1-AG33)*AF33) -> 11241.302 | AI33: =IF(AA33=$B$4,$B$14,0) -> 168967.46 | AJ33: =IF(AH33>0, IF(AJ32="",AH33, (AJ32*(1+$B$8)+AH33)),"") -> 11241.302 | AL33: =AL32+1 -> 65 | AN33: =IF(AL33<$B$9, 0, MAX(AM33,$B$10)) -> 0.04 | AO33: =IF(AL33=$B$4,$B$16+$B$28,IF(AO32="","",AP32*(1+$B$8))) -> 330898.53 | AP33: =IFERROR((1-AN33)*AO33,"") -> 317662.58 | AQ33: =IFERROR(AN33*AO33,0) -> 13235.941 | AR33: 0 | AS33: =IF(AL33<$B$4,0,(1-AR33)*AQ33) -> 13235.941 | AT33: =IF(AL33=$B$4,$B$14,0) -> 168967.46 | AU33: =IF(AS33>0, IF(AU32="",AS33, (AU32*(1+$B$8)+AS33)),"") -> 13235.941
A34: *assume rmd's are spent not invested | P34: =P33+1 -> 66 | R34: =IF(P34<$B$9, 0, MAX(Q34,$B$10)) -> 0.04 | S34: =IF(S33="",IF(P34=$B$4,$B$3,""),T33*(1+$B$8)) -> 462240 | T34: =IFERROR((1-R34)*S34,"") -> 443750.4 | U34: =IFERROR(R34*S34,0) -> 18489.6 | V34: =$B$21 -> 0.35 | W34: =IF(P34<$B$4,0,(1-V34)*U34) -> 12018.24 | X34: =IF(P34<$B$4,"",IF(P34=$B$4,"",IFERROR(U34*V34,0))) -> 6471.36 | Y34: =IF(W34>0, IF(Y33="",W34, (Y33*(1+$B$8)+W34)),"") -> 24537.24 | AA34: =AA33+1 -> 66 | AC34: =IF(AA34<$B$9, 0, MAX(AB34,$B$10)) -> 0.04 | AD34: =IF(AA34=$B$4,$B$16,IF(AD33="","",AE33*(1+$B$8))) -> 288676.63 | AE34: =IFERROR((1-AC34)*AD34,"") -> 277129.56 | AF34: =IFERROR(AC34*AD34,0) -> 11547.065 | AG34: 0 | AH34: =IF(AA34<$B$4,0,(1-AG34)*AF34) -> 11547.065 | AI34: =IF(AA34=$B$4,$B$14,0) -> 0 | AJ34: =IF(AH34>0, IF(AJ33="",AH34, (AJ33*(1+$B$8)+AH34)),"") -> 23575.258 | AL34: =AL33+1 -> 66 | AN34: =IF(AL34<$B$9, 0, MAX(AM34,$B$10)) -> 0.04 | AO34: =IF(AL34=$B$4,$B$16+$B$28,IF(AO33="","",AP33*(1+$B$8))) -> 339898.97 | AP34: =IFERROR((1-AN34)*AO34,"") -> 326303.01 | AQ34: =IFERROR(AN34*AO34,0) -> 13595.959 | AR34: 0 | AS34: =IF(AL34<$B$4,0,(1-AR34)*AQ34) -> 13595.959 | AT34: =IF(AL34=$B$4,$B$14,0) -> 0 | AU34: =IF(AS34>0, IF(AU33="",AS34, (AU33*(1+$B$8)+AS34)),"") -> 27758.415
A35: *LEAP first before charitable | P35: =P34+1 -> 67 | R35: =IF(P35<$B$9, 0, MAX(Q35,$B$10)) -> 0.04 | S35: =IF(S34="",IF(P35=$B$4,$B$3,""),T34*(1+$B$8)) -> 474812.93 | T35: =IFERROR((1-R35)*S35,"") -> 455820.41 | U35: =IFERROR(R35*S35,0) -> 18992.517 | V35: =$B$21 -> 0.35 | W35: =IF(P35<$B$4,0,(1-V35)*U35) -> 12345.136 | X35: =IF(P35<$B$4,"",IF(P35=$B$4,"",IFERROR(U35*V35,0))) -> 6647.381 | Y35: =IF(W35>0, IF(Y34="",W35, (Y34*(1+$B$8)+W35)),"") -> 38599.983 | AA35: =AA34+1 -> 67 | AC35: =IF(AA35<$B$9, 0, MAX(AB35,$B$10)) -> 0.04 | AD35: =IF(AA35=$B$4,$B$16,IF(AD34="","",AE34*(1+$B$8))) -> 296528.63 | AE35: =IFERROR((1-AC35)*AD35,"") -> 284667.48 | AF35: =IFERROR(AC35*AD35,0) -> 11861.145 | AG35: 0 | AH35: =IF(AA35<$B$4,0,(1-AG35)*AF35) -> 11861.145 | AI35: =IF(AA35=$B$4,$B$14,0) -> 0 | AJ35: =IF(AH35>0, IF(AJ34="",AH35, (AJ34*(1+$B$8)+AH35)),"") -> 37086.671 | AL35: =AL34+1 -> 67 | AN35: =IF(AL35<$B$9, 0, MAX(AM35,$B$10)) -> 0.04 | AO35: =IF(AL35=$B$4,$B$16+$B$28,IF(AO34="","",AP34*(1+$B$8))) -> 349144.22 | AP35: =IFERROR((1-AN35)*AO35,"") -> 335178.45 | AQ35: =IFERROR(AN35*AO35,0) -> 13965.769 | AR35: 0 | AS35: =IF(AL35<$B$4,0,(1-AR35)*AQ35) -> 13965.769 | AT35: =IF(AL35=$B$4,$B$14,0) -> 0 | AU35: =IF(AS35>0, IF(AU34="",AS35, (AU34*(1+$B$8)+AS35)),"") -> 43667.273
P36: =P35+1 -> 68 | R36: =IF(P36<$B$9, 0, MAX(Q36,$B$10)) -> 0.04 | S36: =IF(S35="",IF(P36=$B$4,$B$3,""),T35*(1+$B$8)) -> 487727.84 | T36: =IFERROR((1-R36)*S36,"") -> 468218.73 | U36: =IFERROR(R36*S36,0) -> 19509.114 | V36: =$B$21 -> 0.35 | W36: =IF(P36<$B$4,0,(1-V36)*U36) -> 12680.924 | X36: =IF(P36<$B$4,"",IF(P36=$B$4,"",IFERROR(U36*V36,0))) -> 6828.1898 | Y36: =IF(W36>0, IF(Y35="",W36, (Y35*(1+$B$8)+W36)),"") -> 53982.906 | AA36: =AA35+1 -> 68 | AC36: =IF(AA36<$B$9, 0, MAX(AB36,$B$10)) -> 0.04 | AD36: =IF(AA36=$B$4,$B$16,IF(AD35="","",AE35*(1+$B$8))) -> 304594.21 | AE36: =IFERROR((1-AC36)*AD36,"") -> 292410.44 | AF36: =IFERROR(AC36*AD36,0) -> 12183.768 | AG36: 0 | AH36: =IF(AA36<$B$4,0,(1-AG36)*AF36) -> 12183.768 | AI36: =IF(AA36=$B$4,$B$14,0) -> 0 | AJ36: =IF(AH36>0, IF(AJ35="",AH36, (AJ35*(1+$B$8)+AH36)),"") -> 51866.506 | AL36: =AL35+1 -> 68 | AN36: =IF(AL36<$B$9, 0, MAX(AM36,$B$10)) -> 0.04 | AO36: =IF(AL36=$B$4,$B$16+$B$28,IF(AO35="","",AP35*(1+$B$8))) -> 358640.94 | AP36: =IFERROR((1-AN36)*AO36,"") -> 344295.3 | AQ36: =IFERROR(AN36*AO36,0) -> 14345.638 | AR36: 0 | AS36: =IF(AL36<$B$4,0,(1-AR36)*AQ36) -> 14345.638 | AT36: =IF(AL36=$B$4,$B$14,0) -> 0 | AU36: =IF(AS36>0, IF(AU35="",AS36, (AU35*(1+$B$8)+AS36)),"") -> 61069.62
P37: =P36+1 -> 69 | R37: =IF(P37<$B$9, 0, MAX(Q37,$B$10)) -> 0.04 | S37: =IF(S36="",IF(P37=$B$4,$B$3,""),T36*(1+$B$8)) -> 500994.04 | T37: =IFERROR((1-R37)*S37,"") -> 480954.28 | U37: =IFERROR(R37*S37,0) -> 20039.761 | V37: =$B$21 -> 0.35 | W37: =IF(P37<$B$4,0,(1-V37)*U37) -> 13025.845 | X37: =IF(P37<$B$4,"",IF(P37=$B$4,"",IFERROR(U37*V37,0))) -> 7013.9165 | Y37: =IF(W37>0, IF(Y36="",W37, (Y36*(1+$B$8)+W37)),"") -> 70787.554 | AA37: =AA36+1 -> 69 | AC37: =IF(AA37<$B$9, 0, MAX(AB37,$B$10)) -> 0.04 | AD37: =IF(AA37=$B$4,$B$16,IF(AD36="","",AE36*(1+$B$8))) -> 312879.17 | AE37: =IFERROR((1-AC37)*AD37,"") -> 300364 | AF37: =IFERROR(AC37*AD37,0) -> 12515.167 | AG37: 0 | AH37: =IF(AA37<$B$4,0,(1-AG37)*AF37) -> 12515.167 | AI37: =IF(AA37=$B$4,$B$14,0) -> 0 | AJ37: =IF(AH37>0, IF(AJ36="",AH37, (AJ36*(1+$B$8)+AH37)),"") -> 68012.328 | AL37: =AL36+1 -> 69 | AN37: =IF(AL37<$B$9, 0, MAX(AM37,$B$10)) -> 0.04 | AO37: =IF(AL37=$B$4,$B$16+$B$28,IF(AO36="","",AP36*(1+$B$8))) -> 368395.97 | AP37: =IFERROR((1-AN37)*AO37,"") -> 353660.13 | AQ37: =IFERROR(AN37*AO37,0) -> 14735.839 | AR37: 0 | AS37: =IF(AL37<$B$4,0,(1-AR37)*AQ37) -> 14735.839 | AT37: =IF(AL37=$B$4,$B$14,0) -> 0 | AU37: =IF(AS37>0, IF(AU36="",AS37, (AU36*(1+$B$8)+AS37)),"") -> 80080.332
P38: =P37+1 -> 70 | R38: =IF(P38<$B$9, 0, MAX(Q38,$B$10)) -> 0.04 | S38: =IF(S37="",IF(P38=$B$4,$B$3,""),T37*(1+$B$8)) -> 514621.07 | T38: =IFERROR((1-R38)*S38,"") -> 494036.23 | U38: =IFERROR(R38*S38,0) -> 20584.843 | V38: =$B$21 -> 0.35 | W38: =IF(P38<$B$4,0,(1-V38)*U38) -> 13380.148 | X38: =IF(P38<$B$4,"",IF(P38=$B$4,"",IFERROR(U38*V38,0))) -> 7204.695 | Y38: =IF(W38>0, IF(Y37="",W38, (Y37*(1+$B$8)+W38)),"") -> 89122.831 | AA38: =AA37+1 -> 70 | AC38: =IF(AA38<$B$9, 0, MAX(AB38,$B$10)) -> 0.04 | AD38: =IF(AA38=$B$4,$B$16,IF(AD37="","",AE37*(1+$B$8))) -> 321389.48 | AE38: =IFERROR((1-AC38)*AD38,"") -> 308533.9 | AF38: =IFERROR(AC38*AD38,0) -> 12855.579 | AG38: 0 | AH38: =IF(AA38<$B$4,0,(1-AG38)*AF38) -> 12855.579 | AI38: =IF(AA38=$B$4,$B$14,0) -> 0 | AJ38: =IF(AH38>0, IF(AJ37="",AH38, (AJ37*(1+$B$8)+AH38)),"") -> 85628.771 | AL38: =AL37+1 -> 70 | AN38: =IF(AL38<$B$9, 0, MAX(AM38,$B$10)) -> 0.04 | AO38: =IF(AL38=$B$4,$B$16+$B$28,IF(AO37="","",AP37*(1+$B$8))) -> 378416.34 | AP38: =IFERROR((1-AN38)*AO38,"") -> 363279.69 | AQ38: =IFERROR(AN38*AO38,0) -> 15136.654 | AR38: 0 | AS38: =IF(AL38<$B$4,0,(1-AR38)*AQ38) -> 15136.654 | AT38: =IF(AL38=$B$4,$B$14,0) -> 0 | AU38: =IF(AS38>0, IF(AU37="",AS38, (AU37*(1+$B$8)+AS38)),"") -> 100822.61
P39: =P38+1 -> 71 | R39: =IF(P39<$B$9, 0, MAX(Q39,$B$10)) -> 0.04 | S39: =IF(S38="",IF(P39=$B$4,$B$3,""),T38*(1+$B$8)) -> 528618.77 | T39: =IFERROR((1-R39)*S39,"") -> 507474.02 | U39: =IFERROR(R39*S39,0) -> 21144.751 | V39: =$B$21 -> 0.35 | W39: =IF(P39<$B$4,0,(1-V39)*U39) -> 13744.088 | X39: =IF(P39<$B$4,"",IF(P39=$B$4,"",IFERROR(U39*V39,0))) -> 7400.6628 | Y39: =IF(W39>0, IF(Y38="",W39, (Y38*(1+$B$8)+W39)),"") -> 109105.52 | AA39: =AA38+1 -> 71 | AC39: =IF(AA39<$B$9, 0, MAX(AB39,$B$10)) -> 0.04 | AD39: =IF(AA39=$B$4,$B$16,IF(AD38="","",AE38*(1+$B$8))) -> 330131.28 | AE39: =IFERROR((1-AC39)*AD39,"") -> 316926.03 | AF39: =IFERROR(AC39*AD39,0) -> 13205.251 | AG39: 0 | AH39: =IF(AA39<$B$4,0,(1-AG39)*AF39) -> 13205.251 | AI39: =IF(AA39=$B$4,$B$14,0) -> 0 | AJ39: =IF(AH39>0, IF(AJ38="",AH39, (AJ38*(1+$B$8)+AH39)),"") -> 104828.04 | AL39: =AL38+1 -> 71 | AN39: =IF(AL39<$B$9, 0, MAX(AM39,$B$10)) -> 0.04 | AO39: =IF(AL39=$B$4,$B$16+$B$28,IF(AO38="","",AP38*(1+$B$8))) -> 388709.27 | AP39: =IFERROR((1-AN39)*AO39,"") -> 373160.9 | AQ39: =IFERROR(AN39*AO39,0) -> 15548.371 | AR39: 0 | AS39: =IF(AL39<$B$4,0,(1-AR39)*AQ39) -> 15548.371 | AT39: =IF(AL39=$B$4,$B$14,0) -> 0 | AU39: =IF(AS39>0, IF(AU38="",AS39, (AU38*(1+$B$8)+AS39)),"") -> 123428.56
P40: =P39+1 -> 72 | R40: =IF(P40<$B$9, 0, MAX(Q40,$B$10)) -> 0.04 | S40: =IF(S39="",IF(P40=$B$4,$B$3,""),T39*(1+$B$8)) -> 542997.2 | T40: =IFERROR((1-R40)*S40,"") -> 521277.31 | U40: =IFERROR(R40*S40,0) -> 21719.888 | V40: =$B$21 -> 0.35 | W40: =IF(P40<$B$4,0,(1-V40)*U40) -> 14117.927 | X40: =IF(P40<$B$4,"",IF(P40=$B$4,"",IFERROR(U40*V40,0))) -> 7601.9608 | Y40: =IF(W40>0, IF(Y39="",W40, (Y39*(1+$B$8)+W40)),"") -> 130860.83 | AA40: =AA39+1 -> 72 | AC40: =IF(AA40<$B$9, 0, MAX(AB40,$B$10)) -> 0.04 | AD40: =IF(AA40=$B$4,$B$16,IF(AD39="","",AE39*(1+$B$8))) -> 339110.85 | AE40: =IFERROR((1-AC40)*AD40,"") -> 325546.41 | AF40: =IFERROR(AC40*AD40,0) -> 13564.434 | AG40: 0 | AH40: =IF(AA40<$B$4,0,(1-AG40)*AF40) -> 13564.434 | AI40: =IF(AA40=$B$4,$B$14,0) -> 0 | AJ40: =IF(AH40>0, IF(AJ39="",AH40, (AJ39*(1+$B$8)+AH40)),"") -> 125730.43 | AL40: =AL39+1 -> 72 | AN40: =IF(AL40<$B$9, 0, MAX(AM40,$B$10)) -> 0.04 | AO40: =IF(AL40=$B$4,$B$16+$B$28,IF(AO39="","",AP39*(1+$B$8))) -> 399282.16 | AP40: =IFERROR((1-AN40)*AO40,"") -> 383310.87 | AQ40: =IFERROR(AN40*AO40,0) -> 15971.286 | AR40: 0 | AS40: =IF(AL40<$B$4,0,(1-AR40)*AQ40) -> 15971.286 | AT40: =IF(AL40=$B$4,$B$14,0) -> 0 | AU40: =IF(AS40>0, IF(AU39="",AS40, (AU39*(1+$B$8)+AS40)),"") -> 148039.85
P41: =P40+1 -> 73 | Q41: 0.037735849 | R41: =IF(P41<$B$9, 0, MAX(Q41,$B$10)) -> 0.04 | S41: =IF(S40="",IF(P41=$B$4,$B$3,""),T40*(1+$B$8)) -> 557766.72 | T41: =IFERROR((1-R41)*S41,"") -> 535456.05 | U41: =IFERROR(R41*S41,0) -> 22310.669 | V41: =$B$21 -> 0.35 | W41: =IF(P41<$B$4,0,(1-V41)*U41) -> 14501.935 | X41: =IF(P41<$B$4,"",IF(P41=$B$4,"",IFERROR(U41*V41,0))) -> 7808.7341 | Y41: =IF(W41>0, IF(Y40="",W41, (Y40*(1+$B$8)+W41)),"") -> 154523.02 | AA41: =AA40+1 -> 73 | AB41: 0.037735849 | AC41: =IF(AA41<$B$9, 0, MAX(AB41,$B$10)) -> 0.04 | AD41: =IF(AA41=$B$4,$B$16,IF(AD40="","",AE40*(1+$B$8))) -> 348334.66 | AE41: =IFERROR((1-AC41)*AD41,"") -> 334401.28 | AF41: =IFERROR(AC41*AD41,0) -> 13933.387 | AG41: 0 | AH41: =IF(AA41<$B$4,0,(1-AG41)*AF41) -> 13933.387 | AI41: =IF(AA41=$B$4,$B$14,0) -> 0 | AJ41: =IF(AH41>0, IF(AJ40="",AH41, (AJ40*(1+$B$8)+AH41)),"") -> 148464.95 | AL41: =AL40+1 -> 73 | AM41: 0.037735849 | AN41: =IF(AL41<$B$9, 0, MAX(AM41,$B$10)) -> 0.04 | AO41: =IF(AL41=$B$4,$B$16+$B$28,IF(AO40="","",AP40*(1+$B$8))) -> 410142.64 | AP41: =IFERROR((1-AN41)*AO41,"") -> 393736.93 | AQ41: =IFERROR(AN41*AO41,0) -> 16405.705 | AR41: 0 | AS41: =IF(AL41<$B$4,0,(1-AR41)*AQ41) -> 16405.705 | AT41: =IF(AL41=$B$4,$B$14,0) -> 0 | AU41: =IF(AS41>0, IF(AU40="",AS41, (AU40*(1+$B$8)+AS41)),"") -> 174808.34
P42: =P41+1 -> 74 | Q42: 0.039215686 | R42: =IF(P42<$B$9, 0, MAX(Q42,$B$10)) -> 0.04 | S42: =IF(S41="",IF(P42=$B$4,$B$3,""),T41*(1+$B$8)) -> 572937.98 | T42: =IFERROR((1-R42)*S42,"") -> 550020.46 | U42: =IFERROR(R42*S42,0) -> 22917.519 | V42: =$B$21 -> 0.35 | W42: =IF(P42<$B$4,0,(1-V42)*U42) -> 14896.387 | X42: =IF(P42<$B$4,"",IF(P42=$B$4,"",IFERROR(U42*V42,0))) -> 8021.1317 | Y42: =IF(W42>0, IF(Y41="",W42, (Y41*(1+$B$8)+W42)),"") -> 180236.02 | AA42: =AA41+1 -> 74 | AB42: 0.039215686 | AC42: =IF(AA42<$B$9, 0, MAX(AB42,$B$10)) -> 0.04 | AD42: =IF(AA42=$B$4,$B$16,IF(AD41="","",AE41*(1+$B$8))) -> 357809.37 | AE42: =IFERROR((1-AC42)*AD42,"") -> 343496.99 | AF42: =IFERROR(AC42*AD42,0) -> 14312.375 | AG42: 0 | AH42: =IF(AA42<$B$4,0,(1-AG42)*AF42) -> 14312.375 | AI42: =IF(AA42=$B$4,$B$14,0) -> 0 | AJ42: =IF(AH42>0, IF(AJ41="",AH42, (AJ41*(1+$B$8)+AH42)),"") -> 173169.87 | AL42: =AL41+1 -> 74 | AM42: 0.039215686 | AN42: =IF(AL42<$B$9, 0, MAX(AM42,$B$10)) -> 0.04 | AO42: =IF(AL42=$B$4,$B$16+$B$28,IF(AO41="","",AP41*(1+$B$8))) -> 421298.51 | AP42: =IFERROR((1-AN42)*AO42,"") -> 404446.57 | AQ42: =IFERROR(AN42*AO42,0) -> 16851.941 | AR42: 0 | AS42: =IF(AL42<$B$4,0,(1-AR42)*AQ42) -> 16851.941 | AT42: =IF(AL42=$B$4,$B$14,0) -> 0 | AU42: =IF(AS42>0, IF(AU41="",AS42, (AU41*(1+$B$8)+AS42)),"") -> 203896.87
P43: =P42+1 -> 75 | Q43: 0.040650407 | R43: =IF(P43<$B$9, 0, MAX(Q43,$B$10)) -> 0.040650407 | S43: =IF(S42="",IF(P43=$B$4,$B$3,""),T42*(1+$B$8)) -> 588521.89 | T43: =IFERROR((1-R43)*S43,"") -> 564598.24 | U43: =IFERROR(R43*S43,0) -> 23923.654 | V43: =$B$21 -> 0.35 | W43: =IF(P43<$B$4,0,(1-V43)*U43) -> 15550.375 | X43: =IF(P43<$B$4,"",IF(P43=$B$4,"",IFERROR(U43*V43,0))) -> 8373.2789 | Y43: =IF(W43>0, IF(Y42="",W43, (Y42*(1+$B$8)+W43)),"") -> 208402.92 | AA43: =AA42+1 -> 75 | AB43: 0.040650407 | AC43: =IF(AA43<$B$9, 0, MAX(AB43,$B$10)) -> 0.040650407 | AD43: =IF(AA43=$B$4,$B$16,IF(AD42="","",AE42*(1+$B$8))) -> 367541.78 | AE43: =IFERROR((1-AC43)*AD43,"") -> 352601.06 | AF43: =IFERROR(AC43*AD43,0) -> 14940.723 | AG43: 0 | AH43: =IF(AA43<$B$4,0,(1-AG43)*AF43) -> 14940.723 | AI43: =IF(AA43=$B$4,$B$14,0) -> 0 | AJ43: =IF(AH43>0, IF(AJ42="",AH43, (AJ42*(1+$B$8)+AH43)),"") -> 200232.48 | AL43: =AL42+1 -> 75 | AM43: 0.040650407 | AN43: =IF(AL43<$B$9, 0, MAX(AM43,$B$10)) -> 0.040650407 | AO43: =IF(AL43=$B$4,$B$16+$B$28,IF(AO42="","",AP42*(1+$B$8))) -> 432757.83 | AP43: =IFERROR((1-AN43)*AO43,"") -> 415166.05 | AQ43: =IFERROR(AN43*AO43,0) -> 17591.782 | AR43: 0 | AS43: =IF(AL43<$B$4,0,(1-AR43)*AQ43) -> 17591.782 | AT43: =IF(AL43=$B$4,$B$14,0) -> 0 | AU43: =IF(AS43>0, IF(AU42="",AS43, (AU42*(1+$B$8)+AS43)),"") -> 235761.43
P44: =P43+1 -> 76 | Q44: 0.042194093 | R44: =IF(P44<$B$9, 0, MAX(Q44,$B$10)) -> 0.042194093 | S44: =IF(S43="",IF(P44=$B$4,$B$3,""),T43*(1+$B$8)) -> 604120.11 | T44: =IFERROR((1-R44)*S44,"") -> 578629.81 | U44: =IFERROR(R44*S44,0) -> 25490.3 | V44: =$B$21 -> 0.35 | W44: =IF(P44<$B$4,0,(1-V44)*U44) -> 16568.695 | X44: =IF(P44<$B$4,"",IF(P44=$B$4,"",IFERROR(U44*V44,0))) -> 8921.605 | Y44: =IF(W44>0, IF(Y43="",W44, (Y43*(1+$B$8)+W44)),"") -> 239559.82 | AA44: =AA43+1 -> 76 | AB44: 0.042194093 | AC44: =IF(AA44<$B$9, 0, MAX(AB44,$B$10)) -> 0.042194093 | AD44: =IF(AA44=$B$4,$B$16,IF(AD43="","",AE43*(1+$B$8))) -> 377283.13 | AE44: =IFERROR((1-AC44)*AD44,"") -> 361364.01 | AF44: =IFERROR(AC44*AD44,0) -> 15919.12 | AG44: 0 | AH44: =IF(AA44<$B$4,0,(1-AG44)*AF44) -> 15919.12 | AI44: =IF(AA44=$B$4,$B$14,0) -> 0 | AJ44: =IF(AH44>0, IF(AJ43="",AH44, (AJ43*(1+$B$8)+AH44)),"") -> 230167.88 | AL44: =AL43+1 -> 76 | AM44: 0.042194093 | AN44: =IF(AL44<$B$9, 0, MAX(AM44,$B$10)) -> 0.042194093 | AO44: =IF(AL44=$B$4,$B$16+$B$28,IF(AO43="","",AP43*(1+$B$8))) -> 444227.68 | AP44: =IFERROR((1-AN44)*AO44,"") -> 425483.89 | AQ44: =IFERROR(AN44*AO44,0) -> 18743.784 | AR44: 0 | AS44: =IF(AL44<$B$4,0,(1-AR44)*AQ44) -> 18743.784 | AT44: =IF(AL44=$B$4,$B$14,0) -> 0 | AU44: =IF(AS44>0, IF(AU43="",AS44, (AU43*(1+$B$8)+AS44)),"") -> 271008.51
P45: =P44+1 -> 77 | Q45: 0.043668122 | R45: =IF(P45<$B$9, 0, MAX(Q45,$B$10)) -> 0.043668122 | S45: =IF(S44="",IF(P45=$B$4,$B$3,""),T44*(1+$B$8)) -> 619133.9 | T45: =IFERROR((1-R45)*S45,"") -> 592097.48 | U45: =IFERROR(R45*S45,0) -> 27036.415 | V45: =$B$21 -> 0.35 | W45: =IF(P45<$B$4,0,(1-V45)*U45) -> 17573.67 | X45: =IF(P45<$B$4,"",IF(P45=$B$4,"",IFERROR(U45*V45,0))) -> 9462.7452 | Y45: =IF(W45>0, IF(Y44="",W45, (Y44*(1+$B$8)+W45)),"") -> 273902.67 | AA45: =AA44+1 -> 77 | AB45: 0.043668122 | AC45: =IF(AA45<$B$9, 0, MAX(AB45,$B$10)) -> 0.043668122 | AD45: =IF(AA45=$B$4,$B$16,IF(AD44="","",AE44*(1+$B$8))) -> 386659.49 | AE45: =IFERROR((1-AC45)*AD45,"") -> 369774.8 | AF45: =IFERROR(AC45*AD45,0) -> 16884.694 | AG45: 0 | AH45: =IF(AA45<$B$4,0,(1-AG45)*AF45) -> 16884.694 | AI45: =IF(AA45=$B$4,$B$14,0) -> 0 | AJ45: =IF(AH45>0, IF(AJ44="",AH45, (AJ44*(1+$B$8)+AH45)),"") -> 263164.32 | AL45: =AL44+1 -> 77 | AM45: 0.043668122 | AN45: =IF(AL45<$B$9, 0, MAX(AM45,$B$10)) -> 0.043668122 | AO45: =IF(AL45=$B$4,$B$16+$B$28,IF(AO44="","",AP44*(1+$B$8))) -> 455267.76 | AP45: =IFERROR((1-AN45)*AO45,"") -> 435387.08 | AQ45: =IFERROR(AN45*AO45,0) -> 19880.688 | AR45: 0 | AS45: =IF(AL45<$B$4,0,(1-AR45)*AQ45) -> 19880.688 | AT45: =IF(AL45=$B$4,$B$14,0) -> 0 | AU45: =IF(AS45>0, IF(AU44="",AS45, (AU44*(1+$B$8)+AS45)),"") -> 309859.8
P46: =P45+1 -> 78 | Q46: 0.045454545 | R46: =IF(P46<$B$9, 0, MAX(Q46,$B$10)) -> 0.045454545 | S46: =IF(S45="",IF(P46=$B$4,$B$3,""),T45*(1+$B$8)) -> 633544.31 | T46: =IFERROR((1-R46)*S46,"") -> 604746.84 | U46: =IFERROR(R46*S46,0) -> 28797.469 | V46: =$B$21 -> 0.35 | W46: =IF(P46<$B$4,0,(1-V46)*U46) -> 18718.355 | X46: =IF(P46<$B$4,"",IF(P46=$B$4,"",IFERROR(U46*V46,0))) -> 10079.114 | Y46: =IF(W46>0, IF(Y45="",W46, (Y45*(1+$B$8)+W46)),"") -> 311794.22 | AA46: =AA45+1 -> 78 | AB46: 0.045454545 | AC46: =IF(AA46<$B$9, 0, MAX(AB46,$B$10)) -> 0.045454545 | AD46: =IF(AA46=$B$4,$B$16,IF(AD45="","",AE45*(1+$B$8))) -> 395659.04 | AE46: =IFERROR((1-AC46)*AD46,"") -> 377674.53 | AF46: =IFERROR(AC46*AD46,0) -> 17984.502 | AG46: 0 | AH46: =IF(AA46<$B$4,0,(1-AG46)*AF46) -> 17984.502 | AI46: =IF(AA46=$B$4,$B$14,0) -> 0 | AJ46: =IF(AH46>0, IF(AJ45="",AH46, (AJ45*(1+$B$8)+AH46)),"") -> 299570.33 | AL46: =AL45+1 -> 78 | AM46: 0.045454545 | AN46: =IF(AL46<$B$9, 0, MAX(AM46,$B$10)) -> 0.045454545 | AO46: =IF(AL46=$B$4,$B$16+$B$28,IF(AO45="","",AP45*(1+$B$8))) -> 465864.17 | AP46: =IFERROR((1-AN46)*AO46,"") -> 444688.53 | AQ46: =IFERROR(AN46*AO46,0) -> 21175.644 | AR46: 0 | AS46: =IF(AL46<$B$4,0,(1-AR46)*AQ46) -> 21175.644 | AT46: =IF(AL46=$B$4,$B$14,0) -> 0 | AU46: =IF(AS46>0, IF(AU45="",AS46, (AU45*(1+$B$8)+AS46)),"") -> 352725.63
P47: =P46+1 -> 79 | Q47: 0.047393365 | R47: =IF(P47<$B$9, 0, MAX(Q47,$B$10)) -> 0.047393365 | S47: =IF(S46="",IF(P47=$B$4,$B$3,""),T46*(1+$B$8)) -> 647079.12 | T47: =IFERROR((1-R47)*S47,"") -> 616411.86 | U47: =IFERROR(R47*S47,0) -> 30667.257 | V47: =$B$21 -> 0.35 | W47: =IF(P47<$B$4,0,(1-V47)*U47) -> 19933.717 | X47: =IF(P47<$B$4,"",IF(P47=$B$4,"",IFERROR(U47*V47,0))) -> 10733.54 | Y47: =IF(W47>0, IF(Y46="",W47, (Y46*(1+$B$8)+W47)),"") -> 353553.53 | AA47: =AA46+1 -> 79 | AB47: 0.047393365 | AC47: =IF(AA47<$B$9, 0, MAX(AB47,$B$10)) -> 0.047393365 | AD47: =IF(AA47=$B$4,$B$16,IF(AD46="","",AE46*(1+$B$8))) -> 404111.75 | AE47: =IFERROR((1-AC47)*AD47,"") -> 384959.54 | AF47: =IFERROR(AC47*AD47,0) -> 19152.216 | AG47: 0 | AH47: =IF(AA47<$B$4,0,(1-AG47)*AF47) -> 19152.216 | AI47: =IF(AA47=$B$4,$B$14,0) -> 0 | AJ47: =IF(AH47>0, IF(AJ46="",AH47, (AJ46*(1+$B$8)+AH47)),"") -> 339692.47 | AL47: =AL46+1 -> 79 | AM47: 0.047393365 | AN47: =IF(AL47<$B$9, 0, MAX(AM47,$B$10)) -> 0.047393365 | AO47: =IF(AL47=$B$4,$B$16+$B$28,IF(AO46="","",AP46*(1+$B$8))) -> 475816.72 | AP47: =IFERROR((1-AN47)*AO47,"") -> 453266.17 | AQ47: =IFERROR(AN47*AO47,0) -> 22550.556 | AR47: 0 | AS47: =IF(AL47<$B$4,0,(1-AR47)*AQ47) -> 22550.556 | AT47: =IF(AL47=$B$4,$B$14,0) -> 0 | AU47: =IF(AS47>0, IF(AU46="",AS47, (AU46*(1+$B$8)+AS47)),"") -> 399966.98
P48: =P47+1 -> 80 | Q48: 0.04950495 | R48: =IF(P48<$B$9, 0, MAX(Q48,$B$10)) -> 0.04950495 | S48: =IF(S47="",IF(P48=$B$4,$B$3,""),T47*(1+$B$8)) -> 659560.69 | T48: =IFERROR((1-R48)*S48,"") -> 626909.17 | U48: =IFERROR(R48*S48,0) -> 32651.519 | V48: =$B$21 -> 0.35 | W48: =IF(P48<$B$4,0,(1-V48)*U48) -> 21223.488 | X48: =IF(P48<$B$4,"",IF(P48=$B$4,"",IFERROR(U48*V48,0))) -> 11428.032 | Y48: =IF(W48>0, IF(Y47="",W48, (Y47*(1+$B$8)+W48)),"") -> 399525.76 | AA48: =AA47+1 -> 80 | AB48: 0.04950495 | AC48: =IF(AA48<$B$9, 0, MAX(AB48,$B$10)) -> 0.04950495 | AD48: =IF(AA48=$B$4,$B$16,IF(AD47="","",AE47*(1+$B$8))) -> 411906.7 | AE48: =IFERROR((1-AC48)*AD48,"") -> 391515.28 | AF48: =IFERROR(AC48*AD48,0) -> 20391.421 | AG48: 0 | AH48: =IF(AA48<$B$4,0,(1-AG48)*AF48) -> 20391.421 | AI48: =IF(AA48=$B$4,$B$14,0) -> 0 | AJ48: =IF(AH48>0, IF(AJ47="",AH48, (AJ47*(1+$B$8)+AH48)),"") -> 383862.36 | AL48: =AL47+1 -> 80 | AM48: 0.04950495 | AN48: =IF(AL48<$B$9, 0, MAX(AM48,$B$10)) -> 0.04950495 | AO48: =IF(AL48=$B$4,$B$16+$B$28,IF(AO47="","",AP47*(1+$B$8))) -> 484994.8 | AP48: =IFERROR((1-AN48)*AO48,"") -> 460985.16 | AQ48: =IFERROR(AN48*AO48,0) -> 24009.644 | AR48: 0 | AS48: =IF(AL48<$B$4,0,(1-AR48)*AQ48) -> 24009.644 | AT48: =IF(AL48=$B$4,$B$14,0) -> 0 | AU48: =IF(AS48>0, IF(AU47="",AS48, (AU47*(1+$B$8)+AS48)),"") -> 451974.31
P49: =P48+1 -> 81 | Q49: 0.051546392 | R49: =IF(P49<$B$9, 0, MAX(Q49,$B$10)) -> 0.051546392 | S49: =IF(S48="",IF(P49=$B$4,$B$3,""),T48*(1+$B$8)) -> 670792.81 | T49: =IFERROR((1-R49)*S49,"") -> 636215.87 | U49: =IFERROR(R49*S49,0) -> 34576.949 | V49: =$B$21 -> 0.35 | W49: =IF(P49<$B$4,0,(1-V49)*U49) -> 22475.017 | X49: =IF(P49<$B$4,"",IF(P49=$B$4,"",IFERROR(U49*V49,0))) -> 12101.932 | Y49: =IF(W49>0, IF(Y48="",W49, (Y48*(1+$B$8)+W49)),"") -> 449967.58 | AA49: =AA48+1 -> 81 | AB49: 0.051546392 | AC49: =IF(AA49<$B$9, 0, MAX(AB49,$B$10)) -> 0.051546392 | AD49: =IF(AA49=$B$4,$B$16,IF(AD48="","",AE48*(1+$B$8))) -> 418921.35 | AE49: =IFERROR((1-AC49)*AD49,"") -> 397327.47 | AF49: =IFERROR(AC49*AD49,0) -> 21593.884 | AG49: 0 | AH49: =IF(AA49<$B$4,0,(1-AG49)*AF49) -> 21593.884 | AI49: =IF(AA49=$B$4,$B$14,0) -> 0 | AJ49: =IF(AH49>0, IF(AJ48="",AH49, (AJ48*(1+$B$8)+AH49)),"") -> 432326.61 | AL49: =AL48+1 -> 81 | AM49: 0.051546392 | AN49: =IF(AL49<$B$9, 0, MAX(AM49,$B$10)) -> 0.051546392 | AO49: =IF(AL49=$B$4,$B$16+$B$28,IF(AO48="","",AP48*(1+$B$8))) -> 493254.12 | AP49: =IFERROR((1-AN49)*AO49,"") -> 467828.65 | AQ49: =IFERROR(AN49*AO49,0) -> 25425.47 | AR49: 0 | AS49: =IF(AL49<$B$4,0,(1-AR49)*AQ49) -> 25425.47 | AT49: =IF(AL49=$B$4,$B$14,0) -> 0 | AU49: =IF(AS49>0, IF(AU48="",AS49, (AU48*(1+$B$8)+AS49)),"") -> 509037.98
P50: =P49+1 -> 82 | Q50: 0.054054054 | R50: =IF(P50<$B$9, 0, MAX(Q50,$B$10)) -> 0.054054054 | S50: =IF(S49="",IF(P50=$B$4,$B$3,""),T49*(1+$B$8)) -> 680750.98 | T50: =IFERROR((1-R50)*S50,"") -> 643953.63 | U50: =IFERROR(R50*S50,0) -> 36797.35 | V50: =$B$21 -> 0.35 | W50: =IF(P50<$B$4,0,(1-V50)*U50) -> 23918.278 | X50: =IF(P50<$B$4,"",IF(P50=$B$4,"",IFERROR(U50*V50,0))) -> 12879.073 | Y50: =IF(W50>0, IF(Y49="",W50, (Y49*(1+$B$8)+W50)),"") -> 505383.59 | AA50: =AA49+1 -> 82 | AB50: 0.054054054 | AC50: =IF(AA50<$B$9, 0, MAX(AB50,$B$10)) -> 0.054054054 | AD50: =IF(AA50=$B$4,$B$16,IF(AD49="","",AE49*(1+$B$8))) -> 425140.39 | AE50: =IFERROR((1-AC50)*AD50,"") -> 402159.83 | AF50: =IFERROR(AC50*AD50,0) -> 22980.562 | AG50: 0 | AH50: =IF(AA50<$B$4,0,(1-AG50)*AF50) -> 22980.562 | AI50: =IF(AA50=$B$4,$B$14,0) -> 0 | AJ50: =IF(AH50>0, IF(AJ49="",AH50, (AJ49*(1+$B$8)+AH50)),"") -> 485570.03 | AL50: =AL49+1 -> 82 | AM50: 0.054054054 | AN50: =IF(AL50<$B$9, 0, MAX(AM50,$B$10)) -> 0.054054054 | AO50: =IF(AL50=$B$4,$B$16+$B$28,IF(AO49="","",AP49*(1+$B$8))) -> 500576.65 | AP50: =IFERROR((1-AN50)*AO50,"") -> 473518.46 | AQ50: =IFERROR(AN50*AO50,0) -> 27058.197 | AR50: 0 | AS50: =IF(AL50<$B$4,0,(1-AR50)*AQ50) -> 27058.197 | AT50: =IF(AL50=$B$4,$B$14,0) -> 0 | AU50: =IF(AS50>0, IF(AU49="",AS50, (AU49*(1+$B$8)+AS50)),"") -> 571728.84
P51: =P50+1 -> 83 | Q51: 0.056497175 | R51: =IF(P51<$B$9, 0, MAX(Q51,$B$10)) -> 0.056497175 | S51: =IF(S50="",IF(P51=$B$4,$B$3,""),T50*(1+$B$8)) -> 689030.38 | T51: =IFERROR((1-R51)*S51,"") -> 650102.11 | U51: =IFERROR(R51*S51,0) -> 38928.27 | V51: =$B$21 -> 0.35 | W51: =IF(P51<$B$4,0,(1-V51)*U51) -> 25303.376 | X51: =IF(P51<$B$4,"",IF(P51=$B$4,"",IFERROR(U51*V51,0))) -> 13624.895 | Y51: =IF(W51>0, IF(Y50="",W51, (Y50*(1+$B$8)+W51)),"") -> 566063.82 | AA51: =AA50+1 -> 83 | AB51: 0.056497175 | AC51: =IF(AA51<$B$9, 0, MAX(AB51,$B$10)) -> 0.056497175 | AD51: =IF(AA51=$B$4,$B$16,IF(AD50="","",AE50*(1+$B$8))) -> 430311.02 | AE51: =IFERROR((1-AC51)*AD51,"") -> 405999.66 | AF51: =IFERROR(AC51*AD51,0) -> 24311.357 | AG51: 0 | AH51: =IF(AA51<$B$4,0,(1-AG51)*AF51) -> 24311.357 | AI51: =IF(AA51=$B$4,$B$14,0) -> 0 | AJ51: =IF(AH51>0, IF(AJ50="",AH51, (AJ50*(1+$B$8)+AH51)),"") -> 543871.29 | AL51: =AL50+1 -> 83 | AM51: 0.056497175 | AN51: =IF(AL51<$B$9, 0, MAX(AM51,$B$10)) -> 0.056497175 | AO51: =IF(AL51=$B$4,$B$16+$B$28,IF(AO50="","",AP50*(1+$B$8))) -> 506664.75 | AP51: =IFERROR((1-AN51)*AO51,"") -> 478039.62 | AQ51: =IFERROR(AN51*AO51,0) -> 28625.127 | AR51: 0 | AS51: =IF(AL51<$B$4,0,(1-AR51)*AQ51) -> 28625.127 | AT51: =IF(AL51=$B$4,$B$14,0) -> 0 | AU51: =IF(AS51>0, IF(AU50="",AS51, (AU50*(1+$B$8)+AS51)),"") -> 640374.98
P52: =P51+1 -> 84 | Q52: 0.05952381 | R52: =IF(P52<$B$9, 0, MAX(Q52,$B$10)) -> 0.05952381 | S52: =IF(S51="",IF(P52=$B$4,$B$3,""),T51*(1+$B$8)) -> 695609.26 | T52: =IFERROR((1-R52)*S52,"") -> 654203.94 | U52: =IFERROR(R52*S52,0) -> 41405.313 | V52: =$B$21 -> 0.35 | W52: =IF(P52<$B$4,0,(1-V52)*U52) -> 26913.453 | X52: =IF(P52<$B$4,"",IF(P52=$B$4,"",IFERROR(U52*V52,0))) -> 14491.86 | Y52: =IF(W52>0, IF(Y51="",W52, (Y51*(1+$B$8)+W52)),"") -> 632601.74 | AA52: =AA51+1 -> 84 | AB52: 0.05952381 | AC52: =IF(AA52<$B$9, 0, MAX(AB52,$B$10)) -> 0.05952381 | AD52: =IF(AA52=$B$4,$B$16,IF(AD51="","",AE51*(1+$B$8))) -> 434419.64 | AE52: =IFERROR((1-AC52)*AD52,"") -> 408561.32 | AF52: =IFERROR(AC52*AD52,0) -> 25858.312 | AG52: 0 | AH52: =IF(AA52<$B$4,0,(1-AG52)*AF52) -> 25858.312 | AI52: =IF(AA52=$B$4,$B$14,0) -> 0 | AJ52: =IF(AH52>0, IF(AJ51="",AH52, (AJ51*(1+$B$8)+AH52)),"") -> 607800.59 | AL52: =AL51+1 -> 84 | AM52: 0.05952381 | AN52: =IF(AL52<$B$9, 0, MAX(AM52,$B$10)) -> 0.05952381 | AO52: =IF(AL52=$B$4,$B$16+$B$28,IF(AO51="","",AP51*(1+$B$8))) -> 511502.39 | AP52: =IFERROR((1-AN52)*AO52,"") -> 481055.82 | AQ52: =IFERROR(AN52*AO52,0) -> 30446.571 | AR52: 0 | AS52: =IF(AL52<$B$4,0,(1-AR52)*AQ52) -> 30446.571 | AT52: =IF(AL52=$B$4,$B$14,0) -> 0 | AU52: =IF(AS52>0, IF(AU51="",AS52, (AU51*(1+$B$8)+AS52)),"") -> 715647.8
... P67: =P66+1 -> 99 | Q67: 0.14705882 | R67: =IF(P67<$B$9, 0, MAX(Q67,$B$10)) -> 0.14705882 | S67: =IF(S66="",IF(P67=$B$4,$B$3,""),T66*(1+$B$8)) -> 453792.59 | T67: =IFERROR((1-R67)*S67,"") -> 387058.38 | U67: =IFERROR(R67*S67,0) -> 66734.204 | V67: =$B$21 -> 0.35 | W67: =IF(P67<$B$4,0,(1-V67)*U67) -> 43377.232 | X67: =IF(P67<$B$4,"",IF(P67=$B$4,"",IFERROR(U67*V67,0))) -> 23356.971 | Y67: =IF(W67>0, IF(Y66="",W67, (Y66*(1+$B$8)+W67)),"") -> 2667010.3 | AA67: =AA66+1 -> 99 | AB67: 0.14705882 | AC67: =IF(AA67<$B$9, 0, MAX(AB67,$B$10)) -> 0.14705882 | AD67: =IF(AA67=$B$4,$B$16,IF(AD66="","",AE66*(1+$B$8))) -> 283401.07 | AE67: =IFERROR((1-AC67)*AD67,"") -> 241724.44 | AF67: =IFERROR(AC67*AD67,0) -> 41676.628 | AG67: 0 | AH67: =IF(AA67<$B$4,0,(1-AG67)*AF67) -> 41676.628 | AI67: =IF(AA67=$B$4,$B$14,0) -> 0 | AJ67: =IF(AH67>0, IF(AJ66="",AH67, (AJ66*(1+$B$8)+AH67)),"") -> 2562450.1 | AL67: =AL66+1 -> 99 | AM67: 0.14705882 | AN67: =IF(AL67<$B$9, 0, MAX(AM67,$B$10)) -> 0.14705882 | AO67: =IF(AL67=$B$4,$B$16+$B$28,IF(AO66="","",AP66*(1+$B$8))) -> 333687.33 | AP67: =IFERROR((1-AN67)*AO67,"") -> 284615.66 | AQ67: =IFERROR(AN67*AO67,0) -> 49071.666 | AR67: 0 | AS67: =IF(AL67<$B$4,0,(1-AR67)*AQ67) -> 49071.666 | AT67: =IF(AL67=$B$4,$B$14,0) -> 0 | AU67: =IF(AS67>0, IF(AU66="",AS67, (AU66*(1+$B$8)+AS67)),"") -> 3017127.4
P68: =P67+1 -> 100 | Q68: 0.15625 | R68: =IF(P68<$B$9, 0, MAX(Q68,$B$10)) -> 0.15625 | S68: =IF(S67="",IF(P68=$B$4,$B$3,""),T67*(1+$B$8)) -> 414152.47 | T68: =(0)*S68 -> 0 | U68: =1*S68 -> 414152.47 | V68: =$B$21 -> 0.35 | W68: =IF(P68<$B$4,"",(1-V68)*U68) -> 269199.1 | X68: =U68*V68 -> 144953.36 | Y68: =IF(W68>0, IF(Y67="",W68, (Y67*(1+$B$8)+W68)),"") -> 3122900.1 | AA68: =AA67+1 -> 100 | AB68: 0.15625 | AC68: =IF(AA68<$B$9, 0, MAX(AB68,$B$10)) -> 0.15625 | AD68: =IF(AA68=$B$4,$B$16,IF(AD67="","",AE67*(1+$B$8))) -> 258645.16 | AE68: =(0)*AD68 -> 0 | AF68: =1*AD68 -> 258645.16 | AG68: 0 | AH68: =IF(AA68<$B$4,"",(1-AG68)*AF68) -> 258645.16 | AI68: =IF(AA68=$B$4,$B$14,0) -> 0 | AJ68: =IF(AH68>0, IF(AJ67="",AH68, (AJ67*(1+$B$8)+AH68)),"") -> 3000466.8 | AL68: =AL67+1 -> 100 | AM68: 0.15625 | AN68: =IF(AL68<$B$9, 0, MAX(AM68,$B$10)) -> 0.15625 | AO68: =IF(AL68=$B$4,$B$16+$B$28,IF(AO67="","",AP67*(1+$B$8))) -> 304538.76 | AP68: =(0)*AO68 -> 0 | AQ68: =1*AO68 -> 304538.76 | AR68: 0 | AS68: =IF(AL68<$B$4,"",(1-AR68)*AQ68) -> 304538.76 | AT68: =IF(AL68=$B$4,$B$14,0) -> 0 | AU68: =IF(AS68>0, IF(AU67="",AS68, (AU67*(1+$B$8)+AS68)),"") -> 3532865.1

Sheet DB Only
B2: Filing Status | C2: ='Strategy comparison'!C4 -> Married-Joint | E2: Federal Ordinary Income Tax
B3: Business Income | C3: ='Strategy comparison'!C6 -> 0
B4: Business AGI | C4: =C3 -> 0 | E4: Married Filing Joint | H4: Ordinary Income | I4: Ord. Income less Business AGI | J4: Ord. Income less DB Contribution | L4: Unmarried/Single | O4: Ordinary Income | P4: Ord. Income less Business AGI | Q4: Ord. Income less DB Contribution
B5: Marginal Business Tax | C5: =IF(C2="Married-Joint",H15-I15,O15-P15) -> 0 | H5: ='No planning'!J7 -> 400000 | I5: =H5-C4 -> 400000 | J5: =H5-C6 -> 400000 | O5: =H5 -> 400000 | P5: =I5 -> 400000 | Q5: =J5 -> 400000
B6: DB Contribution | C6: ='DB comparison'!C2 -> 0 | E6: ='Tax Tables'!B6 -> 0 | F6: ='Tax Tables'!C6 -> 24800 | G6: ='Tax Tables'!D6 -> 0.1 | H6: =IF(IF(H$5>F6,(F6-E6)*G6,(H$5-E6)*G6)>0,IF(H$5>F6,(F6-E6)*G6,(H$5-E6)*G6),0) -> 2480 | I6: =IF(IF(I$5>F6,(F6-E6)*G6,(I$5-E6)*G6)>0,IF(I$5>F6,(F6-E6)*G6,(I$5-E6)*G6),0) -> 2480 | J6: =IF(IF(J$5>F6,(F6-E6)*G6,(J$5-E6)*G6)>0,IF(J$5>F6,(F6-E6)*G6,(J$5-E6)*G6),0) -> 2480 | L6: ='Tax Tables'!F6 -> 0 | M6: ='Tax Tables'!G6 -> 12400 | N6: ='Tax Tables'!H6 -> 0.1 | O6: =IF(IF(O$5>M6,(M6-L6)*N6,(O$5-L6)*N6)>0,IF(O$5>M6,(M6-L6)*N6,(O$5-L6)*N6),0) -> 1240 | P6: =IF(IF(P$5>M6,(M6-L6)*N6,(P$5-L6)*N6)>0,IF(P$5>M6,(M6-L6)*N6,(P$5-L6)*N6),0) -> 1240 | Q6: =IF(IF(Q$5>M6,(M6-L6)*N6,(Q$5-L6)*N6)>0,IF(Q$5>M6,(M6-L6)*N6,(Q$5-L6)*N6),0) -> 1240
B7: Mod. Business Income | C7: =C3-C6 -> 0 | E7: ='Tax Tables'!B7 -> 24801 | F7: ='Tax Tables'!C7 -> 100800 | G7: ='Tax Tables'!D7 -> 0.12 | H7: =IF(IF(H$5>F7,(F7-E7)*G7,(H$5-E7)*G7)>0,IF(H$5>F7,(F7-E7)*G7,(H$5-E7)*G7),0) -> 9119.88 | I7: =IF(IF(I$5>F7,(F7-E7)*G7,(I$5-E7)*G7)>0,IF(I$5>F7,(F7-E7)*G7,(I$5-E7)*G7),0) -> 9119.88 | J7: =IF(IF(J$5>F7,(F7-E7)*G7,(J$5-E7)*G7)>0,IF(J$5>F7,(F7-E7)*G7,(J$5-E7)*G7),0) -> 9119.88 | L7: ='Tax Tables'!F7 -> 12401 | M7: ='Tax Tables'!G7 -> 50400 | N7: ='Tax Tables'!H7 -> 0.12 | O7: =IF(IF(O$5>M7,(M7-L7)*N7,(O$5-L7)*N7)>0,IF(O$5>M7,(M7-L7)*N7,(O$5-L7)*N7),0) -> 4559.88 | P7: =IF(IF(P$5>M7,(M7-L7)*N7,(P$5-L7)*N7)>0,IF(P$5>M7,(M7-L7)*N7,(P$5-L7)*N7),0) -> 4559.88 | Q7: =IF(IF(Q$5>M7,(M7-L7)*N7,(Q$5-L7)*N7)>0,IF(Q$5>M7,(M7-L7)*N7,(Q$5-L7)*N7),0) -> 4559.88
B8: Mod. Marginal Business Tax | C8: =IF(C2="Married-Joint",J15-I15,Q15-P15) -> 0 | E8: ='Tax Tables'!B8 -> 100801 | F8: ='Tax Tables'!C8 -> 211400 | G8: ='Tax Tables'!D8 -> 0.22 | H8: =IF(IF(H$5>F8,(F8-E8)*G8,(H$5-E8)*G8)>0,IF(H$5>F8,(F8-E8)*G8,(H$5-E8)*G8),0) -> 24331.78 | I8: =IF(IF(I$5>F8,(F8-E8)*G8,(I$5-E8)*G8)>0,IF(I$5>F8,(F8-E8)*G8,(I$5-E8)*G8),0) -> 24331.78 | J8: =IF(IF(J$5>F8,(F8-E8)*G8,(J$5-E8)*G8)>0,IF(J$5>F8,(F8-E8)*G8,(J$5-E8)*G8),0) -> 24331.78 | L8: ='Tax Tables'!F8 -> 50401 | M8: ='Tax Tables'!G8 -> 105700 | N8: ='Tax Tables'!H8 -> 0.22 | O8: =IF(IF(O$5>M8,(M8-L8)*N8,(O$5-L8)*N8)>0,IF(O$5>M8,(M8-L8)*N8,(O$5-L8)*N8),0) -> 12165.78 | P8: =IF(IF(P$5>M8,(M8-L8)*N8,(P$5-L8)*N8)>0,IF(P$5>M8,(M8-L8)*N8,(P$5-L8)*N8),0) -> 12165.78 | Q8: =IF(IF(Q$5>M8,(M8-L8)*N8,(Q$5-L8)*N8)>0,IF(Q$5>M8,(M8-L8)*N8,(Q$5-L8)*N8),0) -> 12165.78
B9: Ord. Income Tax Savings | C9: =C5-C8 -> 0 | E9: ='Tax Tables'!B9 -> 211401 | F9: ='Tax Tables'!C9 -> 403550 | G9: ='Tax Tables'!D9 -> 0.24 | H9: =IF(IF(H$5>F9,(F9-E9)*G9,(H$5-E9)*G9)>0,IF(H$5>F9,(F9-E9)*G9,(H$5-E9)*G9),0) -> 45263.76 | I9: =IF(IF(I$5>F9,(F9-E9)*G9,(I$5-E9)*G9)>0,IF(I$5>F9,(F9-E9)*G9,(I$5-E9)*G9),0) -> 45263.76 | J9: =IF(IF(J$5>F9,(F9-E9)*G9,(J$5-E9)*G9)>0,IF(J$5>F9,(F9-E9)*G9,(J$5-E9)*G9),0) -> 45263.76 | L9: ='Tax Tables'!F9 -> 105701 | M9: ='Tax Tables'!G9 -> 201775 | N9: ='Tax Tables'!H9 -> 0.24 | O9: =IF(IF(O$5>M9,(M9-L9)*N9,(O$5-L9)*N9)>0,IF(O$5>M9,(M9-L9)*N9,(O$5-L9)*N9),0) -> 23057.76 | P9: =IF(IF(P$5>M9,(M9-L9)*N9,(P$5-L9)*N9)>0,IF(P$5>M9,(M9-L9)*N9,(P$5-L9)*N9),0) -> 23057.76 | Q9: =IF(IF(Q$5>M9,(M9-L9)*N9,(Q$5-L9)*N9)>0,IF(Q$5>M9,(M9-L9)*N9,(Q$5-L9)*N9),0) -> 23057.76
B10: State Tax Savings | C10: =0.03*C6 -> 0 | E10: ='Tax Tables'!B10 -> 403551 | F10: ='Tax Tables'!C10 -> 512450 | G10: ='Tax Tables'!D10 -> 0.32 | H10: =IF(IF(H$5>F10,(F10-E10)*G10,(H$5-E10)*G10)>0,IF(H$5>F10,(F10-E10)*G10,(H$5-E10)*G10),0) -> 0 | I10: =IF(IF(I$5>F10,(F10-E10)*G10,(I$5-E10)*G10)>0,IF(I$5>F10,(F10-E10)*G10,(I$5-E10)*G10),0) -> 0 | J10: =IF(IF(J$5>F10,(F10-E10)*G10,(J$5-E10)*G10)>0,IF(J$5>F10,(F10-E10)*G10,(J$5-E10)*G10),0) -> 0 | L10: ='Tax Tables'!F10 -> 201776 | M10: ='Tax Tables'!G10 -> 256225 | N10: ='Tax Tables'!H10 -> 0.32 | O10: =IF(IF(O$5>M10,(M10-L10)*N10,(O$5-L10)*N10)>0,IF(O$5>M10,(M10-L10)*N10,(O$5-L10)*N10),0) -> 17423.68 | P10: =IF(IF(P$5>M10,(M10-L10)*N10,(P$5-L10)*N10)>0,IF(P$5>M10,(M10-L10)*N10,(P$5-L10)*N10),0) -> 17423.68 | Q10: =IF(IF(Q$5>M10,(M10-L10)*N10,(Q$5-L10)*N10)>0,IF(Q$5>M10,(M10-L10)*N10,(Q$5-L10)*N10),0) -> 17423.68
B11: Total Tax Savings | C11: =C9+C10 -> 0 | E11: ='Tax Tables'!B11 -> 512451 | F11: ='Tax Tables'!C11 -> 768700 | G11: ='Tax Tables'!D11 -> 0.35 | H11: =IF(IF(H$5>F11,(F11-E11)*G11,(H$5-E11)*G11)>0,IF(H$5>F11,(F11-E11)*G11,(H$5-E11)*G11),0) -> 0 | I11: =IF(IF(I$5>F11,(F11-E11)*G11,(I$5-E11)*G11)>0,IF(I$5>F11,(F11-E11)*G11,(I$5-E11)*G11),0) -> 0 | J11: =IF(IF(J$5>F11,(F11-E11)*G11,(J$5-E11)*G11)>0,IF(J$5>F11,(F11-E11)*G11,(J$5-E11)*G11),0) -> 0 | L11: ='Tax Tables'!F11 -> 256226 | M11: ='Tax Tables'!G11 -> 640600 | N11: ='Tax Tables'!H11 -> 0.35 | O11: =IF(IF(O$5>M11,(M11-L11)*N11,(O$5-L11)*N11)>0,IF(O$5>M11,(M11-L11)*N11,(O$5-L11)*N11),0) -> 50320.9 | P11: =IF(IF(P$5>M11,(M11-L11)*N11,(P$5-L11)*N11)>0,IF(P$5>M11,(M11-L11)*N11,(P$5-L11)*N11),0) -> 50320.9 | Q11: =IF(IF(Q$5>M11,(M11-L11)*N11,(Q$5-L11)*N11)>0,IF(Q$5>M11,(M11-L11)*N11,(Q$5-L11)*N11),0) -> 50320.9
E12: ='Tax Tables'!B12 -> 768701 | F12: ='Tax Tables'!C12 -> 99999999999 | G12: ='Tax Tables'!D12 -> 0.37 | H12: =IF(H5>=E12,(H5-E12)*G12,0) -> 0 | I12: =IF(I5>=E12,(I5-E12)*G12,0) -> 0 | J12: =IF(J5>=E12,(J5-E12)*G12,0) -> 0 | L12: ='Tax Tables'!F12 -> 640601 | M12: ='Tax Tables'!G12 -> 99999999999 | N12: ='Tax Tables'!H12 -> 0.37 | O12: =IF(O5>=L12,(O5-L12)*N12,0) -> 0 | P12: =IF(P5>=L12,(P5-L12)*N12,0) -> 0 | Q12: =IF(Q5>=L12,(Q5-L12)*N12,0) -> 0
B13: Summary
B14: Fed Ord. Income Tax | C14: =IF(C2="Married-Joint", J15,Q15) -> 81195.42 | H14: Est. Tax Expense | O14: Est. Tax Expense
B15: Fed LTCG Tax | C15: ='No planning'!C20 -> 0 | H15: =SUM(H6:H12) -> 81195.42 | I15: =SUM(I6:I12) -> 81195.42 | J15: =SUM(J6:J12) -> 81195.42 | O15: =SUM(O6:O12) -> 108768 | P15: =SUM(P6:P12) -> 108768 | Q15: =SUM(Q6:Q12) -> 108768
B16: State Tax | C16: =MAX('No planning'!C21-(0.03*'DB Only'!C6),0) -> 12000
B17: NIIT | C17: =MAX('No planning'!C22-(0.038*C6),0) -> 5700
B18: Total | C18: =SUM(C14:C17) -> 98895.42

Sheet Film
D2: % of Offset
B3: Filing Status - LA | C3: ='Strategy comparison'!C4 -> Married-Joint | D3: Income
B4: W2 Income | C4: ='Strategy comparison'!C5 -> 400000 | D4: 1 | F4: Federal Ordinary Income Tax
B5: Business Income | C5: ='Strategy comparison'!C6 -> 0
B6: ST Capital Gains | C6: ='Strategy comparison'!C7 -> 0 | D6: Multiple On Contribution | F6: Married Filing Joint | I6: Ordinary Income | J6: Ordinary Income w Film | L6: Unmarried/Single | O6: Ordinary Income | P6: Ordinary Income w Filn
B7: Interest | C7: ='Strategy comparison'!$C$9 -> 0 | D7: 4.75 | I7: =C10 -> 400000 | J7: =C10-MIN(C10,C20) -> 100800 | O7: =I7 -> 400000 | P7: =J7 -> 100800
B8: Qualified Dividends | C8: ='Strategy comparison'!$C$10 -> 0 | D8: Unadjusted | F8: ='Tax Tables'!B6 -> 0 | G8: ='Tax Tables'!C6 -> 24800 | H8: ='Tax Tables'!D6 -> 0.1 | I8: =IF(IF(I$7>G8,(G8-F8)*H8,(I$7-F8)*H8)>0,IF(I$7>G8,(G8-F8)*H8,(I$7-F8)*H8),0) -> 2480 | J8: =IF(IF(J$7>G8,(G8-F8)*H8,(J$7-F8)*H8)>0,IF(J$7>G8,(G8-F8)*H8,(J$7-F8)*H8),0) -> 2480 | L8: ='Tax Tables'!F6 -> 0 | M8: ='Tax Tables'!G6 -> 12400 | N8: ='Tax Tables'!H6 -> 0.1 | O8: =IF(IF(O$7>M8,(M8-L8)*N8,(O$7-L8)*N8)>0,IF(O$7>M8,(M8-L8)*N8,(O$7-L8)*N8),0) -> 1240 | P8: =IF(IF(P$7>M8,(M8-L8)*N8,(P$7-L8)*N8)>0,IF(P$7>M8,(M8-L8)*N8,(P$7-L8)*N8),0) -> 1240
B9: Nonqualified Dividends | C9: ='Strategy comparison'!$C$11 -> 0 | D9: Contribution | F9: ='Tax Tables'!B7 -> 24801 | G9: ='Tax Tables'!C7 -> 100800 | H9: ='Tax Tables'!D7 -> 0.12 | I9: =IF(IF(I$7>G9,(G9-F9)*H9,(I$7-F9)*H9)>0,IF(I$7>G9,(G9-F9)*H9,(I$7-F9)*H9),0) -> 9119.88 | J9: =IF(IF(J$7>G9,(G9-F9)*H9,(J$7-F9)*H9)>0,IF(J$7>G9,(G9-F9)*H9,(J$7-F9)*H9),0) -> 9119.88 | L9: ='Tax Tables'!F7 -> 12401 | M9: ='Tax Tables'!G7 -> 50400 | N9: ='Tax Tables'!H7 -> 0.12 | O9: =IF(IF(O$7>M9,(M9-L9)*N9,(O$7-L9)*N9)>0,IF(O$7>M9,(M9-L9)*N9,(O$7-L9)*N9),0) -> 4559.88 | P9: =IF(IF(P$7>M9,(M9-L9)*N9,(P$7-L9)*N9)>0,IF(P$7>M9,(M9-L9)*N9,(P$7-L9)*N9),0) -> 4559.88
B10: Ordinary Income | C10: =SUM(C4:C7)+C9 -> 400000 | D10: =C20/D7 -> 62989.474 | F10: ='Tax Tables'!B8 -> 100801 | G10: ='Tax Tables'!C8 -> 211400 | H10: ='Tax Tables'!D8 -> 0.22 | I10: =IF(IF(I$7>G10,(G10-F10)*H10,(I$7-F10)*H10)>0,IF(I$7>G10,(G10-F10)*H10,(I$7-F10)*H10),0) -> 24331.78 | J10: =IF(IF(J$7>G10,(G10-F10)*H10,(J$7-F10)*H10)>0,IF(J$7>G10,(G10-F10)*H10,(J$7-F10)*H10),0) -> 0 | L10: ='Tax Tables'!F8 -> 50401 | M10: ='Tax Tables'!G8 -> 105700 | N10: ='Tax Tables'!H8 -> 0.22 | O10: =IF(IF(O$7>M10,(M10-L10)*N10,(O$7-L10)*N10)>0,IF(O$7>M10,(M10-L10)*N10,(O$7-L10)*N10),0) -> 12165.78 | P10: =IF(IF(P$7>M10,(M10-L10)*N10,(P$7-L10)*N10)>0,IF(P$7>M10,(M10-L10)*N10,(P$7-L10)*N10),0) -> 11087.78
B11: LT Cap Gains | C11: ='Strategy comparison'!C8 -> 0 | D11: RIA Discount | F11: ='Tax Tables'!B9 -> 211401 | G11: ='Tax Tables'!C9 -> 403550 | H11: ='Tax Tables'!D9 -> 0.24 | I11: =IF(IF(I$7>G11,(G11-F11)*H11,(I$7-F11)*H11)>0,IF(I$7>G11,(G11-F11)*H11,(I$7-F11)*H11),0) -> 45263.76 | J11: =IF(IF(J$7>G11,(G11-F11)*H11,(J$7-F11)*H11)>0,IF(J$7>G11,(G11-F11)*H11,(J$7-F11)*H11),0) -> 0 | L11: ='Tax Tables'!F9 -> 105701 | M11: ='Tax Tables'!G9 -> 201775 | N11: ='Tax Tables'!H9 -> 0.24 | O11: =IF(IF(O$7>M11,(M11-L11)*N11,(O$7-L11)*N11)>0,IF(O$7>M11,(M11-L11)*N11,(O$7-L11)*N11),0) -> 23057.76 | P11: =IF(IF(P$7>M11,(M11-L11)*N11,(P$7-L11)*N11)>0,IF(P$7>M11,(M11-L11)*N11,(P$7-L11)*N11),0) -> 0
B12: LTCG + Qualified Dividends | C12: =C11+C8 -> 0 | D12: 0 | F12: ='Tax Tables'!B10 -> 403551 | G12: ='Tax Tables'!C10 -> 512450 | H12: ='Tax Tables'!D10 -> 0.32 | I12: =IF(IF(I$7>G12,(G12-F12)*H12,(I$7-F12)*H12)>0,IF(I$7>G12,(G12-F12)*H12,(I$7-F12)*H12),0) -> 0 | J12: =IF(IF(J$7>G12,(G12-F12)*H12,(J$7-F12)*H12)>0,IF(J$7>G12,(G12-F12)*H12,(J$7-F12)*H12),0) -> 0 | L12: ='Tax Tables'!F10 -> 201776 | M12: ='Tax Tables'!G10 -> 256225 | N12: ='Tax Tables'!H10 -> 0.32 | O12: =IF(IF(O$7>M12,(M12-L12)*N12,(O$7-L12)*N12)>0,IF(O$7>M12,(M12-L12)*N12,(O$7-L12)*N12),0) -> 17423.68 | P12: =IF(IF(P$7>M12,(M12-L12)*N12,(P$7-L12)*N12)>0,IF(P$7>M12,(M12-L12)*N12,(P$7-L12)*N12),0) -> 0
B13: AGI | C13: =C10+C12 -> 400000 | D13: Client Contribution | F13: ='Tax Tables'!B11 -> 512451 | G13: ='Tax Tables'!C11 -> 768700 | H13: ='Tax Tables'!D11 -> 0.35 | I13: =IF(IF(I$7>G13,(G13-F13)*H13,(I$7-F13)*H13)>0,IF(I$7>G13,(G13-F13)*H13,(I$7-F13)*H13),0) -> 0 | J13: =IF(IF(J$7>G13,(G13-F13)*H13,(J$7-F13)*H13)>0,IF(J$7>G13,(G13-F13)*H13,(J$7-F13)*H13),0) -> 0 | L13: ='Tax Tables'!F11 -> 256226 | M13: ='Tax Tables'!G11 -> 640600 | N13: ='Tax Tables'!H11 -> 0.35 | O13: =IF(IF(O$7>M13,(M13-L13)*N13,(O$7-L13)*N13)>0,IF(O$7>M13,(M13-L13)*N13,(O$7-L13)*N13),0) -> 50320.9 | P13: =IF(IF(P$7>M13,(M13-L13)*N13,(P$7-L13)*N13)>0,IF(P$7>M13,(M13-L13)*N13,(P$7-L13)*N13),0) -> 0
B14: Current Fed Tax | C14: =IF(C3="Single",N17,IF(C3="Married-Joint",H17,"Filing Status?")) -> 81195.42 | D14: =D10*(1-D12) -> 62989.474 | F14: ='Tax Tables'!B12 -> 768701 | G14: ='Tax Tables'!C12 -> 99999999999 | H14: ='Tax Tables'!D12 -> 0.37 | I14: =IF(I7>=F14,(I7-F14)*H14,0) -> 0 | J14: =IF(J7>=F14,(J7-F14)*H14,0) -> 0 | L14: ='Tax Tables'!F12 -> 640601 | M14: ='Tax Tables'!G12 -> 99999999999 | N14: ='Tax Tables'!H12 -> 0.37 | O14: =IF(O7>=L14,(O7-L14)*N14,0) -> 0 | P14: =IF(P7>=L14,(P7-L14)*N14,0) -> 0
B15: LT Cap Gains Tax | C15: =IF(C3="Single",N28,IF(C3="Married-Joint",H28,"Filing Status?")) -> 0 | D15: Consulting Fee
B16: Current State Tax | C16: =IF(C3="Single",N42,IF(C3="Married-Joint",H42,"Filing Status?")) -> 12000 | D16: ='Strategy comparison'!C12 -> 0 | H16: Est. Tax Expense | J16: Difference | N16: Est. Tax Expense | P16: Difference
B17: Total Inc Tax | C17: =SUM(C14:C16)+H45 -> 98895.42 | D17: Film Cost | H17: =SUM(I8:I14) -> 81195.42 | I17: =SUM(J8:J14) -> 11599.88 | J17: =H17-I17 -> 69595.54 | N17: =SUM(O8:O14) -> 108768 | O17: =SUM(P8:P14) -> 16887.66 | P17: =N17-O17 -> 91880.34
B18: Effective Tax Rate | C18: =C17/SUM(C10:C11) -> 0.24723855 | D18: =SUM(D14,D16) -> 62989.474
F19: Long Term Capital Gains & Qualified Dividends Tax
B20: Film Offset | C20: =IF('Strategy comparison'!G18="",(I7+I22)*D4,'Strategy comparison'!G18) -> 299200
B21: Post Offset Taxable Income | C21: =C13-C20 -> 100800 | F21: Married Filing Joint | I21: LTCG & QD | J21: LTCG & QD w Film | L21: Unmarried/Single | O21: LTCG & QD | P21: LTCG & QD w Film
B22: Modified Fed | C22: =IF(C3="Single",O17,IF(C3="Married-Joint",I17,"Filing Status?")) -> 11599.88 | I22: =C12 -> 0 | J22: =I22-IF(C20>I7,C20-I7,0) -> 0 | O22: =C12 -> 0 | P22: =J22 -> 0
B23: Mod State Tax | C23: =IF(C3="Single",O42,IF(C3="Married-Joint",I42,"Filing Status?")) -> 3024 | F23: ='Tax Tables'!B18 -> 0 | G23: ='Tax Tables'!C18 -> 98900 | H23: ='Tax Tables'!D18 -> 0 | I23: =IF(I$22>$G23,($G23-$F23)*$H23,MAX((I$22-$F23),0)*$H23) -> 0 | J23: =IF(J$22>$G23,($G23-$F23)*$H23,MAX((J$22-$F23),0)*$H23) -> 0 | L23: ='Tax Tables'!F18 -> 0 | M23: ='Tax Tables'!G18 -> 49450 | N23: ='Tax Tables'!H18 -> 0 | O23: =IF(O$22>$M23,($M23-$L23)*$N23,MAX((O$22-$L23),0)*$N23) -> 0 | P23: =IF(P$22>$M23,($M23-$L23)*$N23,MAX((P$22-$L23),0)*$N23) -> 0
B24: LT Cap Gains Tax | C24: =IF(C3="Single",O28,IF(C3="Married-Joint",I28,"Filing Status?")) -> 0 | F24: ='Tax Tables'!B19 -> 98901 | G24: ='Tax Tables'!C19 -> 613700 | H24: ='Tax Tables'!D19 -> 0.15 | I24: =IF(I$22>$G24,($G24-$F24)*$H24,MAX((I$22-$F24),0)*$H24) -> 0 | J24: =IF(J$22>$G24,($G24-$F24)*$H24,MAX((J$22-$F24),0)*$H24) -> 0 | L24: ='Tax Tables'!F19 -> 49451 | M24: ='Tax Tables'!G19 -> 545500 | N24: ='Tax Tables'!H19 -> 0.15 | O24: =IF(O$22>$M24,($M24-$L24)*$N24,MAX((O$22-$L24),0)*$N24) -> 0 | P24: =IF(P$22>$M24,($M24-$L24)*$N24,MAX((P$22-$L24),0)*$N24) -> 0
B25: NIIT | C25: 0 | F25: ='Tax Tables'!B20 -> 613701 | G25: ='Tax Tables'!C20 -> 99999999999 | H25: ='Tax Tables'!D20 -> 0.2 | I25: =IF(I$22>$G25,($G25-$F25)*$H25,MAX((I$22-$F25),0)*$H25) -> 0 | J25: =IF(J$22>$G25,($G25-$F25)*$H25,MAX((J$22-$F25),0)*$H25) -> 0 | L25: ='Tax Tables'!F20 -> 545501 | M25: ='Tax Tables'!G20 -> 99999999999 | N25: ='Tax Tables'!H20 -> 0.2 | O25: =IF(O$22>$M25,($M25-$L25)*$N25,MAX((O$22-$L25),0)*$N25) -> 0 | P25: =IF(P$22>$M25,($M25-$L25)*$N25,MAX((P$22-$L25),0)*$N25) -> 0
B26: Total Mod Inc Tax | C26: =SUM(C22:C25) -> 14623.88
B27: Effective Tax Rate | C27: =(C26+C29)/C13 -> 0.19403338 | H27: Est. Tax Expense | J27: Difference | N27: Est. Tax Expense | P27: Difference
B28: Tax Reduction | C28: =C17-C26 -> 84271.54 | H28: =SUM(I23:I25) -> 0 | I28: =SUM(J23:J25) -> 0 | J28: =H28-I28 -> 0 | N28: =SUM(O23:O25) -> 0 | O28: =SUM(P23:P25) -> 0 | P28: =N28-O28 -> 0
B29: Contribution + Fee | C29: =D18 -> 62989.474
B30: Access Net Savings | C30: =C28-C29 -> 21282.066 | F30: State Income Tax - Louisiana
F32: Married Filing Joint | I32: AGI | J32: AGI w Film | L32: Unmarried/Single | O32: AGI | P32: AGI w Film
I33: =C13 -> 400000 | J33: =I33-C20 -> 100800 | O33: =I33 -> 400000 | P33: =J33 -> 100800
F34: ='Tax Tables'!B25 -> 0 | G34: ='Tax Tables'!C25 -> 100000000 | H34: ='Tax Tables'!D25 -> 0.03 | I34: =IF(IF(I$33>G34,(G34-F34)*H34,(I$33-F34)*H34)>0,IF(I$33>G34,(G34-F34)*H34,(I$33-F34)*H34),0) -> 12000 | J34: =IF(IF(J$33>G34,(G34-F34)*H34,(J$33-F34)*H34)>0,IF(J$33>G34,(G34-F34)*H34,(J$33-F34)*H34),0) -> 3024 | L34: ='Tax Tables'!F25 -> 0 | M34: ='Tax Tables'!G25 -> 100000000 | N34: ='Tax Tables'!H25 -> 0.03 | O34: =IF(IF(O$33>M34,(M34-L34)*N34,(O$33-L34)*N34)>0,IF(O$33>M34,(M34-L34)*N34,(O$33-L34)*N34),0) -> 12000 | P34: =IF(IF(P$33>M34,(M34-L34)*N34,(P$33-L34)*N34)>0,IF(P$33>M34,(M34-L34)*N34,(P$33-L34)*N34),0) -> 3024
F35: ='Tax Tables'!B26 -> 0 | G35: ='Tax Tables'!C26 -> 0 | H35: ='Tax Tables'!D26 -> 0 | I35: =IF(IF(I$33>G35,(G35-F35)*H35,(I$33-F35)*H35)>0,IF(I$33>G35,(G35-F35)*H35,(I$33-F35)*H35),0) -> 0 | J35: =IF(IF(J$33>G35,(G35-F35)*H35,(J$33-F35)*H35)>0,IF(J$33>G35,(G35-F35)*H35,(J$33-F35)*H35),0) -> 0 | L35: ='Tax Tables'!F26 -> 0 | M35: ='Tax Tables'!G26 -> 0 | N35: ='Tax Tables'!H26 -> 0 | O35: =IF(IF(O$33>M35,(M35-L35)*N35,(O$33-L35)*N35)>0,IF(O$33>M35,(M35-L35)*N35,(O$33-L35)*N35),0) -> 0 | P35: =IF(IF(P$33>M35,(M35-L35)*N35,(P$33-L35)*N35)>0,IF(P$33>M35,(M35-L35)*N35,(P$33-L35)*N35),0) -> 0
F36: ='Tax Tables'!B27 -> 0 | G36: ='Tax Tables'!C27 -> 0 | H36: ='Tax Tables'!D27 -> 0 | I36: =IF(IF(I$33>G36,(G36-F36)*H36,(I$33-F36)*H36)>0,IF(I$33>G36,(G36-F36)*H36,(I$33-F36)*H36),0) -> 0 | J36: =IF(IF(J$33>G36,(G36-F36)*H36,(J$33-F36)*H36)>0,IF(J$33>G36,(G36-F36)*H36,(J$33-F36)*H36),0) -> 0 | L36: ='Tax Tables'!F27 -> 0 | M36: ='Tax Tables'!G27 -> 0 | N36: ='Tax Tables'!H27 -> 0 | O36: =IF(IF(O$33>M36,(M36-L36)*N36,(O$33-L36)*N36)>0,IF(O$33>M36,(M36-L36)*N36,(O$33-L36)*N36),0) -> 0 | P36: =IF(IF(P$33>M36,(M36-L36)*N36,(P$33-L36)*N36)>0,IF(P$33>M36,(M36-L36)*N36,(P$33-L36)*N36),0) -> 0
F37: ='Tax Tables'!B28 -> 0 | G37: ='Tax Tables'!C28 -> 0 | H37: ='Tax Tables'!D28 -> 0 | I37: =IF(IF(I$33>G37,(G37-F37)*H37,(I$33-F37)*H37)>0,IF(I$33>G37,(G37-F37)*H37,(I$33-F37)*H37),0) -> 0 | J37: =IF(IF(J$33>G37,(G37-F37)*H37,(J$33-F37)*H37)>0,IF(J$33>G37,(G37-F37)*H37,(J$33-F37)*H37),0) -> 0 | L37: ='Tax Tables'!F28 -> 0 | M37: ='Tax Tables'!G28 -> 0 | N37: ='Tax Tables'!H28 -> 0 | O37: =IF(IF(O$33>M37,(M37-L37)*N37,(O$33-L37)*N37)>0,IF(O$33>M37,(M37-L37)*N37,(O$33-L37)*N37),0) -> 0 | P37: =IF(IF(P$33>M37,(M37-L37)*N37,(P$33-L37)*N37)>0,IF(P$33>M37,(M37-L37)*N37,(P$33-L37)*N37),0) -> 0
F38: ='Tax Tables'!B29 -> 0 | G38: ='Tax Tables'!C29 -> 0 | H38: ='Tax Tables'!D29 -> 0 | I38: =IF(IF(I$33>G38,(G38-F38)*H38,(I$33-F38)*H38)>0,IF(I$33>G38,(G38-F38)*H38,(I$33-F38)*H38),0) -> 0 | J38: =IF(IF(J$33>G38,(G38-F38)*H38,(J$33-F38)*H38)>0,IF(J$33>G38,(G38-F38)*H38,(J$33-F38)*H38),0) -> 0 | L38: ='Tax Tables'!F29 -> 0 | M38: ='Tax Tables'!G29 -> 0 | N38: ='Tax Tables'!H29 -> 0 | O38: =IF(IF(O$33>M38,(M38-L38)*N38,(O$33-L38)*N38)>0,IF(O$33>M38,(M38-L38)*N38,(O$33-L38)*N38),0) -> 0 | P38: =IF(IF(P$33>M38,(M38-L38)*N38,(P$33-L38)*N38)>0,IF(P$33>M38,(M38-L38)*N38,(P$33-L38)*N38),0) -> 0
F39: ='Tax Tables'!B30 -> 0 | G39: ='Tax Tables'!C30 -> 0 | H39: ='Tax Tables'!D30 -> 0 | I39: =IF(I33>=F39,(I33-F39)*H39,0) -> 0 | J39: =IF(J33>=F39,(J33-F39)*H39,0) -> 0 | L39: ='Tax Tables'!F30 -> 0 | M39: ='Tax Tables'!G30 -> 0 | N39: ='Tax Tables'!H30 -> 0 | O39: =IF(O33>=L39,(O33-L39)*N39,0) -> 0 | P39: =IF(P33>=L39,(P33-L39)*N39,0) -> 0
H41: Est. Tax Expense | J41: Difference | N41: Est. Tax Expense | P41: Difference
H42: =SUM(I34:I39) -> 12000 | I42: =SUM(J34:J39) -> 3024 | J42: =H42-I42 -> 8976 | N42: =SUM(O34:O39) -> 12000 | O42: =SUM(P34:P39) -> 3024 | P42: =N42-O42 -> 8976
G44: NIIT (pre Film) | H44: ='Tax Tables'!$C$34 -> 0.038
G45: =SUM(C6:C9)+C11 -> 0 | H45: =IF(C13-IF(C3="Married-Joint",250000,200000)>G45,(C13-IF(C3="Married-Joint",250000,200000))*H44, G45*H44) -> 5700

Sheet Film & DB
D2: % of Offset
B3: Filing Status - LA | C3: ='Strategy comparison'!C4 -> Married-Joint | D3: Income
B4: W2 Income | C4: ='Strategy comparison'!C5 -> 400000 | D4: 1 | F4: Federal Ordinary Income Tax
B5: Business Income | C5: ='Strategy comparison'!C6-'DB comparison'!C2 -> 0
B6: ST Capital Gains | C6: ='Strategy comparison'!C7 -> 0 | D6: Multiple On Contribution | F6: Married Filing Joint | I6: Ordinary Income | J6: Ordinary Income w Film | L6: Unmarried/Single | O6: Ordinary Income | P6: Ordinary Income w Filn
B7: Interest | C7: ='Strategy comparison'!$C$9 -> 0 | D7: 4.75 | I7: =C10 -> 400000 | J7: =C10-MIN(C10,C20) -> 0 | O7: =I7 -> 400000 | P7: =J7 -> 0
B8: Qualified Dividends | C8: ='Strategy comparison'!$C$10 -> 0 | D8: Unadjusted | F8: ='Tax Tables'!B6 -> 0 | G8: ='Tax Tables'!C6 -> 24800 | H8: ='Tax Tables'!D6 -> 0.1 | I8: =IF(IF(I$7>G8,(G8-F8)*H8,(I$7-F8)*H8)>0,IF(I$7>G8,(G8-F8)*H8,(I$7-F8)*H8),0) -> 2480 | J8: =IF(IF(J$7>G8,(G8-F8)*H8,(J$7-F8)*H8)>0,IF(J$7>G8,(G8-F8)*H8,(J$7-F8)*H8),0) -> 0 | L8: ='Tax Tables'!F6 -> 0 | M8: ='Tax Tables'!G6 -> 12400 | N8: ='Tax Tables'!H6 -> 0.1 | O8: =IF(IF(O$7>M8,(M8-L8)*N8,(O$7-L8)*N8)>0,IF(O$7>M8,(M8-L8)*N8,(O$7-L8)*N8),0) -> 1240 | P8: =IF(IF(P$7>M8,(M8-L8)*N8,(P$7-L8)*N8)>0,IF(P$7>M8,(M8-L8)*N8,(P$7-L8)*N8),0) -> 0
B9: Nonqualified Dividends | C9: ='Strategy comparison'!$C$11 -> 0 | D9: Contribution | F9: ='Tax Tables'!B7 -> 24801 | G9: ='Tax Tables'!C7 -> 100800 | H9: ='Tax Tables'!D7 -> 0.12 | I9: =IF(IF(I$7>G9,(G9-F9)*H9,(I$7-F9)*H9)>0,IF(I$7>G9,(G9-F9)*H9,(I$7-F9)*H9),0) -> 9119.88 | J9: =IF(IF(J$7>G9,(G9-F9)*H9,(J$7-F9)*H9)>0,IF(J$7>G9,(G9-F9)*H9,(J$7-F9)*H9),0) -> 0 | L9: ='Tax Tables'!F7 -> 12401 | M9: ='Tax Tables'!G7 -> 50400 | N9: ='Tax Tables'!H7 -> 0.12 | O9: =IF(IF(O$7>M9,(M9-L9)*N9,(O$7-L9)*N9)>0,IF(O$7>M9,(M9-L9)*N9,(O$7-L9)*N9),0) -> 4559.88 | P9: =IF(IF(P$7>M9,(M9-L9)*N9,(P$7-L9)*N9)>0,IF(P$7>M9,(M9-L9)*N9,(P$7-L9)*N9),0) -> 0
B10: Ordinary Income | C10: =SUM(C4:C7)+C9 -> 400000 | D10: =C20/D7 -> 84210.526 | F10: ='Tax Tables'!B8 -> 100801 | G10: ='Tax Tables'!C8 -> 211400 | H10: ='Tax Tables'!D8 -> 0.22 | I10: =IF(IF(I$7>G10,(G10-F10)*H10,(I$7-F10)*H10)>0,IF(I$7>G10,(G10-F10)*H10,(I$7-F10)*H10),0) -> 24331.78 | J10: =IF(IF(J$7>G10,(G10-F10)*H10,(J$7-F10)*H10)>0,IF(J$7>G10,(G10-F10)*H10,(J$7-F10)*H10),0) -> 0 | L10: ='Tax Tables'!F8 -> 50401 | M10: ='Tax Tables'!G8 -> 105700 | N10: ='Tax Tables'!H8 -> 0.22 | O10: =IF(IF(O$7>M10,(M10-L10)*N10,(O$7-L10)*N10)>0,IF(O$7>M10,(M10-L10)*N10,(O$7-L10)*N10),0) -> 12165.78 | P10: =IF(IF(P$7>M10,(M10-L10)*N10,(P$7-L10)*N10)>0,IF(P$7>M10,(M10-L10)*N10,(P$7-L10)*N10),0) -> 0
B11: LT Cap Gains | C11: ='Strategy comparison'!C8 -> 0 | D11: RIA Discount | F11: ='Tax Tables'!B9 -> 211401 | G11: ='Tax Tables'!C9 -> 403550 | H11: ='Tax Tables'!D9 -> 0.24 | I11: =IF(IF(I$7>G11,(G11-F11)*H11,(I$7-F11)*H11)>0,IF(I$7>G11,(G11-F11)*H11,(I$7-F11)*H11),0) -> 45263.76 | J11: =IF(IF(J$7>G11,(G11-F11)*H11,(J$7-F11)*H11)>0,IF(J$7>G11,(G11-F11)*H11,(J$7-F11)*H11),0) -> 0 | L11: ='Tax Tables'!F9 -> 105701 | M11: ='Tax Tables'!G9 -> 201775 | N11: ='Tax Tables'!H9 -> 0.24 | O11: =IF(IF(O$7>M11,(M11-L11)*N11,(O$7-L11)*N11)>0,IF(O$7>M11,(M11-L11)*N11,(O$7-L11)*N11),0) -> 23057.76 | P11: =IF(IF(P$7>M11,(M11-L11)*N11,(P$7-L11)*N11)>0,IF(P$7>M11,(M11-L11)*N11,(P$7-L11)*N11),0) -> 0
B12: LTCG + Qualified Dividends | C12: =C11+C8 -> 0 | D12: 0 | F12: ='Tax Tables'!B10 -> 403551 | G12: ='Tax Tables'!C10 -> 512450 | H12: ='Tax Tables'!D10 -> 0.32 | I12: =IF(IF(I$7>G12,(G12-F12)*H12,(I$7-F12)*H12)>0,IF(I$7>G12,(G12-F12)*H12,(I$7-F12)*H12),0) -> 0 | J12: =IF(IF(J$7>G12,(G12-F12)*H12,(J$7-F12)*H12)>0,IF(J$7>G12,(G12-F12)*H12,(J$7-F12)*H12),0) -> 0 | L12: ='Tax Tables'!F10 -> 201776 | M12: ='Tax Tables'!G10 -> 256225 | N12: ='Tax Tables'!H10 -> 0.32 | O12: =IF(IF(O$7>M12,(M12-L12)*N12,(O$7-L12)*N12)>0,IF(O$7>M12,(M12-L12)*N12,(O$7-L12)*N12),0) -> 17423.68 | P12: =IF(IF(P$7>M12,(M12-L12)*N12,(P$7-L12)*N12)>0,IF(P$7>M12,(M12-L12)*N12,(P$7-L12)*N12),0) -> 0
B13: AGI | C13: =C10+C12 -> 400000 | D13: Client Contribution | F13: ='Tax Tables'!B11 -> 512451 | G13: ='Tax Tables'!C11 -> 768700 | H13: ='Tax Tables'!D11 -> 0.35 | I13: =IF(IF(I$7>G13,(G13-F13)*H13,(I$7-F13)*H13)>0,IF(I$7>G13,(G13-F13)*H13,(I$7-F13)*H13),0) -> 0 | J13: =IF(IF(J$7>G13,(G13-F13)*H13,(J$7-F13)*H13)>0,IF(J$7>G13,(G13-F13)*H13,(J$7-F13)*H13),0) -> 0 | L13: ='Tax Tables'!F11 -> 256226 | M13: ='Tax Tables'!G11 -> 640600 | N13: ='Tax Tables'!H11 -> 0.35 | O13: =IF(IF(O$7>M13,(M13-L13)*N13,(O$7-L13)*N13)>0,IF(O$7>M13,(M13-L13)*N13,(O$7-L13)*N13),0) -> 50320.9 | P13: =IF(IF(P$7>M13,(M13-L13)*N13,(P$7-L13)*N13)>0,IF(P$7>M13,(M13-L13)*N13,(P$7-L13)*N13),0) -> 0
B14: Current Fed Tax | C14: =IF(C3="Single",N17,IF(C3="Married-Joint",H17,"Filing Status?")) -> 81195.42 | D14: =D10*(1-D12) -> 84210.526 | F14: ='Tax Tables'!B12 -> 768701 | G14: ='Tax Tables'!C12 -> 99999999999 | H14: ='Tax Tables'!D12 -> 0.37 | I14: =IF(I7>=F14,(I7-F14)*H14,0) -> 0 | J14: =IF(J7>=F14,(J7-F14)*H14,0) -> 0 | L14: ='Tax Tables'!F12 -> 640601 | M14: ='Tax Tables'!G12 -> 99999999999 | N14: ='Tax Tables'!H12 -> 0.37 | O14: =IF(O7>=L14,(O7-L14)*N14,0) -> 0 | P14: =IF(P7>=L14,(P7-L14)*N14,0) -> 0
B15: LT Cap Gains Tax | C15: =IF(C3="Single",N28,IF(C3="Married-Joint",H28,"Filing Status?")) -> 0 | D15: Consulting Fee
B16: Current State Tax | C16: =IF(C3="Single",N42,IF(C3="Married-Joint",H42,"Filing Status?")) -> 12000 | D16: ='Strategy comparison'!C12 -> 0 | H16: Est. Tax Expense | J16: Difference | N16: Est. Tax Expense | P16: Difference
B17: Total Inc Tax | C17: =SUM(C14:C16)+H45 -> 98895.42 | D17: Film Cost | H17: =SUM(I8:I14) -> 81195.42 | I17: =SUM(J8:J14) -> 0 | J17: =H17-I17 -> 81195.42 | N17: =SUM(O8:O14) -> 108768 | O17: =SUM(P8:P14) -> 0 | P17: =N17-O17 -> 108768
B18: Effective Tax Rate | C18: =C17/SUM(C10:C11) -> 0.24723855 | D18: =SUM(D14,D16) -> 84210.526
F19: Long Term Capital Gains & Qualified Dividends Tax
B20: Film Offset | C20: =IF('DB comparison'!G5="",(I7+I22)*D4,'DB comparison'!G5) -> 400000
B21: Post Offset Taxable Income | C21: =C13-C20 -> 0 | F21: Married Filing Joint | I21: LTCG & QD | J21: LTCG & QD w Film | L21: Unmarried/Single | O21: LTCG & QD | P21: LTCG & QD w Film
B22: Modified Fed | C22: =IF(C3="Single",O17,IF(C3="Married-Joint",I17,"Filing Status?")) -> 0 | I22: =C12 -> 0 | J22: =I22-IF(C20>I7,C20-I7,0) -> 0 | O22: =C12 -> 0 | P22: =J22 -> 0
B23: Mod State Tax | C23: =IF(C3="Single",O42,IF(C3="Married-Joint",I42,"Filing Status?")) -> 0 | F23: ='Tax Tables'!B18 -> 0 | G23: ='Tax Tables'!C18 -> 98900 | H23: ='Tax Tables'!D18 -> 0 | I23: =IF(I$22>$G23,($G23-$F23)*$H23,MAX((I$22-$F23),0)*$H23) -> 0 | J23: =IF(J$22>$G23,($G23-$F23)*$H23,MAX((J$22-$F23),0)*$H23) -> 0 | L23: ='Tax Tables'!F18 -> 0 | M23: ='Tax Tables'!G18 -> 49450 | N23: ='Tax Tables'!H18 -> 0 | O23: =IF(O$22>$M23,($M23-$L23)*$N23,MAX((O$22-$L23),0)*$N23) -> 0 | P23: =IF(P$22>$M23,($M23-$L23)*$N23,MAX((P$22-$L23),0)*$N23) -> 0
B24: LT Cap Gains Tax | C24: =IF(C3="Single",O28,IF(C3="Married-Joint",I28,"Filing Status?")) -> 0 | F24: ='Tax Tables'!B19 -> 98901 | G24: ='Tax Tables'!C19 -> 613700 | H24: ='Tax Tables'!D19 -> 0.15 | I24: =IF(I$22>$G24,($G24-$F24)*$H24,MAX((I$22-$F24),0)*$H24) -> 0 | J24: =IF(J$22>$G24,($G24-$F24)*$H24,MAX((J$22-$F24),0)*$H24) -> 0 | L24: ='Tax Tables'!F19 -> 49451 | M24: ='Tax Tables'!G19 -> 545500 | N24: ='Tax Tables'!H19 -> 0.15 | O24: =IF(O$22>$M24,($M24-$L24)*$N24,MAX((O$22-$L24),0)*$N24) -> 0 | P24: =IF(P$22>$M24,($M24-$L24)*$N24,MAX((P$22-$L24),0)*$N24) -> 0
B25: NIIT | C25: 0 | F25: ='Tax Tables'!B20 -> 613701 | G25: ='Tax Tables'!C20 -> 99999999999 | H25: ='Tax Tables'!D20 -> 0.2 | I25: =IF(I$22>$G25,($G25-$F25)*$H25,MAX((I$22-$F25),0)*$H25) -> 0 | J25: =IF(J$22>$G25,($G25-$F25)*$H25,MAX((J$22-$F25),0)*$H25) -> 0 | L25: ='Tax Tables'!F20 -> 545501 | M25: ='Tax Tables'!G20 -> 99999999999 | N25: ='Tax Tables'!H20 -> 0.2 | O25: =IF(O$22>$M25,($M25-$L25)*$N25,MAX((O$22-$L25),0)*$N25) -> 0 | P25: =IF(P$22>$M25,($M25-$L25)*$N25,MAX((P$22-$L25),0)*$N25) -> 0
B26: Total Mod Inc Tax | C26: =SUM(C22:C25) -> 0
B27: Effective Tax Rate | C27: =(C26+C29)/C13 -> 0.21052632 | H27: Est. Tax Expense | J27: Difference | N27: Est. Tax Expense | P27: Difference
B28: Tax Reduction | C28: =C17-C26 -> 98895.42 | H28: =SUM(I23:I25) -> 0 | I28: =SUM(J23:J25) -> 0 | J28: =H28-I28 -> 0 | N28: =SUM(O23:O25) -> 0 | O28: =SUM(P23:P25) -> 0 | P28: =N28-O28 -> 0
B29: Contribution + Fee | C29: =D18 -> 84210.526
B30: Access Net Savings | C30: =C28-C29 -> 14684.894 | F30: State Income Tax - Louisiana
F32: Married Filing Joint | I32: AGI | J32: AGI w Film | L32: Unmarried/Single | O32: AGI | P32: AGI w Film
I33: =C13 -> 400000 | J33: =I33-C20 -> 0 | O33: =I33 -> 400000 | P33: =J33 -> 0
F34: ='Tax Tables'!B25 -> 0 | G34: ='Tax Tables'!C25 -> 100000000 | H34: ='Tax Tables'!D25 -> 0.03 | I34: =IF(IF(I$33>G34,(G34-F34)*H34,(I$33-F34)*H34)>0,IF(I$33>G34,(G34-F34)*H34,(I$33-F34)*H34),0) -> 12000 | J34: =IF(IF(J$33>G34,(G34-F34)*H34,(J$33-F34)*H34)>0,IF(J$33>G34,(G34-F34)*H34,(J$33-F34)*H34),0) -> 0 | L34: ='Tax Tables'!F25 -> 0 | M34: ='Tax Tables'!G25 -> 100000000 | N34: ='Tax Tables'!H25 -> 0.03 | O34: =IF(IF(O$33>M34,(M34-L34)*N34,(O$33-L34)*N34)>0,IF(O$33>M34,(M34-L34)*N34,(O$33-L34)*N34),0) -> 12000 | P34: =IF(IF(P$33>M34,(M34-L34)*N34,(P$33-L34)*N34)>0,IF(P$33>M34,(M34-L34)*N34,(P$33-L34)*N34),0) -> 0
F35: ='Tax Tables'!B26 -> 0 | G35: ='Tax Tables'!C26 -> 0 | H35: ='Tax Tables'!D26 -> 0 | I35: =IF(IF(I$33>G35,(G35-F35)*H35,(I$33-F35)*H35)>0,IF(I$33>G35,(G35-F35)*H35,(I$33-F35)*H35),0) -> 0 | J35: =IF(IF(J$33>G35,(G35-F35)*H35,(J$33-F35)*H35)>0,IF(J$33>G35,(G35-F35)*H35,(J$33-F35)*H35),0) -> 0 | L35: ='Tax Tables'!F26 -> 0 | M35: ='Tax Tables'!G26 -> 0 | N35: ='Tax Tables'!H26 -> 0 | O35: =IF(IF(O$33>M35,(M35-L35)*N35,(O$33-L35)*N35)>0,IF(O$33>M35,(M35-L35)*N35,(O$33-L35)*N35),0) -> 0 | P35: =IF(IF(P$33>M35,(M35-L35)*N35,(P$33-L35)*N35)>0,IF(P$33>M35,(M35-L35)*N35,(P$33-L35)*N35),0) -> 0
F36: ='Tax Tables'!B27 -> 0 | G36: ='Tax Tables'!C27 -> 0 | H36: ='Tax Tables'!D27 -> 0 | I36: =IF(IF(I$33>G36,(G36-F36)*H36,(I$33-F36)*H36)>0,IF(I$33>G36,(G36-F36)*H36,(I$33-F36)*H36),0) -> 0 | J36: =IF(IF(J$33>G36,(G36-F36)*H36,(J$33-F36)*H36)>0,IF(J$33>G36,(G36-F36)*H36,(J$33-F36)*H36),0) -> 0 | L36: ='Tax Tables'!F27 -> 0 | M36: ='Tax Tables'!G27 -> 0 | N36: ='Tax Tables'!H27 -> 0 | O36: =IF(IF(O$33>M36,(M36-L36)*N36,(O$33-L36)*N36)>0,IF(O$33>M36,(M36-L36)*N36,(O$33-L36)*N36),0) -> 0 | P36: =IF(IF(P$33>M36,(M36-L36)*N36,(P$33-L36)*N36)>0,IF(P$33>M36,(M36-L36)*N36,(P$33-L36)*N36),0) -> 0
F37: ='Tax Tables'!B28 -> 0 | G37: ='Tax Tables'!C28 -> 0 | H37: ='Tax Tables'!D28 -> 0 | I37: =IF(IF(I$33>G37,(G37-F37)*H37,(I$33-F37)*H37)>0,IF(I$33>G37,(G37-F37)*H37,(I$33-F37)*H37),0) -> 0 | J37: =IF(IF(J$33>G37,(G37-F37)*H37,(J$33-F37)*H37)>0,IF(J$33>G37,(G37-F37)*H37,(J$33-F37)*H37),0) -> 0 | L37: ='Tax Tables'!F28 -> 0 | M37: ='Tax Tables'!G28 -> 0 | N37: ='Tax Tables'!H28 -> 0 | O37: =IF(IF(O$33>M37,(M37-L37)*N37,(O$33-L37)*N37)>0,IF(O$33>M37,(M37-L37)*N37,(O$33-L37)*N37),0) -> 0 | P37: =IF(IF(P$33>M37,(M37-L37)*N37,(P$33-L37)*N37)>0,IF(P$33>M37,(M37-L37)*N37,(P$33-L37)*N37),0) -> 0
F38: ='Tax Tables'!B29 -> 0 | G38: ='Tax Tables'!C29 -> 0 | H38: ='Tax Tables'!D29 -> 0 | I38: =IF(IF(I$33>G38,(G38-F38)*H38,(I$33-F38)*H38)>0,IF(I$33>G38,(G38-F38)*H38,(I$33-F38)*H38),0) -> 0 | J38: =IF(IF(J$33>G38,(G38-F38)*H38,(J$33-F38)*H38)>0,IF(J$33>G38,(G38-F38)*H38,(J$33-F38)*H38),0) -> 0 | L38: ='Tax Tables'!F29 -> 0 | M38: ='Tax Tables'!G29 -> 0 | N38: ='Tax Tables'!H29 -> 0 | O38: =IF(IF(O$33>M38,(M38-L38)*N38,(O$33-L38)*N38)>0,IF(O$33>M38,(M38-L38)*N38,(O$33-L38)*N38),0) -> 0 | P38: =IF(IF(P$33>M38,(M38-L38)*N38,(P$33-L38)*N38)>0,IF(P$33>M38,(M38-L38)*N38,(P$33-L38)*N38),0) -> 0
F39: ='Tax Tables'!B30 -> 0 | G39: ='Tax Tables'!C30 -> 0 | H39: ='Tax Tables'!D30 -> 0 | I39: =IF(I33>=F39,(I33-F39)*H39,0) -> 0 | J39: =IF(J33>=F39,(J33-F39)*H39,0) -> 0 | L39: ='Tax Tables'!F30 -> 0 | M39: ='Tax Tables'!G30 -> 0 | N39: ='Tax Tables'!H30 -> 0 | O39: =IF(O33>=L39,(O33-L39)*N39,0) -> 0 | P39: =IF(P33>=L39,(P33-L39)*N39,0) -> 0
H41: Est. Tax Expense | J41: Difference | N41: Est. Tax Expense | P41: Difference
H42: =SUM(I34:I39) -> 12000 | I42: =SUM(J34:J39) -> 0 | J42: =H42-I42 -> 12000 | N42: =SUM(O34:O39) -> 12000 | O42: =SUM(P34:P39) -> 0 | P42: =N42-O42 -> 12000
G44: NIIT (pre Film) | H44: ='Tax Tables'!$C$34 -> 0.038
G45: =SUM(C6:C9)+C11 -> 0 | H45: =IF(C13-IF(C3="Married-Joint",250000,200000)>G45,(C13-IF(C3="Married-Joint",250000,200000))*H44, G45*H44) -> 5700

Sheet Film & Roth
D2: % of Offset
B3: Filing Status - LA | C3: ='Strategy comparison'!C4 -> Married-Joint | D3: Income
B4: W2 Income | C4: ='Strategy comparison'!C5+'Roth comparison'!C2 -> 850000 | D4: 1 | F4: Federal Ordinary Income Tax
B5: Business Income | C5: ='Strategy comparison'!C6 -> 0
B6: ST Capital Gains | C6: ='Strategy comparison'!C7 -> 0 | D6: Multiple On Contribution | F6: Married Filing Joint | I6: Ordinary Income | J6: Ordinary Income w Film | L6: Unmarried/Single | O6: Ordinary Income | P6: Ordinary Income w Filn
B7: Interest | C7: ='Strategy comparison'!$C$9 -> 0 | D7: 4.75 | I7: =C10 -> 850000 | J7: =C10-MIN(C10,C20) -> 0 | O7: =I7 -> 850000 | P7: =J7 -> 0
B8: Qualified Dividends | C8: ='Strategy comparison'!$C$10 -> 0 | D8: Unadjusted | F8: ='Tax Tables'!B6 -> 0 | G8: ='Tax Tables'!C6 -> 24800 | H8: ='Tax Tables'!D6 -> 0.1 | I8: =IF(IF(I$7>G8,(G8-F8)*H8,(I$7-F8)*H8)>0,IF(I$7>G8,(G8-F8)*H8,(I$7-F8)*H8),0) -> 2480 | J8: =IF(IF(J$7>G8,(G8-F8)*H8,(J$7-F8)*H8)>0,IF(J$7>G8,(G8-F8)*H8,(J$7-F8)*H8),0) -> 0 | L8: ='Tax Tables'!F6 -> 0 | M8: ='Tax Tables'!G6 -> 12400 | N8: ='Tax Tables'!H6 -> 0.1 | O8: =IF(IF(O$7>M8,(M8-L8)*N8,(O$7-L8)*N8)>0,IF(O$7>M8,(M8-L8)*N8,(O$7-L8)*N8),0) -> 1240 | P8: =IF(IF(P$7>M8,(M8-L8)*N8,(P$7-L8)*N8)>0,IF(P$7>M8,(M8-L8)*N8,(P$7-L8)*N8),0) -> 0
B9: Nonqualified Dividends | C9: ='Strategy comparison'!$C$11 -> 0 | D9: Contribution | F9: ='Tax Tables'!B7 -> 24801 | G9: ='Tax Tables'!C7 -> 100800 | H9: ='Tax Tables'!D7 -> 0.12 | I9: =IF(IF(I$7>G9,(G9-F9)*H9,(I$7-F9)*H9)>0,IF(I$7>G9,(G9-F9)*H9,(I$7-F9)*H9),0) -> 9119.88 | J9: =IF(IF(J$7>G9,(G9-F9)*H9,(J$7-F9)*H9)>0,IF(J$7>G9,(G9-F9)*H9,(J$7-F9)*H9),0) -> 0 | L9: ='Tax Tables'!F7 -> 12401 | M9: ='Tax Tables'!G7 -> 50400 | N9: ='Tax Tables'!H7 -> 0.12 | O9: =IF(IF(O$7>M9,(M9-L9)*N9,(O$7-L9)*N9)>0,IF(O$7>M9,(M9-L9)*N9,(O$7-L9)*N9),0) -> 4559.88 | P9: =IF(IF(P$7>M9,(M9-L9)*N9,(P$7-L9)*N9)>0,IF(P$7>M9,(M9-L9)*N9,(P$7-L9)*N9),0) -> 0
B10: Ordinary Income | C10: =SUM(C4:C7)+C9 -> 850000 | D10: =C20/D7 -> 178947.37 | F10: ='Tax Tables'!B8 -> 100801 | G10: ='Tax Tables'!C8 -> 211400 | H10: ='Tax Tables'!D8 -> 0.22 | I10: =IF(IF(I$7>G10,(G10-F10)*H10,(I$7-F10)*H10)>0,IF(I$7>G10,(G10-F10)*H10,(I$7-F10)*H10),0) -> 24331.78 | J10: =IF(IF(J$7>G10,(G10-F10)*H10,(J$7-F10)*H10)>0,IF(J$7>G10,(G10-F10)*H10,(J$7-F10)*H10),0) -> 0 | L10: ='Tax Tables'!F8 -> 50401 | M10: ='Tax Tables'!G8 -> 105700 | N10: ='Tax Tables'!H8 -> 0.22 | O10: =IF(IF(O$7>M10,(M10-L10)*N10,(O$7-L10)*N10)>0,IF(O$7>M10,(M10-L10)*N10,(O$7-L10)*N10),0) -> 12165.78 | P10: =IF(IF(P$7>M10,(M10-L10)*N10,(P$7-L10)*N10)>0,IF(P$7>M10,(M10-L10)*N10,(P$7-L10)*N10),0) -> 0
B11: LT Cap Gains | C11: ='Strategy comparison'!C8 -> 0 | D11: RIA Discount | F11: ='Tax Tables'!B9 -> 211401 | G11: ='Tax Tables'!C9 -> 403550 | H11: ='Tax Tables'!D9 -> 0.24 | I11: =IF(IF(I$7>G11,(G11-F11)*H11,(I$7-F11)*H11)>0,IF(I$7>G11,(G11-F11)*H11,(I$7-F11)*H11),0) -> 46115.76 | J11: =IF(IF(J$7>G11,(G11-F11)*H11,(J$7-F11)*H11)>0,IF(J$7>G11,(G11-F11)*H11,(J$7-F11)*H11),0) -> 0 | L11: ='Tax Tables'!F9 -> 105701 | M11: ='Tax Tables'!G9 -> 201775 | N11: ='Tax Tables'!H9 -> 0.24 | O11: =IF(IF(O$7>M11,(M11-L11)*N11,(O$7-L11)*N11)>0,IF(O$7>M11,(M11-L11)*N11,(O$7-L11)*N11),0) -> 23057.76 | P11: =IF(IF(P$7>M11,(M11-L11)*N11,(P$7-L11)*N11)>0,IF(P$7>M11,(M11-L11)*N11,(P$7-L11)*N11),0) -> 0
B12: LTCG + Qualified Dividends | C12: =C11+C8 -> 0 | D12: 0 | F12: ='Tax Tables'!B10 -> 403551 | G12: ='Tax Tables'!C10 -> 512450 | H12: ='Tax Tables'!D10 -> 0.32 | I12: =IF(IF(I$7>G12,(G12-F12)*H12,(I$7-F12)*H12)>0,IF(I$7>G12,(G12-F12)*H12,(I$7-F12)*H12),0) -> 34847.68 | J12: =IF(IF(J$7>G12,(G12-F12)*H12,(J$7-F12)*H12)>0,IF(J$7>G12,(G12-F12)*H12,(J$7-F12)*H12),0) -> 0 | L12: ='Tax Tables'!F10 -> 201776 | M12: ='Tax Tables'!G10 -> 256225 | N12: ='Tax Tables'!H10 -> 0.32 | O12: =IF(IF(O$7>M12,(M12-L12)*N12,(O$7-L12)*N12)>0,IF(O$7>M12,(M12-L12)*N12,(O$7-L12)*N12),0) -> 17423.68 | P12: =IF(IF(P$7>M12,(M12-L12)*N12,(P$7-L12)*N12)>0,IF(P$7>M12,(M12-L12)*N12,(P$7-L12)*N12),0) -> 0
B13: AGI | C13: =C10+C12 -> 850000 | D13: Client Contribution | F13: ='Tax Tables'!B11 -> 512451 | G13: ='Tax Tables'!C11 -> 768700 | H13: ='Tax Tables'!D11 -> 0.35 | I13: =IF(IF(I$7>G13,(G13-F13)*H13,(I$7-F13)*H13)>0,IF(I$7>G13,(G13-F13)*H13,(I$7-F13)*H13),0) -> 89687.15 | J13: =IF(IF(J$7>G13,(G13-F13)*H13,(J$7-F13)*H13)>0,IF(J$7>G13,(G13-F13)*H13,(J$7-F13)*H13),0) -> 0 | L13: ='Tax Tables'!F11 -> 256226 | M13: ='Tax Tables'!G11 -> 640600 | N13: ='Tax Tables'!H11 -> 0.35 | O13: =IF(IF(O$7>M13,(M13-L13)*N13,(O$7-L13)*N13)>0,IF(O$7>M13,(M13-L13)*N13,(O$7-L13)*N13),0) -> 134530.9 | P13: =IF(IF(P$7>M13,(M13-L13)*N13,(P$7-L13)*N13)>0,IF(P$7>M13,(M13-L13)*N13,(P$7-L13)*N13),0) -> 0
B14: Current Fed Tax | C14: =IF(C3="Single",N17,IF(C3="Married-Joint",H17,"Filing Status?")) -> 236662.88 | D14: =D10*(1-D12) -> 178947.37 | F14: ='Tax Tables'!B12 -> 768701 | G14: ='Tax Tables'!C12 -> 99999999999 | H14: ='Tax Tables'!D12 -> 0.37 | I14: =IF(I7>=F14,(I7-F14)*H14,0) -> 30080.63 | J14: =IF(J7>=F14,(J7-F14)*H14,0) -> 0 | L14: ='Tax Tables'!F12 -> 640601 | M14: ='Tax Tables'!G12 -> 99999999999 | N14: ='Tax Tables'!H12 -> 0.37 | O14: =IF(O7>=L14,(O7-L14)*N14,0) -> 77477.63 | P14: =IF(P7>=L14,(P7-L14)*N14,0) -> 0
B15: LT Cap Gains Tax | C15: =IF(C3="Single",N28,IF(C3="Married-Joint",H28,"Filing Status?")) -> 0 | D15: Consulting Fee
B16: Current State Tax | C16: =IF(C3="Single",N42,IF(C3="Married-Joint",H42,"Filing Status?")) -> 25500 | D16: ='Strategy comparison'!C12 -> 0 | H16: Est. Tax Expense | J16: Difference | N16: Est. Tax Expense | P16: Difference
B17: Total Inc Tax | C17: =SUM(C14:C16)+H45 -> 284962.88 | D17: Film Cost | H17: =SUM(I8:I14) -> 236662.88 | I17: =SUM(J8:J14) -> 0 | J17: =H17-I17 -> 236662.88 | N17: =SUM(O8:O14) -> 270455.63 | O17: =SUM(P8:P14) -> 0 | P17: =N17-O17 -> 270455.63
B18: Effective Tax Rate | C18: =C17/SUM(C10:C11) -> 0.33525045 | D18: =SUM(D14,D16) -> 178947.37
F19: Long Term Capital Gains & Qualified Dividends Tax
B20: Film Offset | C20: =IF('Roth comparison'!G5="",(I7+I22)*D4,'Roth comparison'!G5) -> 850000
B21: Post Offset Taxable Income | C21: =C13-C20 -> 0 | F21: Married Filing Joint | I21: LTCG & QD | J21: LTCG & QD w Film | L21: Unmarried/Single | O21: LTCG & QD | P21: LTCG & QD w Film
B22: Modified Fed | C22: =IF(C3="Single",O17,IF(C3="Married-Joint",I17,"Filing Status?")) -> 0 | I22: =C12 -> 0 | J22: =I22-IF(C20>I7,C20-I7,0) -> 0 | O22: =C12 -> 0 | P22: =J22 -> 0
B23: Mod State Tax | C23: =IF(C3="Single",O42,IF(C3="Married-Joint",I42,"Filing Status?")) -> 0 | F23: ='Tax Tables'!B18 -> 0 | G23: ='Tax Tables'!C18 -> 98900 | H23: ='Tax Tables'!D18 -> 0 | I23: =IF(I$22>$G23,($G23-$F23)*$H23,MAX((I$22-$F23),0)*$H23) -> 0 | J23: =IF(J$22>$G23,($G23-$F23)*$H23,MAX((J$22-$F23),0)*$H23) -> 0 | L23: ='Tax Tables'!F18 -> 0 | M23: ='Tax Tables'!G18 -> 49450 | N23: ='Tax Tables'!H18 -> 0 | O23: =IF(O$22>$M23,($M23-$L23)*$N23,MAX((O$22-$L23),0)*$N23) -> 0 | P23: =IF(P$22>$M23,($M23-$L23)*$N23,MAX((P$22-$L23),0)*$N23) -> 0
B24: LT Cap Gains Tax | C24: =IF(C3="Single",O28,IF(C3="Married-Joint",I28,"Filing Status?")) -> 0 | F24: ='Tax Tables'!B19 -> 98901 | G24: ='Tax Tables'!C19 -> 613700 | H24: ='Tax Tables'!D19 -> 0.15 | I24: =IF(I$22>$G24,($G24-$F24)*$H24,MAX((I$22-$F24),0)*$H24) -> 0 | J24: =IF(J$22>$G24,($G24-$F24)*$H24,MAX((J$22-$F24),0)*$H24) -> 0 | L24: ='Tax Tables'!F19 -> 49451 | M24: ='Tax Tables'!G19 -> 545500 | N24: ='Tax Tables'!H19 -> 0.15 | O24: =IF(O$22>$M24,($M24-$L24)*$N24,MAX((O$22-$L24),0)*$N24) -> 0 | P24: =IF(P$22>$M24,($M24-$L24)*$N24,MAX((P$22-$L24),0)*$N24) -> 0
B25: NIIT | C25: 0 | F25: ='Tax Tables'!B20 -> 613701 | G25: ='Tax Tables'!C20 -> 99999999999 | H25: ='Tax Tables'!D20 -> 0.2 | I25: =IF(I$22>$G25,($G25-$F25)*$H25,MAX((I$22-$F25),0)*$H25) -> 0 | J25: =IF(J$22>$G25,($G25-$F25)*$H25,MAX((J$22-$F25),0)*$H25) -> 0 | L25: ='Tax Tables'!F20 -> 545501 | M25: ='Tax Tables'!G20 -> 99999999999 | N25: ='Tax Tables'!H20 -> 0.2 | O25: =IF(O$22>$M25,($M25-$L25)*$N25,MAX((O$22-$L25),0)*$N25) -> 0 | P25: =IF(P$22>$M25,($M25-$L25)*$N25,MAX((P$22-$L25),0)*$N25) -> 0
B26: Total Mod Inc Tax | C26: =SUM(C22:C25) -> 0
B27: Effective Tax Rate | C27: =(C26+C29)/C13 -> 0.21052632 | H27: Est. Tax Expense | J27: Difference | N27: Est. Tax Expense | P27: Difference
B28: Tax Reduction | C28: =C17-C26 -> 284962.88 | H28: =SUM(I23:I25) -> 0 | I28: =SUM(J23:J25) -> 0 | J28: =H28-I28 -> 0 | N28: =SUM(O23:O25) -> 0 | O28: =SUM(P23:P25) -> 0 | P28: =N28-O28 -> 0
B29: Contribution + Fee | C29: =D18 -> 178947.37
B30: Access Net Savings | C30: =C28-C29 -> 106015.51 | F30: State Income Tax - Louisiana
F32: Married Filing Joint | I32: AGI | J32: AGI w Film | L32: Unmarried/Single | O32: AGI | P32: AGI w Film
I33: =C13 -> 850000 | J33: =I33-C20 -> 0 | O33: =I33 -> 850000 | P33: =J33 -> 0
F34: ='Tax Tables'!B25 -> 0 | G34: ='Tax Tables'!C25 -> 100000000 | H34: ='Tax Tables'!D25 -> 0.03 | I34: =IF(IF(I$33>G34,(G34-F34)*H34,(I$33-F34)*H34)>0,IF(I$33>G34,(G34-F34)*H34,(I$33-F34)*H34),0) -> 25500 | J34: =IF(IF(J$33>G34,(G34-F34)*H34,(J$33-F34)*H34)>0,IF(J$33>G34,(G34-F34)*H34,(J$33-F34)*H34),0) -> 0 | L34: ='Tax Tables'!F25 -> 0 | M34: ='Tax Tables'!G25 -> 100000000 | N34: ='Tax Tables'!H25 -> 0.03 | O34: =IF(IF(O$33>M34,(M34-L34)*N34,(O$33-L34)*N34)>0,IF(O$33>M34,(M34-L34)*N34,(O$33-L34)*N34),0) -> 25500 | P34: =IF(IF(P$33>M34,(M34-L34)*N34,(P$33-L34)*N34)>0,IF(P$33>M34,(M34-L34)*N34,(P$33-L34)*N34),0) -> 0
F35: ='Tax Tables'!B26 -> 0 | G35: ='Tax Tables'!C26 -> 0 | H35: ='Tax Tables'!D26 -> 0 | I35: =IF(IF(I$33>G35,(G35-F35)*H35,(I$33-F35)*H35)>0,IF(I$33>G35,(G35-F35)*H35,(I$33-F35)*H35),0) -> 0 | J35: =IF(IF(J$33>G35,(G35-F35)*H35,(J$33-F35)*H35)>0,IF(J$33>G35,(G35-F35)*H35,(J$33-F35)*H35),0) -> 0 | L35: ='Tax Tables'!F26 -> 0 | M35: ='Tax Tables'!G26 -> 0 | N35: ='Tax Tables'!H26 -> 0 | O35: =IF(IF(O$33>M35,(M35-L35)*N35,(O$33-L35)*N35)>0,IF(O$33>M35,(M35-L35)*N35,(O$33-L35)*N35),0) -> 0 | P35: =IF(IF(P$33>M35,(M35-L35)*N35,(P$33-L35)*N35)>0,IF(P$33>M35,(M35-L35)*N35,(P$33-L35)*N35),0) -> 0
F36: ='Tax Tables'!B27 -> 0 | G36: ='Tax Tables'!C27 -> 0 | H36: ='Tax Tables'!D27 -> 0 | I36: =IF(IF(I$33>G36,(G36-F36)*H36,(I$33-F36)*H36)>0,IF(I$33>G36,(G36-F36)*H36,(I$33-F36)*H36),0) -> 0 | J36: =IF(IF(J$33>G36,(G36-F36)*H36,(J$33-F36)*H36)>0,IF(J$33>G36,(G36-F36)*H36,(J$33-F36)*H36),0) -> 0 | L36: ='Tax Tables'!F27 -> 0 | M36: ='Tax Tables'!G27 -> 0 | N36: ='Tax Tables'!H27 -> 0 | O36: =IF(IF(O$33>M36,(M36-L36)*N36,(O$33-L36)*N36)>0,IF(O$33>M36,(M36-L36)*N36,(O$33-L36)*N36),0) -> 0 | P36: =IF(IF(P$33>M36,(M36-L36)*N36,(P$33-L36)*N36)>0,IF(P$33>M36,(M36-L36)*N36,(P$33-L36)*N36),0) -> 0
F37: ='Tax Tables'!B28 -> 0 | G37: ='Tax Tables'!C28 -> 0 | H37: ='Tax Tables'!D28 -> 0 | I37: =IF(IF(I$33>G37,(G37-F37)*H37,(I$33-F37)*H37)>0,IF(I$33>G37,(G37-F37)*H37,(I$33-F37)*H37),0) -> 0 | J37: =IF(IF(J$33>G37,(G37-F37)*H37,(J$33-F37)*H37)>0,IF(J$33>G37,(G37-F37)*H37,(J$33-F37)*H37),0) -> 0 | L37: ='Tax Tables'!F28 -> 0 | M37: ='Tax Tables'!G28 -> 0 | N37: ='Tax Tables'!H28 -> 0 | O37: =IF(IF(O$33>M37,(M37-L37)*N37,(O$33-L37)*N37)>0,IF(O$33>M37,(M37-L37)*N37,(O$33-L37)*N37),0) -> 0 | P37: =IF(IF(P$33>M37,(M37-L37)*N37,(P$33-L37)*N37)>0,IF(P$33>M37,(M37-L37)*N37,(P$33-L37)*N37),0) -> 0
F38: ='Tax Tables'!B29 -> 0 | G38: ='Tax Tables'!C29 -> 0 | H38: ='Tax Tables'!D29 -> 0 | I38: =IF(IF(I$33>G38,(G38-F38)*H38,(I$33-F38)*H38)>0,IF(I$33>G38,(G38-F38)*H38,(I$33-F38)*H38),0) -> 0 | J38: =IF(IF(J$33>G38,(G38-F38)*H38,(J$33-F38)*H38)>0,IF(J$33>G38,(G38-F38)*H38,(J$33-F38)*H38),0) -> 0 | L38: ='Tax Tables'!F29 -> 0 | M38: ='Tax Tables'!G29 -> 0 | N38: ='Tax Tables'!H29 -> 0 | O38: =IF(IF(O$33>M38,(M38-L38)*N38,(O$33-L38)*N38)>0,IF(O$33>M38,(M38-L38)*N38,(O$33-L38)*N38),0) -> 0 | P38: =IF(IF(P$33>M38,(M38-L38)*N38,(P$33-L38)*N38)>0,IF(P$33>M38,(M38-L38)*N38,(P$33-L38)*N38),0) -> 0
F39: ='Tax Tables'!B30 -> 0 | G39: ='Tax Tables'!C30 -> 0 | H39: ='Tax Tables'!D30 -> 0 | I39: =IF(I33>=F39,(I33-F39)*H39,0) -> 0 | J39: =IF(J33>=F39,(J33-F39)*H39,0) -> 0 | L39: ='Tax Tables'!F30 -> 0 | M39: ='Tax Tables'!G30 -> 0 | N39: ='Tax Tables'!H30 -> 0 | O39: =IF(O33>=L39,(O33-L39)*N39,0) -> 0 | P39: =IF(P33>=L39,(P33-L39)*N39,0) -> 0
H41: Est. Tax Expense | J41: Difference | N41: Est. Tax Expense | P41: Difference
H42: =SUM(I34:I39) -> 25500 | I42: =SUM(J34:J39) -> 0 | J42: =H42-I42 -> 25500 | N42: =SUM(O34:O39) -> 25500 | O42: =SUM(P34:P39) -> 0 | P42: =N42-O42 -> 25500
G44: NIIT (pre Film) | H44: ='Tax Tables'!$C$34 -> 0.038
G45: =SUM(C6:C9)+C11 -> 0 | H45: =IF(C13-IF(C3="Married-Joint",250000,200000)>G45,(C13-IF(C3="Married-Joint",250000,200000))*H44, G45*H44) -> 22800

Sheet Solar
B4: Solar Strategy Inputs | D4: Solar Strategy Details | G4: Federal Ordinary Income Tax
B5: Filing Status - LA | C5: ='Strategy comparison'!C4 -> Married-Joint | D5: Reducible Taxes | E5: =IF(C5="Married-Joint",I17+I28+I45,IF(C5="Single",O17+O28+I45,"Filing Status?")) -> 86895.42
B6: W2 Income | C6: ='Strategy comparison'!C5 -> 400000 | D6: Equity Contribution | E6: =C18 -> 70583.134 | G6: Married Filing Joint | J6: Ordinary Income | K6: Non-LTCG AGI w Gift | M6: Unmarried/Single | P6: Ordinary Income | Q6: Non-LTCG AGI w Gift
B7: Business Income | C7: ='Strategy comparison'!C6 -> 0 | D7: Upfront Electric Sale | E7: =E8-E6 -> 125456.99 | J7: =C12 -> 400000 | K7: =J7-MIN(C15*#REF!,J7) -> #REF! | P7: =J7 -> 400000 | Q7: =K7 -> #REF!
B8: ST Capital Gains | C8: ='Strategy comparison'!C7 -> 0 | D8: Project Cost | E8: =C18/C16 -> 196064.26 | G8: ='Tax Tables'!B6 -> 0 | H8: ='Tax Tables'!C6 -> 24800 | I8: ='Tax Tables'!D6 -> 0.1 | J8: =IF(IF(J$7>H8,(H8-G8)*I8,(J$7-G8)*I8)>0,IF(J$7>H8,(H8-G8)*I8,(J$7-G8)*I8),0) -> 2480 | K8: =IF(IF(K$7>H8,(H8-G8)*I8,(K$7-G8)*I8)>0,IF(K$7>H8,(H8-G8)*I8,(K$7-G8)*I8),0) -> #REF! | M8: ='Tax Tables'!F6 -> 0 | N8: ='Tax Tables'!G6 -> 12400 | O8: ='Tax Tables'!H6 -> 0.1 | P8: =IF(IF(P$7>N8,(N8-M8)*O8,(P$7-M8)*O8)>0,IF(P$7>N8,(N8-M8)*O8,(P$7-M8)*O8),0) -> 1240 | Q8: =IF(IF(Q$7>N8,(N8-M8)*O8,(Q$7-M8)*O8)>0,IF(Q$7>N8,(N8-M8)*O8,(Q$7-M8)*O8),0) -> #REF!
B9: Interest | C9: ='Strategy comparison'!$C$9 -> 0 | D9: Fed Credit | E9: =E8*C17 -> 78425.704 | G9: ='Tax Tables'!B7 -> 24801 | H9: ='Tax Tables'!C7 -> 100800 | I9: ='Tax Tables'!D7 -> 0.12 | J9: =IF(IF(J$7>H9,(H9-G9)*I9,(J$7-G9)*I9)>0,IF(J$7>H9,(H9-G9)*I9,(J$7-G9)*I9),0) -> 9119.88 | K9: =IF(IF(K$7>H9,(H9-G9)*I9,(K$7-G9)*I9)>0,IF(K$7>H9,(H9-G9)*I9,(K$7-G9)*I9),0) -> #REF! | M9: ='Tax Tables'!F7 -> 12401 | N9: ='Tax Tables'!G7 -> 50400 | O9: ='Tax Tables'!H7 -> 0.12 | P9: =IF(IF(P$7>N9,(N9-M9)*O9,(P$7-M9)*O9)>0,IF(P$7>N9,(N9-M9)*O9,(P$7-M9)*O9),0) -> 4559.88 | Q9: =IF(IF(Q$7>N9,(N9-M9)*O9,(Q$7-M9)*O9)>0,IF(Q$7>N9,(N9-M9)*O9,(Q$7-M9)*O9),0) -> #REF!
B10: Qualified Dividends | C10: ='Strategy comparison'!$C$10 -> 0 | D10: Depreciation Benefit Yr 1 | E10: =E16 -> 7522.1477 | G10: ='Tax Tables'!B8 -> 100801 | H10: ='Tax Tables'!C8 -> 211400 | I10: ='Tax Tables'!D8 -> 0.22 | J10: =IF(IF(J$7>H10,(H10-G10)*I10,(J$7-G10)*I10)>0,IF(J$7>H10,(H10-G10)*I10,(J$7-G10)*I10),0) -> 24331.78 | K10: =IF(IF(K$7>H10,(H10-G10)*I10,(K$7-G10)*I10)>0,IF(K$7>H10,(H10-G10)*I10,(K$7-G10)*I10),0) -> #REF! | M10: ='Tax Tables'!F8 -> 50401 | N10: ='Tax Tables'!G8 -> 105700 | O10: ='Tax Tables'!H8 -> 0.22 | P10: =IF(IF(P$7>N10,(N10-M10)*O10,(P$7-M10)*O10)>0,IF(P$7>N10,(N10-M10)*O10,(P$7-M10)*O10),0) -> 12165.78 | Q10: =IF(IF(Q$7>N10,(N10-M10)*O10,(Q$7-M10)*O10)>0,IF(Q$7>N10,(N10-M10)*O10,(Q$7-M10)*O10),0) -> #REF!
B11: Nonqualified Dividends | C11: ='Strategy comparison'!$C$11 -> 0 | D11: Solar Tax Benefit Yr 1 | E11: =SUM(E9:E10)+K42 -> 86888.121 | G11: ='Tax Tables'!B9 -> 211401 | H11: ='Tax Tables'!C9 -> 403550 | I11: ='Tax Tables'!D9 -> 0.24 | J11: =IF(IF(J$7>H11,(H11-G11)*I11,(J$7-G11)*I11)>0,IF(J$7>H11,(H11-G11)*I11,(J$7-G11)*I11),0) -> 45263.76 | K11: =IF(IF(K$7>H11,(H11-G11)*I11,(K$7-G11)*I11)>0,IF(K$7>H11,(H11-G11)*I11,(K$7-G11)*I11),0) -> #REF! | M11: ='Tax Tables'!F9 -> 105701 | N11: ='Tax Tables'!G9 -> 201775 | O11: ='Tax Tables'!H9 -> 0.24 | P11: =IF(IF(P$7>N11,(N11-M11)*O11,(P$7-M11)*O11)>0,IF(P$7>N11,(N11-M11)*O11,(P$7-M11)*O11),0) -> 23057.76 | Q11: =IF(IF(Q$7>N11,(N11-M11)*O11,(Q$7-M11)*O11)>0,IF(Q$7>N11,(N11-M11)*O11,(Q$7-M11)*O11),0) -> #REF!
B12: Ordinary Income | C12: =SUM(C6:C9)+C11 -> 400000 | D12: Solar Tax Net Savings | E12: =E11-C18-'Strategy comparison'!C12 -> 16304.987 | G12: ='Tax Tables'!B10 -> 403551 | H12: ='Tax Tables'!C10 -> 512450 | I12: ='Tax Tables'!D10 -> 0.32 | J12: =IF(IF(J$7>H12,(H12-G12)*I12,(J$7-G12)*I12)>0,IF(J$7>H12,(H12-G12)*I12,(J$7-G12)*I12),0) -> 0 | K12: =IF(IF(K$7>H12,(H12-G12)*I12,(K$7-G12)*I12)>0,IF(K$7>H12,(H12-G12)*I12,(K$7-G12)*I12),0) -> #REF! | M12: ='Tax Tables'!F10 -> 201776 | N12: ='Tax Tables'!G10 -> 256225 | O12: ='Tax Tables'!H10 -> 0.32 | P12: =IF(IF(P$7>N12,(N12-M12)*O12,(P$7-M12)*O12)>0,IF(P$7>N12,(N12-M12)*O12,(P$7-M12)*O12),0) -> 17423.68 | Q12: =IF(IF(Q$7>N12,(N12-M12)*O12,(Q$7-M12)*O12)>0,IF(Q$7>N12,(N12-M12)*O12,(Q$7-M12)*O12),0) -> #REF!
B13: LTCG | C13: ='Strategy comparison'!C8 -> 0 | D13: Depreciable Basis | E13: =E8-(E9/2) -> 156851.41 | G13: ='Tax Tables'!B11 -> 512451 | H13: ='Tax Tables'!C11 -> 768700 | I13: ='Tax Tables'!D11 -> 0.35 | J13: =IF(IF(J$7>H13,(H13-G13)*I13,(J$7-G13)*I13)>0,IF(J$7>H13,(H13-G13)*I13,(J$7-G13)*I13),0) -> 0 | K13: =IF(IF(K$7>H13,(H13-G13)*I13,(K$7-G13)*I13)>0,IF(K$7>H13,(H13-G13)*I13,(K$7-G13)*I13),0) -> #REF! | M13: ='Tax Tables'!F11 -> 256226 | N13: ='Tax Tables'!G11 -> 640600 | O13: ='Tax Tables'!H11 -> 0.35 | P13: =IF(IF(P$7>N13,(N13-M13)*O13,(P$7-M13)*O13)>0,IF(P$7>N13,(N13-M13)*O13,(P$7-M13)*O13),0) -> 50320.9 | Q13: =IF(IF(Q$7>N13,(N13-M13)*O13,(Q$7-M13)*O13)>0,IF(Q$7>N13,(N13-M13)*O13,(Q$7-M13)*O13),0) -> #REF!
B14: LTCG & Qualified Dividends | C14: =C13+C10 -> 0 | D14: Upfront Electric Sale | E14: =E7 -> 125456.99 | G14: ='Tax Tables'!B12 -> 768701 | H14: ='Tax Tables'!C12 -> 99999999999 | I14: ='Tax Tables'!D12 -> 0.37 | J14: =IF(J7>=G14,(J7-G14)*I14,0) -> 0 | K14: =IF(K7>=G14,(K7-G14)*I14,0) -> #REF! | M14: ='Tax Tables'!F12 -> 640601 | N14: ='Tax Tables'!G12 -> 99999999999 | O14: ='Tax Tables'!H12 -> 0.37 | P14: =IF(P7>=M14,(P7-M14)*O14,0) -> 0 | Q14: =IF(Q7>=M14,(Q7-M14)*O14,0) -> #REF!
B15: AGI | C15: =C12+C14 -> 400000 | D15: Net Depreciation Yr 1 | E15: =E13-E14 -> 31394.419
B16: % Equity Contribution | C16: 0.36 | D16: Depreciation Benefit Yr 1 | E16: =IF($C$5="Married-Joint", I17-((MAX(0,MIN(J7-E15,H8)-G8)*I8) +(MAX(0,MIN(J7-E15,H9)-G9)*I9) +(MAX(0,MIN(J7-E15,H10)-G10)*I10) +(MAX(0,MIN(J7-E15,H11)-G11)*I11) +(MAX(0,MIN(J7-E15,H12)-G12)*I12) +(MAX(0,MIN(J7-E15,H13)-G13)*I13) +(MAX(0,MIN(J7-E15,H14)-G14)*I14)), O17-((MAX(0,MIN(P7-E15,N8)-M8)*O8) +(MAX(0,MIN(P7-E15,N9)-M9)*O9) +(MAX(0,MIN(P7-E15,N10)-M10)*O10) +(MAX(0,MIN(P7-E15,N11)-M11)*O11) +(MAX(0,MIN(P7-E15,N12)-M12)*O12) +(MAX(0,MIN(P7-E15,N13)-M13)*O13) +(MAX(0,MIN(P7-E15,N14)-M14)*O14)) ) -> 7534.6607 | I16: Est. Tax Expense | K16: Difference | O16: Est. Tax Expense | Q16: Difference
B17: % Fed Credit | C17: 0.4 | I17: =SUM(J8:J14) -> 81195.42 | J17: =SUM(K8:K14) -> #REF! | K17: =I17-J17 -> #REF! | O17: =SUM(P8:P14) -> 108768 | P17: =SUM(Q8:Q14) -> #REF! | Q17: =O17-P17 -> #REF!
B18: Equity Contribution Input | C18: =IF('Strategy comparison'!H18="",IF(E11>E5,IF(ABS(E5-E11)>10000,C18-(0.01*E5),C18-(0.0001*E5)),IF(ABS(E5-E11)>10000,C18+(0.01*E5),C18+(0.0001*E5))),'Strategy comparison'!H18) -> 70591.824
G19: Long Term Capital Gains & Qualified Dividends Tax
B20: Fed Taxes Remaining | C20: =IF(ABS(SUM('Strategy comparison'!F4:F5)-MAX(MIN(Solar!E11,SUM('Strategy comparison'!F4:F5)),0))>1000, SUM('Strategy comparison'!F4:F5)-MAX(MIN(Solar!E11,SUM('Strategy comparison'!F4:F5)),0),0) -> 0
G21: Married Filing Joint | J21: LTCG & QD | K21: AGI w Gift | M21: Unmarried/Single | P21: LTCG & QD | Q21: AGI w Gift
J22: =C14 -> 0 | K22: =J22-IF((#REF!*#REF!)>J7, (#REF!*#REF!)-J7,0) -> #REF! | P22: =C13 -> 0 | Q22: =P22-IF((#REF!*#REF!)>P7, (#REF!*#REF!)-P7,0) -> #REF!
G23: ='Tax Tables'!B18 -> 0 | H23: ='Tax Tables'!C18 -> 98900 | I23: ='Tax Tables'!D18 -> 0 | J23: =IF(J$22>$H23,($H23-$G23)*$I23,MAX((J$22-$G23),0)*$I23) -> 0 | K23: =IF(K$22>$H23,($H23-$G23)*$I23,MAX((K$22-$G23),0)*$I23) -> #REF! | M23: ='Tax Tables'!F18 -> 0 | N23: ='Tax Tables'!G18 -> 49450 | O23: ='Tax Tables'!H18 -> 0 | P23: =IF(P$22>$N23,($N23-$M23)*$O23,MAX((P$22-$M23),0)*$O23) -> 0 | Q23: =IF(Q$22>$N23,($N23-$M23)*$O23,MAX((Q$22-$M23),0)*$O23) -> #REF!
G24: ='Tax Tables'!B19 -> 98901 | H24: ='Tax Tables'!C19 -> 613700 | I24: ='Tax Tables'!D19 -> 0.15 | J24: =IF(J$22>$H24,($H24-$G24)*$I24,MAX((J$22-$G24),0)*$I24) -> 0 | K24: =IF(K$22>$H24,($H24-$G24)*$I24,MAX((K$22-$G24),0)*$I24) -> #REF! | M24: ='Tax Tables'!F19 -> 49451 | N24: ='Tax Tables'!G19 -> 545500 | O24: ='Tax Tables'!H19 -> 0.15 | P24: =IF(P$22>$N24,($N24-$M24)*$O24,MAX((P$22-$M24),0)*$O24) -> 0 | Q24: =IF(Q$22>$N24,($N24-$M24)*$O24,MAX((Q$22-$M24),0)*$O24) -> #REF!
G25: ='Tax Tables'!B20 -> 613701 | H25: ='Tax Tables'!C20 -> 99999999999 | I25: ='Tax Tables'!D20 -> 0.2 | J25: =IF(J$22>$H25,($H25-$G25)*$I25,MAX((J$22-$G25),0)*$I25) -> 0 | K25: =IF(K$22>$H25,($H25-$G25)*$I25,MAX((K$22-$G25),0)*$I25) -> #REF! | M25: ='Tax Tables'!F20 -> 545501 | N25: ='Tax Tables'!G20 -> 99999999999 | O25: ='Tax Tables'!H20 -> 0.2 | P25: =IF(P$22>$N25,($N25-$M25)*$O25,MAX((P$22-$M25),0)*$O25) -> 0 | Q25: =IF(Q$22>$N25,($N25-$M25)*$O25,MAX((Q$22-$M25),0)*$O25) -> #REF!
I27: Est. Tax Expense | K27: Difference | O27: Est. Tax Expense | Q27: Difference
I28: =SUM(J23:J25) -> 0 | J28: =SUM(K23:K25) -> #REF! | K28: =I28-J28 -> #REF! | O28: =SUM(P23:P25) -> 0 | P28: =SUM(Q23:Q25) -> #REF! | Q28: =O28-P28 -> #REF!
G30: State Income Tax - Louisiana
G32: Married Filing Joint | J32: AGI | K32: AGI w Depreciation | M32: Unmarried/Single | P32: AGI | Q32: AGI w Depreciation
J33: =C15 -> 400000 | K33: =J33-E15 -> 368605.58 | P33: =J33 -> 400000 | Q33: =P33-E15 -> 368605.58
G34: ='Tax Tables'!B25 -> 0 | H34: ='Tax Tables'!C25 -> 100000000 | I34: ='Tax Tables'!D25 -> 0.03 | J34: =IF(IF(J$33>H34,(H34-G34)*I34,(J$33-G34)*I34)>0,IF(J$33>H34,(H34-G34)*I34,(J$33-G34)*I34),0) -> 12000 | K34: =IF(IF(K$33>H34,(H34-G34)*I34,(K$33-G34)*I34)>0,IF(K$33>H34,(H34-G34)*I34,(K$33-G34)*I34),0) -> 11058.167 | M34: ='Tax Tables'!F25 -> 0 | N34: ='Tax Tables'!G25 -> 100000000 | O34: ='Tax Tables'!H25 -> 0.03 | P34: =IF(IF(P$33>N34,(N34-M34)*O34,(P$33-M34)*O34)>0,IF(P$33>N34,(N34-M34)*O34,(P$33-M34)*O34),0) -> 12000 | Q34: =IF(IF(Q$33>N34,(N34-M34)*O34,(Q$33-M34)*O34)>0,IF(Q$33>N34,(N34-M34)*O34,(Q$33-M34)*O34),0) -> 11058.167
G35: ='Tax Tables'!B26 -> 0 | H35: ='Tax Tables'!C26 -> 0 | I35: ='Tax Tables'!D26 -> 0 | J35: =IF(IF(J$33>H35,(H35-G35)*I35,(J$33-G35)*I35)>0,IF(J$33>H35,(H35-G35)*I35,(J$33-G35)*I35),0) -> 0 | K35: =IF(IF(K$33>H35,(H35-G35)*I35,(K$33-G35)*I35)>0,IF(K$33>H35,(H35-G35)*I35,(K$33-G35)*I35),0) -> 0 | M35: ='Tax Tables'!F26 -> 0 | N35: ='Tax Tables'!G26 -> 0 | O35: ='Tax Tables'!H26 -> 0 | P35: =IF(IF(P$33>N35,(N35-M35)*O35,(P$33-M35)*O35)>0,IF(P$33>N35,(N35-M35)*O35,(P$33-M35)*O35),0) -> 0 | Q35: =IF(IF(Q$33>N35,(N35-M35)*O35,(Q$33-M35)*O35)>0,IF(Q$33>N35,(N35-M35)*O35,(Q$33-M35)*O35),0) -> 0
G36: ='Tax Tables'!B27 -> 0 | H36: ='Tax Tables'!C27 -> 0 | I36: ='Tax Tables'!D27 -> 0 | J36: =IF(IF(J$33>H36,(H36-G36)*I36,(J$33-G36)*I36)>0,IF(J$33>H36,(H36-G36)*I36,(J$33-G36)*I36),0) -> 0 | K36: =IF(IF(K$33>H36,(H36-G36)*I36,(K$33-G36)*I36)>0,IF(K$33>H36,(H36-G36)*I36,(K$33-G36)*I36),0) -> 0 | M36: ='Tax Tables'!F27 -> 0 | N36: ='Tax Tables'!G27 -> 0 | O36: ='Tax Tables'!H27 -> 0 | P36: =IF(IF(P$33>N36,(N36-M36)*O36,(P$33-M36)*O36)>0,IF(P$33>N36,(N36-M36)*O36,(P$33-M36)*O36),0) -> 0 | Q36: =IF(IF(Q$33>N36,(N36-M36)*O36,(Q$33-M36)*O36)>0,IF(Q$33>N36,(N36-M36)*O36,(Q$33-M36)*O36),0) -> 0
G37: ='Tax Tables'!B28 -> 0 | H37: ='Tax Tables'!C28 -> 0 | I37: ='Tax Tables'!D28 -> 0 | J37: =IF(IF(J$33>H37,(H37-G37)*I37,(J$33-G37)*I37)>0,IF(J$33>H37,(H37-G37)*I37,(J$33-G37)*I37),0) -> 0 | K37: =IF(IF(K$33>H37,(H37-G37)*I37,(K$33-G37)*I37)>0,IF(K$33>H37,(H37-G37)*I37,(K$33-G37)*I37),0) -> 0 | M37: ='Tax Tables'!F28 -> 0 | N37: ='Tax Tables'!G28 -> 0 | O37: ='Tax Tables'!H28 -> 0 | P37: =IF(IF(P$33>N37,(N37-M37)*O37,(P$33-M37)*O37)>0,IF(P$33>N37,(N37-M37)*O37,(P$33-M37)*O37),0) -> 0 | Q37: =IF(IF(Q$33>N37,(N37-M37)*O37,(Q$33-M37)*O37)>0,IF(Q$33>N37,(N37-M37)*O37,(Q$33-M37)*O37),0) -> 0
G38: ='Tax Tables'!B29 -> 0 | H38: ='Tax Tables'!C29 -> 0 | I38: ='Tax Tables'!D29 -> 0 | J38: =IF(IF(J$33>H38,(H38-G38)*I38,(J$33-G38)*I38)>0,IF(J$33>H38,(H38-G38)*I38,(J$33-G38)*I38),0) -> 0 | K38: =IF(IF(K$33>H38,(H38-G38)*I38,(K$33-G38)*I38)>0,IF(K$33>H38,(H38-G38)*I38,(K$33-G38)*I38),0) -> 0 | M38: ='Tax Tables'!F29 -> 0 | N38: ='Tax Tables'!G29 -> 0 | O38: ='Tax Tables'!H29 -> 0 | P38: =IF(IF(P$33>N38,(N38-M38)*O38,(P$33-M38)*O38)>0,IF(P$33>N38,(N38-M38)*O38,(P$33-M38)*O38),0) -> 0 | Q38: =IF(IF(Q$33>N38,(N38-M38)*O38,(Q$33-M38)*O38)>0,IF(Q$33>N38,(N38-M38)*O38,(Q$33-M38)*O38),0) -> 0
G39: ='Tax Tables'!B30 -> 0 | H39: ='Tax Tables'!C30 -> 0 | I39: ='Tax Tables'!D30 -> 0 | J39: =IF(J33>=G39,(J33-G39)*I39,0) -> 0 | K39: =IF(K33>=G39,(K33-G39)*I39,0) -> 0 | M39: ='Tax Tables'!F30 -> 0 | N39: ='Tax Tables'!G30 -> 0 | O39: ='Tax Tables'!H30 -> 0 | P39: =IF(P33>=M39,(P33-M39)*O39,0) -> 0 | Q39: =IF(Q33>=M39,(Q33-M39)*O39,0) -> 0
I41: Est. Tax Expense | K41: Difference | O41: Est. Tax Expense | Q41: Difference
I42: =SUM(J34:J39) -> 12000 | J42: =SUM(K34:K39) -> 11058.167 | K42: =I42-J42 -> 941.83258 | O42: =SUM(P34:P39) -> 12000 | P42: =SUM(Q34:Q39) -> 11058.167 | Q42: =O42-P42 -> 941.83258
H44: NIIT | I44: ='Tax Tables'!$C$34 -> 0.038
H45: =SUM(C8:C11)+C13 -> 0 | I45: =IF(C15-IF(C5="Married-Joint",250000,200000)>H45,(C15-IF(C5="Married-Joint",250000,200000))*I44, H45*I44) -> 5700

Sheet Solar & DB
B4: Solar Strategy Inputs | D4: Solar Strategy Details | G4: Federal Ordinary Income Tax
B5: Filing Status - LA | C5: ='Strategy comparison'!C4 -> Married-Joint | D5: Reducible Taxes | E5: =IF(C5="Married-Joint",I17+I28+I45,IF(C5="Single",O17+O28+I45,"Filing Status?")) -> 86895.42
B6: W2 Income | C6: ='Strategy comparison'!C5 -> 400000 | D6: Equity Contribution | E6: =C18 -> 70583.134 | G6: Married Filing Joint | J6: Ordinary Income | K6: Non-LTCG AGI w Gift | M6: Unmarried/Single | P6: Ordinary Income | Q6: Non-LTCG AGI w Gift
B7: Business Income | C7: ='Strategy comparison'!C6-'DB comparison'!C2 -> 0 | D7: Upfront Electric Sale | E7: =E8-E6 -> 125456.99 | J7: =C12 -> 400000 | K7: =J7-MIN(C15*#REF!,J7) -> #REF! | P7: =J7 -> 400000 | Q7: =K7 -> #REF!
B8: ST Capital Gains | C8: ='Strategy comparison'!C7 -> 0 | D8: Project Cost | E8: =C18/C16 -> 196064.26 | G8: ='Tax Tables'!B6 -> 0 | H8: ='Tax Tables'!C6 -> 24800 | I8: ='Tax Tables'!D6 -> 0.1 | J8: =IF(IF(J$7>H8,(H8-G8)*I8,(J$7-G8)*I8)>0,IF(J$7>H8,(H8-G8)*I8,(J$7-G8)*I8),0) -> 2480 | K8: =IF(IF(K$7>H8,(H8-G8)*I8,(K$7-G8)*I8)>0,IF(K$7>H8,(H8-G8)*I8,(K$7-G8)*I8),0) -> #REF! | M8: ='Tax Tables'!F6 -> 0 | N8: ='Tax Tables'!G6 -> 12400 | O8: ='Tax Tables'!H6 -> 0.1 | P8: =IF(IF(P$7>N8,(N8-M8)*O8,(P$7-M8)*O8)>0,IF(P$7>N8,(N8-M8)*O8,(P$7-M8)*O8),0) -> 1240 | Q8: =IF(IF(Q$7>N8,(N8-M8)*O8,(Q$7-M8)*O8)>0,IF(Q$7>N8,(N8-M8)*O8,(Q$7-M8)*O8),0) -> #REF!
B9: Interest | C9: ='Strategy comparison'!$C$9 -> 0 | D9: Fed Credit | E9: =E8*C17 -> 78425.704 | G9: ='Tax Tables'!B7 -> 24801 | H9: ='Tax Tables'!C7 -> 100800 | I9: ='Tax Tables'!D7 -> 0.12 | J9: =IF(IF(J$7>H9,(H9-G9)*I9,(J$7-G9)*I9)>0,IF(J$7>H9,(H9-G9)*I9,(J$7-G9)*I9),0) -> 9119.88 | K9: =IF(IF(K$7>H9,(H9-G9)*I9,(K$7-G9)*I9)>0,IF(K$7>H9,(H9-G9)*I9,(K$7-G9)*I9),0) -> #REF! | M9: ='Tax Tables'!F7 -> 12401 | N9: ='Tax Tables'!G7 -> 50400 | O9: ='Tax Tables'!H7 -> 0.12 | P9: =IF(IF(P$7>N9,(N9-M9)*O9,(P$7-M9)*O9)>0,IF(P$7>N9,(N9-M9)*O9,(P$7-M9)*O9),0) -> 4559.88 | Q9: =IF(IF(Q$7>N9,(N9-M9)*O9,(Q$7-M9)*O9)>0,IF(Q$7>N9,(N9-M9)*O9,(Q$7-M9)*O9),0) -> #REF!
B10: Qualified Dividends | C10: ='Strategy comparison'!$C$10 -> 0 | D10: Depreciation Benefit Yr 1 | E10: =E16 -> 7522.1477 | G10: ='Tax Tables'!B8 -> 100801 | H10: ='Tax Tables'!C8 -> 211400 | I10: ='Tax Tables'!D8 -> 0.22 | J10: =IF(IF(J$7>H10,(H10-G10)*I10,(J$7-G10)*I10)>0,IF(J$7>H10,(H10-G10)*I10,(J$7-G10)*I10),0) -> 24331.78 | K10: =IF(IF(K$7>H10,(H10-G10)*I10,(K$7-G10)*I10)>0,IF(K$7>H10,(H10-G10)*I10,(K$7-G10)*I10),0) -> #REF! | M10: ='Tax Tables'!F8 -> 50401 | N10: ='Tax Tables'!G8 -> 105700 | O10: ='Tax Tables'!H8 -> 0.22 | P10: =IF(IF(P$7>N10,(N10-M10)*O10,(P$7-M10)*O10)>0,IF(P$7>N10,(N10-M10)*O10,(P$7-M10)*O10),0) -> 12165.78 | Q10: =IF(IF(Q$7>N10,(N10-M10)*O10,(Q$7-M10)*O10)>0,IF(Q$7>N10,(N10-M10)*O10,(Q$7-M10)*O10),0) -> #REF!
B11: Nonqualified Dividends | C11: ='Strategy comparison'!$C$11 -> 0 | D11: Solar Tax Benefit Yr 1 | E11: =SUM(E9:E10)+K42 -> 86888.121 | G11: ='Tax Tables'!B9 -> 211401 | H11: ='Tax Tables'!C9 -> 403550 | I11: ='Tax Tables'!D9 -> 0.24 | J11: =IF(IF(J$7>H11,(H11-G11)*I11,(J$7-G11)*I11)>0,IF(J$7>H11,(H11-G11)*I11,(J$7-G11)*I11),0) -> 45263.76 | K11: =IF(IF(K$7>H11,(H11-G11)*I11,(K$7-G11)*I11)>0,IF(K$7>H11,(H11-G11)*I11,(K$7-G11)*I11),0) -> #REF! | M11: ='Tax Tables'!F9 -> 105701 | N11: ='Tax Tables'!G9 -> 201775 | O11: ='Tax Tables'!H9 -> 0.24 | P11: =IF(IF(P$7>N11,(N11-M11)*O11,(P$7-M11)*O11)>0,IF(P$7>N11,(N11-M11)*O11,(P$7-M11)*O11),0) -> 23057.76 | Q11: =IF(IF(Q$7>N11,(N11-M11)*O11,(Q$7-M11)*O11)>0,IF(Q$7>N11,(N11-M11)*O11,(Q$7-M11)*O11),0) -> #REF!
B12: Ordinary Income | C12: =SUM(C6:C9)+C11 -> 400000 | D12: Solar Tax Net Savings | E12: =E11-C18-'Strategy comparison'!C12 -> 16304.987 | G12: ='Tax Tables'!B10 -> 403551 | H12: ='Tax Tables'!C10 -> 512450 | I12: ='Tax Tables'!D10 -> 0.32 | J12: =IF(IF(J$7>H12,(H12-G12)*I12,(J$7-G12)*I12)>0,IF(J$7>H12,(H12-G12)*I12,(J$7-G12)*I12),0) -> 0 | K12: =IF(IF(K$7>H12,(H12-G12)*I12,(K$7-G12)*I12)>0,IF(K$7>H12,(H12-G12)*I12,(K$7-G12)*I12),0) -> #REF! | M12: ='Tax Tables'!F10 -> 201776 | N12: ='Tax Tables'!G10 -> 256225 | O12: ='Tax Tables'!H10 -> 0.32 | P12: =IF(IF(P$7>N12,(N12-M12)*O12,(P$7-M12)*O12)>0,IF(P$7>N12,(N12-M12)*O12,(P$7-M12)*O12),0) -> 17423.68 | Q12: =IF(IF(Q$7>N12,(N12-M12)*O12,(Q$7-M12)*O12)>0,IF(Q$7>N12,(N12-M12)*O12,(Q$7-M12)*O12),0) -> #REF!
B13: LTCG | C13: ='Strategy comparison'!C8 -> 0 | D13: Depreciable Basis | E13: =E8-(E9/2) -> 156851.41 | G13: ='Tax Tables'!B11 -> 512451 | H13: ='Tax Tables'!C11 -> 768700 | I13: ='Tax Tables'!D11 -> 0.35 | J13: =IF(IF(J$7>H13,(H13-G13)*I13,(J$7-G13)*I13)>0,IF(J$7>H13,(H13-G13)*I13,(J$7-G13)*I13),0) -> 0 | K13: =IF(IF(K$7>H13,(H13-G13)*I13,(K$7-G13)*I13)>0,IF(K$7>H13,(H13-G13)*I13,(K$7-G13)*I13),0) -> #REF! | M13: ='Tax Tables'!F11 -> 256226 | N13: ='Tax Tables'!G11 -> 640600 | O13: ='Tax Tables'!H11 -> 0.35 | P13: =IF(IF(P$7>N13,(N13-M13)*O13,(P$7-M13)*O13)>0,IF(P$7>N13,(N13-M13)*O13,(P$7-M13)*O13),0) -> 50320.9 | Q13: =IF(IF(Q$7>N13,(N13-M13)*O13,(Q$7-M13)*O13)>0,IF(Q$7>N13,(N13-M13)*O13,(Q$7-M13)*O13),0) -> #REF!
B14: LTCG & Qualified Dividends | C14: =C13+C10 -> 0 | D14: Upfront Electric Sale | E14: =E7 -> 125456.99 | G14: ='Tax Tables'!B12 -> 768701 | H14: ='Tax Tables'!C12 -> 99999999999 | I14: ='Tax Tables'!D12 -> 0.37 | J14: =IF(J7>=G14,(J7-G14)*I14,0) -> 0 | K14: =IF(K7>=G14,(K7-G14)*I14,0) -> #REF! | M14: ='Tax Tables'!F12 -> 640601 | N14: ='Tax Tables'!G12 -> 99999999999 | O14: ='Tax Tables'!H12 -> 0.37 | P14: =IF(P7>=M14,(P7-M14)*O14,0) -> 0 | Q14: =IF(Q7>=M14,(Q7-M14)*O14,0) -> #REF!
B15: AGI | C15: =C12+C14 -> 400000 | D15: Net Depreciation Yr 1 | E15: =E13-E14 -> 31394.419
B16: % Equity Contribution | C16: 0.36 | D16: Depreciation Benefit Yr 1 | E16: =IF($C$5="Married-Joint", I17-((MAX(0,MIN(J7-E15,H8)-G8)*I8) +(MAX(0,MIN(J7-E15,H9)-G9)*I9) +(MAX(0,MIN(J7-E15,H10)-G10)*I10) +(MAX(0,MIN(J7-E15,H11)-G11)*I11) +(MAX(0,MIN(J7-E15,H12)-G12)*I12) +(MAX(0,MIN(J7-E15,H13)-G13)*I13) +(MAX(0,MIN(J7-E15,H14)-G14)*I14)), O17-((MAX(0,MIN(P7-E15,N8)-M8)*O8) +(MAX(0,MIN(P7-E15,N9)-M9)*O9) +(MAX(0,MIN(P7-E15,N10)-M10)*O10) +(MAX(0,MIN(P7-E15,N11)-M11)*O11) +(MAX(0,MIN(P7-E15,N12)-M12)*O12) +(MAX(0,MIN(P7-E15,N13)-M13)*O13) +(MAX(0,MIN(P7-E15,N14)-M14)*O14)) ) -> 7534.6607 | I16: Est. Tax Expense | K16: Difference | O16: Est. Tax Expense | Q16: Difference
B17: % Fed Credit | C17: 0.4 | I17: =SUM(J8:J14) -> 81195.42 | J17: =SUM(K8:K14) -> #REF! | K17: =I17-J17 -> #REF! | O17: =SUM(P8:P14) -> 108768 | P17: =SUM(Q8:Q14) -> #REF! | Q17: =O17-P17 -> #REF!
B18: Equity Contribution Input | C18: =IF('DB comparison'!H5="",IF(E11>E5,IF(ABS(E5-E11)>10000,C18-(0.01*E5),C18-(0.0001*E5)),IF(ABS(E5-E11)>10000,C18+(0.01*E5),C18+(0.0001*E5))),'DB comparison'!H5) -> 70591.824
G19: Long Term Capital Gains & Qualified Dividends Tax
B20: Fed Taxes Remaining | C20: =IF(ABS(SUM('DB comparison'!F26:F27)-MAX(MIN('Solar & DB'!E11,SUM('DB comparison'!F26:F27)),0))>1000, SUM('DB comparison'!F26:F27)-MAX(MIN('Solar & DB'!E11,SUM('DB comparison'!F26:F27)),0),0) -> 0
G21: Married Filing Joint | J21: LTCG & QD | K21: AGI w Gift | M21: Unmarried/Single | P21: LTCG & QD | Q21: AGI w Gift
J22: =C14 -> 0 | K22: =J22-IF((#REF!*#REF!)>J7, (#REF!*#REF!)-J7,0) -> #REF! | P22: =C13 -> 0 | Q22: =P22-IF((#REF!*#REF!)>P7, (#REF!*#REF!)-P7,0) -> #REF!
G23: ='Tax Tables'!B18 -> 0 | H23: ='Tax Tables'!C18 -> 98900 | I23: ='Tax Tables'!D18 -> 0 | J23: =IF(J$22>$H23,($H23-$G23)*$I23,MAX((J$22-$G23),0)*$I23) -> 0 | K23: =IF(K$22>$H23,($H23-$G23)*$I23,MAX((K$22-$G23),0)*$I23) -> #REF! | M23: ='Tax Tables'!F18 -> 0 | N23: ='Tax Tables'!G18 -> 49450 | O23: ='Tax Tables'!H18 -> 0 | P23: =IF(P$22>$N23,($N23-$M23)*$O23,MAX((P$22-$M23),0)*$O23) -> 0 | Q23: =IF(Q$22>$N23,($N23-$M23)*$O23,MAX((Q$22-$M23),0)*$O23) -> #REF!
G24: ='Tax Tables'!B19 -> 98901 | H24: ='Tax Tables'!C19 -> 613700 | I24: ='Tax Tables'!D19 -> 0.15 | J24: =IF(J$22>$H24,($H24-$G24)*$I24,MAX((J$22-$G24),0)*$I24) -> 0 | K24: =IF(K$22>$H24,($H24-$G24)*$I24,MAX((K$22-$G24),0)*$I24) -> #REF! | M24: ='Tax Tables'!F19 -> 49451 | N24: ='Tax Tables'!G19 -> 545500 | O24: ='Tax Tables'!H19 -> 0.15 | P24: =IF(P$22>$N24,($N24-$M24)*$O24,MAX((P$22-$M24),0)*$O24) -> 0 | Q24: =IF(Q$22>$N24,($N24-$M24)*$O24,MAX((Q$22-$M24),0)*$O24) -> #REF!
G25: ='Tax Tables'!B20 -> 613701 | H25: ='Tax Tables'!C20 -> 99999999999 | I25: ='Tax Tables'!D20 -> 0.2 | J25: =IF(J$22>$H25,($H25-$G25)*$I25,MAX((J$22-$G25),0)*$I25) -> 0 | K25: =IF(K$22>$H25,($H25-$G25)*$I25,MAX((K$22-$G25),0)*$I25) -> #REF! | M25: ='Tax Tables'!F20 -> 545501 | N25: ='Tax Tables'!G20 -> 99999999999 | O25: ='Tax Tables'!H20 -> 0.2 | P25: =IF(P$22>$N25,($N25-$M25)*$O25,MAX((P$22-$M25),0)*$O25) -> 0 | Q25: =IF(Q$22>$N25,($N25-$M25)*$O25,MAX((Q$22-$M25),0)*$O25) -> #REF!
I27: Est. Tax Expense | K27: Difference | O27: Est. Tax Expense | Q27: Difference
I28: =SUM(J23:J25) -> 0 | J28: =SUM(K23:K25) -> #REF! | K28: =I28-J28 -> #REF! | O28: =SUM(P23:P25) -> 0 | P28: =SUM(Q23:Q25) -> #REF! | Q28: =O28-P28 -> #REF!
G30: State Income Tax - Louisiana
G32: Married Filing Joint | J32: AGI | K32: AGI w Depreciation | M32: Unmarried/Single | P32: AGI | Q32: AGI w Depreciation
J33: =C15 -> 400000 | K33: =J33-E15 -> 368605.58 | P33: =J33 -> 400000 | Q33: =P33-E15 -> 368605.58
G34: ='Tax Tables'!B25 -> 0 | H34: ='Tax Tables'!C25 -> 100000000 | I34: ='Tax Tables'!D25 -> 0.03 | J34: =IF(IF(J$33>H34,(H34-G34)*I34,(J$33-G34)*I34)>0,IF(J$33>H34,(H34-G34)*I34,(J$33-G34)*I34),0) -> 12000 | K34: =IF(IF(K$33>H34,(H34-G34)*I34,(K$33-G34)*I34)>0,IF(K$33>H34,(H34-G34)*I34,(K$33-G34)*I34),0) -> 11058.167 | M34: ='Tax Tables'!F25 -> 0 | N34: ='Tax Tables'!G25 -> 100000000 | O34: ='Tax Tables'!H25 -> 0.03 | P34: =IF(IF(P$33>N34,(N34-M34)*O34,(P$33-M34)*O34)>0,IF(P$33>N34,(N34-M34)*O34,(P$33-M34)*O34),0) -> 12000 | Q34: =IF(IF(Q$33>N34,(N34-M34)*O34,(Q$33-M34)*O34)>0,IF(Q$33>N34,(N34-M34)*O34,(Q$33-M34)*O34),0) -> 11058.167
G35: ='Tax Tables'!B26 -> 0 | H35: ='Tax Tables'!C26 -> 0 | I35: ='Tax Tables'!D26 -> 0 | J35: =IF(IF(J$33>H35,(H35-G35)*I35,(J$33-G35)*I35)>0,IF(J$33>H35,(H35-G35)*I35,(J$33-G35)*I35),0) -> 0 | K35: =IF(IF(K$33>H35,(H35-G35)*I35,(K$33-G35)*I35)>0,IF(K$33>H35,(H35-G35)*I35,(K$33-G35)*I35),0) -> 0 | M35: ='Tax Tables'!F26 -> 0 | N35: ='Tax Tables'!G26 -> 0 | O35: ='Tax Tables'!H26 -> 0 | P35: =IF(IF(P$33>N35,(N35-M35)*O35,(P$33-M35)*O35)>0,IF(P$33>N35,(N35-M35)*O35,(P$33-M35)*O35),0) -> 0 | Q35: =IF(IF(Q$33>N35,(N35-M35)*O35,(Q$33-M35)*O35)>0,IF(Q$33>N35,(N35-M35)*O35,(Q$33-M35)*O35),0) -> 0
G36: ='Tax Tables'!B27 -> 0 | H36: ='Tax Tables'!C27 -> 0 | I36: ='Tax Tables'!D27 -> 0 | J36: =IF(IF(J$33>H36,(H36-G36)*I36,(J$33-G36)*I36)>0,IF(J$33>H36,(H36-G36)*I36,(J$33-G36)*I36),0) -> 0 | K36: =IF(IF(K$33>H36,(H36-G36)*I36,(K$33-G36)*I36)>0,IF(K$33>H36,(H36-G36)*I36,(K$33-G36)*I36),0) -> 0 | M36: ='Tax Tables'!F27 -> 0 | N36: ='Tax Tables'!G27 -> 0 | O36: ='Tax Tables'!H27 -> 0 | P36: =IF(IF(P$33>N36,(N36-M36)*O36,(P$33-M36)*O36)>0,IF(P$33>N36,(N36-M36)*O36,(P$33-M36)*O36),0) -> 0 | Q36: =IF(IF(Q$33>N36,(N36-M36)*O36,(Q$33-M36)*O36)>0,IF(Q$33>N36,(N36-M36)*O36,(Q$33-M36)*O36),0) -> 0
G37: ='Tax Tables'!B28 -> 0 | H37: ='Tax Tables'!C28 -> 0 | I37: ='Tax Tables'!D28 -> 0 | J37: =IF(IF(J$33>H37,(H37-G37)*I37,(J$33-G37)*I37)>0,IF(J$33>H37,(H37-G37)*I37,(J$33-G37)*I37),0) -> 0 | K37: =IF(IF(K$33>H37,(H37-G37)*I37,(K$33-G37)*I37)>0,IF(K$33>H37,(H37-G37)*I37,(K$33-G37)*I37),0) -> 0 | M37: ='Tax Tables'!F28 -> 0 | N37: ='Tax Tables'!G28 -> 0 | O37: ='Tax Tables'!H28 -> 0 | P37: =IF(IF(P$33>N37,(N37-M37)*O37,(P$33-M37)*O37)>0,IF(P$33>N37,(N37-M37)*O37,(P$33-M37)*O37),0) -> 0 | Q37: =IF(IF(Q$33>N37,(N37-M37)*O37,(Q$33-M37)*O37)>0,IF(Q$33>N37,(N37-M37)*O37,(Q$33-M37)*O37),0) -> 0
